Workbook
Name OLE_LINK1: '1.2'!#REF!
Name OLE_LINK1_1: '1.6'!#REF!

Sheet Bilan
P1: Fichier publié le 19/08/2021
C4: QCM CONCEPTEUR "C" | F4: QCM ENCADRANT "E" | I4: QCM OPERATEUR "O" | L4: Nombre Questions | P4: Légendes :
C5: Nb | D5: Prio. | E5: Illust. | F5: Nb | G5: Prio. | H5: Illust. | I5: Nb | J5: Prio. | K5: Illust. | L5: Nb | M5: Prio. | N5: Illust. | P5: QCM illustré (1) | T5: I
B6: 1. Responsable de projet avant les chantiers | P6: QCM dit "prioritaire" | T6: P
B7: 1.1 DT | C7: ='1.1'!C$4 -> 17 | D7: ='1.1'!C$6 -> 3 | E7: ='1.1'!C$5 -> 2 | F7: ='1.1'!D$4 -> 11 | G7: ='1.1'!D$6 -> 2 | H7: ='1.1'!D$5 -> 2 | I7: ='1.1'!E$4 -> 0 | J7: ='1.1'!E$6 -> 0 | K7: ='1.1'!E$5 -> 0 | L7: ='1.1'!F$4 -> 17 | M7: ='1.1'!F$6 -> 3 | N7: ='1.1'!F$5 -> 2 | P7: QCM du "tronc commun Opérateur" | T7: TC OPERATEUR
B8: 1.2 Analyse des réponses - IC - Cartographie | C8: ='1.2'!C$4 -> 16 | D8: ='1.2'!C$6 -> 1 | E8: ='1.2'!C$5 -> 2 | F8: ='1.2'!D$4 -> 9 | G8: ='1.2'!D$6 -> 0 | H8: ='1.2'!D$5 -> 2 | I8: ='1.2'!E$4 -> 2 | J8: ='1.2'!E$6 -> 0 | K8: ='1.2'!E$5 -> 2 | L8: ='1.2'!F$4 -> 16 | M8: ='1.2'!F$6 -> 1 | N8: ='1.2'!F$5 -> 2 | P8: Référerences réglementaires du QCM | T8: R554-25
B9: 1.3 Clauses dans les marchés et DCE | C9: ='1.3'!C$4 -> 4 | D9: ='1.3'!C$6 -> 0 | E9: ='1.3'!C$5 -> 0 | F9: ='1.3'!D$4 -> 2 | G9: ='1.3'!D$6 -> 0 | H9: ='1.3'!D$5 -> 0 | I9: ='1.3'!E$4 -> 0 | J9: ='1.3'!E$6 -> 0 | K9: ='1.3'!E$5 -> 0 | L9: ='1.3'!F$4 -> 4 | M9: ='1.3'!F$6 -> 0 | N9: ='1.3'!F$5 -> 0
B10: 1.4 Marquage - Piquetage | C10: ='1.4'!C$4 -> 7 | D10: ='1.4'!C$6 -> 1 | E10: ='1.4'!C$5 -> 3 | F10: ='1.4'!D$4 -> 7 | G10: ='1.4'!D$6 -> 1 | H10: ='1.4'!D$5 -> 3 | I10: ='1.4'!E$4 -> 4 | J10: ='1.4'!E$6 -> 0 | K10: ='1.4'!E$5 -> 4 | L10: ='1.4'!F$4 -> 8 | M10: ='1.4'!F$6 -> 1 | N10: ='1.4'!F$5 -> 4 | P10: (1) Toutes les illustrations sont dans le fichier ZIP joint
B11: 1.5 Compétences des personnels | C11: ='1.5'!C$4 -> 2 | D11: ='1.5'!C$6 -> 0 | E11: ='1.5'!C$5 -> 0 | F11: ='1.5'!D$4 -> 0 | G11: ='1.5'!D$6 -> 0 | H11: ='1.5'!D$5 -> 0 | I11: ='1.5'!E$4 -> 0 | J11: ='1.5'!E$6 -> 0 | K11: ='1.5'!E$5 -> 0 | L11: ='1.5'!F$4 -> 2 | M11: ='1.5'!F$6 -> 0 | N11: ='1.5'!F$5 -> 0 | P11: Nota important : parmi les 250 QCM de ce fichier, 103 ont fait l'objet d'une modification ou ont été ajoutée. Elle sont publiées pour information sur le site du GU le 19/08/2021
B12: 1.6 Cartographie | C12: ='1.6'!C$4 -> 8 | D12: ='1.6'!C$6 -> 1 | E12: ='1.6'!C$5 -> 1 | F12: ='1.6'!D$4 -> 8 | G12: ='1.6'!D$6 -> 1 | H12: ='1.6'!D$5 -> 1 | I12: ='1.6'!E$4 -> 1 | J12: ='1.6'!E$6 -> 0 | K12: ='1.6'!E$5 -> 1 | L12: ='1.6'!F$4 -> 9 | M12: ='1.6'!F$6 -> 1 | N12: ='1.6'!F$5 -> 2 | P12: en application du V de l'article 3 Arrêté du 22 décembre 2015 relatif au contrôle des compétences des personnes intervenant dans les travaux à proximité des réseaux
B13: 2. Exécutants avant les chantiers | P13: et seront suceptibles de figurer à l'examen à complter du 19 novembre 2021
B14: 2.1 DICT | C14: ='2.1'!C$4 -> 3 | D14: ='2.1'!C$6 -> 1 | E14: ='2.1'!C$5 -> 0 | F14: ='2.1'!D$4 -> 3 | G14: ='2.1'!D$6 -> 1 | H14: ='2.1'!D$5 -> 0 | I14: ='2.1'!E$4 -> 0 | J14: ='2.1'!E$6 -> 0 | K14: ='2.1'!E$5 -> 0 | L14: ='2.1'!F$4 -> 3 | M14: ='2.1'!F$6 -> 1 | N14: ='2.1'!F$5 -> 0 | P14: 1-1_007 | Q14: 1-5_011 | R14: 2-4_014 | S14: 2-5_026 | T14: 3-2_017o | U14: 3-3_051
B15: 2.2 Analyse des réponses, du DCE et du marché | C15: ='2.2'!C$4 -> 18 | D15: ='2.2'!C$6 -> 3 | E15: ='2.2'!C$5 -> 4 | F15: ='2.2'!D$4 -> 17 | G15: ='2.2'!D$6 -> 3 | H15: ='2.2'!D$5 -> 4 | I15: ='2.2'!E$4 -> 0 | J15: ='2.2'!E$6 -> 0 | K15: ='2.2'!E$5 -> 0 | L15: ='2.2'!F$4 -> 18 | M15: ='2.2'!F$6 -> 3 | N15: ='2.2'!F$5 -> 4 | P15: 1-1_012 | Q15: 1-6_011 | R15: 2-4_019o | S15: 2-5_031 | T15: 3-2_028 | U15: 3-3_052
B16: 2.3 Compétences des personnels | C16: ='2.3'!C$4 -> 5 | D16: ='2.3'!C$6 -> 1 | E16: ='2.3'!C$5 -> 3 | F16: ='2.3'!D$4 -> 16 | G16: ='2.3'!D$6 -> 4 | H16: ='2.3'!D$5 -> 14 | I16: ='2.3'!E$4 -> 14 | J16: ='2.3'!E$6 -> 1 | K16: ='2.3'!E$5 -> 14 | L16: ='2.3'!F$4 -> 18 | M16: ='2.3'!F$6 -> 4 | N16: ='2.3'!F$5 -> 16 | P16: 1-1_013 | Q16: 1-6_016ce | R16: 2-4_019ce | S16: 2-5_032 | T16: 3-2_029 | U16: 3-3_053
B17: 2.4 Application du guide technique | C17: ='2.4'!C$4 -> 23 | D17: ='2.4'!C$6 -> 3 | E17: ='2.4'!C$5 -> 12 | F17: ='2.4'!D$4 -> 28 | G17: ='2.4'!D$6 -> 4 | H17: ='2.4'!D$5 -> 16 | I17: ='2.4'!E$4 -> 23 | J17: ='2.4'!E$6 -> 2 | K17: ='2.4'!E$5 -> 19 | L17: ='2.4'!F$4 -> 38 | M17: ='2.4'!F$6 -> 5 | N17: ='2.4'!F$5 -> 26 | P17: 1-1_015 | Q17: 1-6_018 | R17: 2-4_033 | S17: 2-5_033 | T17: 3-3_007
B18: 2.5 Lecture des indices et affleurants | C18: ='2.5'!C$4 -> 21 | D18: ='2.5'!C$6 -> 1 | E18: ='2.5'!C$5 -> 19 | F18: ='2.5'!D$4 -> 25 | G18: ='2.5'!D$6 -> 1 | H18: ='2.5'!D$5 -> 23 | I18: ='2.5'!E$4 -> 24 | J18: ='2.5'!E$6 -> 0 | K18: ='2.5'!E$5 -> 24 | L18: ='2.5'!F$4 -> 28 | M18: ='2.5'!F$6 -> 1 | N18: ='2.5'!F$5 -> 26 | P18: 1-1_016 | Q18: 2-1_005 | R18: 2-4_036 | S18: 3-1_010 | T18: 3-3_008
B19: 2.6 Travaux sans tranchée | C19: ='2.6'!C$4 -> 1 | D19: ='2.6'!C$6 -> 0 | E19: ='2.6'!C$5 -> 1 | F19: ='2.6'!D$4 -> 1 | G19: ='2.6'!D$6 -> 0 | H19: ='2.6'!D$5 -> 1 | I19: ='2.6'!E$4 -> 1 | J19: ='2.6'!E$6 -> 0 | K19: ='2.6'!E$5 -> 1 | L19: ='2.6'!F$4 -> 1 | M19: ='2.6'!F$6 -> 0 | N19: ='2.6'!F$5 -> 1 | P19: 1-1_031 | Q19: 2-2_007 | R19: 2-4_038 | S19: 3-1_011 | T19: 3-3_009
B20: 3. Au cours du chantier | P20: 1-1_032 | Q20: 2-2_008 | R20: 2-4_042 | S20: 3-1_011e | T20: 3-3_011
B21: 3.1 Constat d'arrêt ou de sursis | C21: ='3.1'!C$4 -> 3 | D21: ='3.1'!C$6 -> 1 | E21: ='3.1'!C$5 -> 1 | F21: ='3.1'!D$4 -> 7 | G21: ='3.1'!D$6 -> 1 | H21: ='3.1'!D$5 -> 5 | I21: ='3.1'!E$4 -> 11 | J21: ='3.1'!E$6 -> 1 | K21: ='3.1'!E$5 -> 11 | L21: ='3.1'!F$4 -> 18 | M21: ='3.1'!F$6 -> 2 | N21: ='3.1'!F$5 -> 16 | P21: 1-1_033 | Q21: 2-2_009 | R21: 2-4_043 | S21: 3-1_012 | T21: 3-3_015
B22: 3.2 Constat de dommage | C22: ='3.2'!C$4 -> 7 | D22: ='3.2'!C$6 -> 2 | E22: ='3.2'!C$5 -> 4 | F22: ='3.2'!D$4 -> 14 | G22: ='3.2'!D$6 -> 3 | H22: ='3.2'!D$5 -> 9 | I22: ='3.2'!E$4 -> 15 | J22: ='3.2'!E$6 -> 2 | K22: ='3.2'!E$5 -> 15 | L22: ='3.2'!F$4 -> 24 | M22: ='3.2'!F$6 -> 4 | N22: ='3.2'!F$5 -> 19 | P22: 1-2_003 | Q22: 2-2_014 | R22: 2-4_044 | S22: 3-1_013 | T22: 3-3_017
B23: 3.3 Opérations sur chantier | C23: ='3.3'!C$4 -> 20 | D23: ='3.3'!C$6 -> 1 | E23: ='3.3'!C$5 -> 16 | F23: ='3.3'!D$4 -> 34 | G23: ='3.3'!D$6 -> 1 | H23: ='3.3'!D$5 -> 28 | I23: ='3.3'!E$4 -> 36 | J23: ='3.3'!E$6 -> 0 | K23: ='3.3'!E$5 -> 35 | L23: ='3.3'!F$4 -> 46 | M23: ='3.3'!F$6 -> 1 | N23: ='3.3'!F$5 -> 39 | P23: 1-2_004 | Q23: 2-2_015 | R23: 2-4_045 | S23: 3-1_014o | T23: 3-3_033
B24: TOTAL | C24: =SUM(C7:C23) -> 155 | D24: =SUM(D7:D23) -> 19 | E24: =SUM(E7:E23) -> 68 | F24: =SUM(F7:F23) -> 182 | G24: =SUM(G7:G23) -> 22 | H24: =SUM(H7:H23) -> 108 | I24: =SUM(I7:I23) -> 131 | J24: =SUM(J7:J23) -> 6 | ... N24: =SUM(N7:N23) -> 157 | P24: 1-2_006 | Q24: 2-3_018 | R24: 2-4_046 | S24: 3-1_014e | T24: 3-3_041
P25: 1-2_007 | Q25: 2-3_020 | R25: 2-4_047 | S25: 3-1_015 | T25: 3-3_042
P26: 1-2_009 | Q26: 2-3_016 | R26: 2-4_048 | S26: 3-1_016 | T26: 3-3_043
P27: 1-2_023 | Q27: 2-3_028 | R27: 2-5_005 | S27: 3-1_017 | T27: 3-3_044
P28: 1-3_011 | Q28: 2-3_029 | R28: 2-5_008 | S28: 3-1_018 | T28: 3-3_045
P29: 1-3_012 | Q29: 2-4_004 | R29: 2-5_009 | S29: 3-1_019 | T29: 3-3_046
P30: 1-4_004 | Q30: 2-4_007 | R30: 2-5_010 | S30: 3-1_020 | T30: 3-3_047
P31: 1-4_008 | Q31: 2-4_008 | R31: 2-5_011 | S31: 3-2_014e | T31: 3-3_048
P32: 1-5_001 | Q32: 2-4_011 | R32: 2-5_012 | S32: 3-2_014 | T32: 3-3_049
P33: 1-5_002 | Q33: 2-4_012 | R33: 2-5_013 | S33: 3-2_017e | T33: 3-3_050

Sheet 1.1
A1: =Bilan!B7 -> 1.1 DT
C3: C | D3: E | E3: O | F3: Total
B4: Nb quest. | C4: =COUNTIF(C8:C660,C3) -> 17 | D4: =COUNTIF(D8:D660,D3) -> 11 | E4: =COUNTIF(E8:E660,E3) -> 0 | F4: =COUNTA(B8:B660) -> 17
B5: Illust. | C5: =COUNTIF(C8:C660,"i")+COUNTIF(C8:C660,"p i") -> 2 | D5: =COUNTIF(D8:D660,"i")+COUNTIF(D8:D660,"p i") -> 2 | E5: =COUNTIF(E8:E660,"i")+COUNTIF(E8:E660,"p i") -> 0 | F5: =COUNTIF(A8:A660,"I") -> 2
B6: Prio | C6: =COUNTIF(C8:C660,"p")+COUNTIF(C8:C660,"p i") -> 3 | D6: =COUNTIF(D8:D660,"p")+COUNTIF(D8:D660,"p i") -> 2 | E6: =COUNTIF(E8:E660,"p")+COUNTIF(E8:E660,"p i") -> 0 | F6: =COUNTIF(A8:A660,"P") -> 3
B8: 1-1_001 | C8: C | F8: Si je ne prévois pas de clause particulière dans le marché de travaux, je devrai renouveler la DT au bout de :
C9: =IF(C8="C",IF(A9="P",IF(A8="I","p i","p"),IF(A8="I","i","")),"") | D9: =IF(D8="E",IF(A9="P",IF(A8="I","p i","p"),IF(A8="I","i"," ")),"") | E9: =IF(E8="O",IF(A9="P",IF(A8="I","p i","p"),IF(A8="I","i"," ")),"") | F9: A | G9: 1 mois
A10: R554-33I | F10: B | G10: 3 mois
F11: C | G11: 6 mois
F12: D | G12: Je ne sais pas
B14: 1-1_002 | C14: C | D14: E | F14: Qui doit établir la DT ?
A15: P | C15: =IF(C14="C",IF(A15="P",IF(A14="I","p i","p"),IF(A14="I","i","")),"") -> p | D15: =IF(D14="E",IF(A15="P",IF(A14="I","p i","p"),IF(A14="I","i"," ")),"") -> p | E15: =IF(E14="O",IF(A15="P",IF(A14="I","p i","p"),IF(A14="I","i"," ")),"") | F15: A | G15: Le responsable de projet
A16: R554-21 | F16: B | G16: L’exécutant des travaux
F17: C | G17: L’exploitant de réseau
F18: D | G18: Je ne sais pas
B20: 1-1_003 | C20: C | D20: E | F20: Qui doit envoyer la DT aux exploitants des réseaux concernés ?
C21: =IF(C20="C",IF(A21="P",IF(A20="I","p i","p"),IF(A20="I","i","")),"") | D21: =IF(D20="E",IF(A21="P",IF(A20="I","p i","p"),IF(A20="I","i"," ")),"") | E21: =IF(E20="O",IF(A21="P",IF(A20="I","p i","p"),IF(A20="I","i"," ")),"") | F21: A | G21: Le guichet unique
A22: R554-21 | F22: B | G22: Le responsable de projet
F23: C | G23: Le responsable de l'entreprise exécutant les travaux
F24: D | G24: Je ne sais pas
B26: 1-1_005 | C26: C | F26: Le responsable de projet doit inclure obligatoirement dans le dossier de consultation des entreprises :
A27: P | C27: =IF(C26="C",IF(A27="P",IF(A26="I","p i","p"),IF(A26="I","i","")),"") -> p | D27: =IF(D26="E",IF(A27="P",IF(A26="I","p i","p"),IF(A26="I","i"," ")),"") | E27: =IF(E26="O",IF(A27="P",IF(A26="I","p i","p"),IF(A26="I","i"," ")),"") | F27: A | G27: Le plan de récolement
A28: R554-23I | F28: B | G28: Les DT et leurs récépissés, ainsi que le résultat des investigations complémentaires éventuellement réalisées
F29: C | G29: Les DICT et leurs récépissés
F30: D | G30: Je ne sais pas
B32: 1-1_006 | C32: C | D32: E | F32: Parmi les travaux suivants, quels sont ceux qui répondent à la définition de "Travaux Urgents" ?
C33: =IF(C32="C",IF(A33="P",IF(A32="I","p i","p"),IF(A32="I","i","")),"") | D33: =IF(D32="E",IF(A33="P",IF(A32="I","p i","p"),IF(A32="I","i"," ")),"") | E33: =IF(E32="O",IF(A33="P",IF(A32="I","p i","p"),IF(A32="I","i"," ")),"") | F33: A | G33: Les travaux de rétablissement d'un service public après une coupure accidentelle
A34: R554-32 | F34: B | G34: Les travaux de raccordement d’une nouvelle habitation
F35: C | G35: La pose de mobiliers urbains pour une manifestation
F36: D | G36: Je ne sais pas
B38: 1-1_007 | C38: C | D38: E | F38: La procédure d'Avis de Travaux Urgents diffère notamment selon :
C39: =IF(C38="C",IF(A39="P",IF(A38="I","p i","p"),IF(A38="I","i","")),"") | D39: =IF(D38="E",IF(A39="P",IF(A38="I","p i","p"),IF(A38="I","i"," ")),"") | E39: =IF(E38="O",IF(A39="P",IF(A38="I","p i","p"),IF(A38="I","i"," ")),"") | F39: A | G39: Le délai d'intervention et le type de réseaux présents
A40: R554-32 | F40: B | G40: Le gestionnaire du lieu d'intervention
F41: C | G41: La personne qui l'envoie
F42: D | G42: Je ne sais pas
B45: 1-1_008 | C45: C | D45: E | F45: Dans lequel des cas suivants le responsable de projet est dispensé de DT ?
C46: =IF(C45="C",IF(A46="P",IF(A45="I","p i","p"),IF(A45="I","i","")),"") | D46: =IF(D45="E",IF(A46="P",IF(A45="I","p i","p"),IF(A45="I","i"," ")),"") | E46: =IF(E45="O",IF(A46="P",IF(A45="I","p i","p"),IF(A45="I","i"," ")),"") | F46: A | G46: Le reprofilage de fossés
A47: R554-1 | F47: B | G47: Les travaux agricoles ou horticoles à moins de 40 cm de profondeur
F48: C | G48: Le décapage d'une chaussée à moins de 15 cm de profondeur
F49: D | G49: Je ne sais pas
A51: I | B51: 1-1_009 | C51: C | D51: E | F51: La DT et la DICT sont obligatoires si les travaux s'approchent, en projection horizontale, d'une ligne aérienne à très haute tension et à conducteurs nus à moins de : | I51: x
C52: =IF(C51="C",IF(A52="P",IF(A51="I","p i","p"),IF(A51="I","i","")),"") -> i | D52: =IF(D51="E",IF(A52="P",IF(A51="I","p i","p"),IF(A51="I","i"," ")),"") -> i | F52: A | G52: 7 mètres
A53: R554-1 | F53: B | G53: 3 mètres
F54: C | G54: 5 mètres
F55: D | G55: Je ne sais pas
A57: I | B57: 1-1_010 | C57: C | D57: E | F57: La DT et la DICT sont obligatoires si les travaux s'approchent, en projection horizontale, d'une ligne aérienne à basse tension et à conducteurs nus à moins de : | I57: x
C58: =IF(C57="C",IF(A58="P",IF(A57="I","p i","p"),IF(A57="I","i","")),"") -> i | D58: =IF(D57="E",IF(A58="P",IF(A57="I","p i","p"),IF(A57="I","i"," ")),"") -> i | F58: A | G58: 7 mètres
A59: A15-2-12/art5 | F59: B | G59: 3 mètres
F60: C | G60: 5 mètres
F61: D | G61: Je ne sais pas
B63: 1-1_012 | C63: C | D63: E | F63: Le remplacement d'un potelet est dispensé de DT et DICT lorsqu'il est effectué :
C64: =IF(C63="C",IF(A64="P",IF(A63="I","p i","p"),IF(A63="I","i","")),"") | D64: =IF(D63="E",IF(A64="P",IF(A63="I","p i","p"),IF(A63="I","i"," ")),"") | E64: =IF(E63="O",IF(A64="P",IF(A63="I","p i","p"),IF(A63="I","i"," ")),"") | F64: A | G64: Avec élargissement de la fouille initiale, jusqu'à 20 cm de profondeur
A65: R554-1 | F65: B | G65: Sans élargissement de la fouille initiale, jusqu'à 60 cm de profondeur
F66: C | G66: Sans élargissement de la fouille initiale, jusqu'à 40 cm de profondeur
F67: D | G67: Je ne sais pas
B69: 1-1_013 | C69: C | D69: E | F69: Je suis à la fois responsable de projet et exécutant de travaux. Je peux faire :
C70: =IF(C69="C",IF(A70="P",IF(A69="I","p i","p"),IF(A69="I","i","")),"") | D70: =IF(D69="E",IF(A70="P",IF(A69="I","p i","p"),IF(A69="I","i"," ")),"") | E70: =IF(E69="O",IF(A70="P",IF(A69="I","p i","p"),IF(A69="I","i"," ")),"") | F70: A | G70: Uniquement une DICT
A71: R554-25IV | F71: B | G71: Uniquement une DT
F72: C | G72: Une DT-DICT conjointe
F73: D | G73: Je ne sais pas
B75: 1-1_014 | C75: C | D75: E | F75: La DT-DICT conjointe doit être remplie :
A76: P | C76: =IF(C75="C",IF(A76="P",IF(A75="I","p i","p"),IF(A75="I","i","")),"") -> p | D76: =IF(D75="E",IF(A76="P",IF(A75="I","p i","p"),IF(A75="I","i"," ")),"") -> p | E76: =IF(E75="O",IF(A76="P",IF(A75="I","p i","p"),IF(A75="I","i"," ")),"") | F76: A | G76: Entièrement par le responsable de projet
A77: R554-25IV | F77: B | G77: Entièrement par l'exécutant des travaux
F78: C | G78: Par le responsable de projet pour le volet DT et par l'exécutant des travaux pour le volet DICT
F79: D | G79: Je ne sais pas
B82: 1-1_015 | C82: C | D82: =IF(D80="E",IF(A82="P",IF(A80="I","p i","p"),IF(A80="I","i"," ")),"") | F82: Si je ne fais pas la déclaration de projet de travaux (DT), je m'expose à :
C83: =IF(C82="C",IF(A83="P",IF(A82="I","p i","p"),IF(A82="I","i","")),"") | D83: =IF(D82="E",IF(A83="P",IF(A82="I","p i","p"),IF(A82="I","i"," ")),"") | F83: A | G83: Une amende pénale maximale de 15 000 euros
A84: L.554-1-1 | F84: B | G84: Un retrait de mon autorisation d’intervention à proximité des réseaux (AIPR)
F85: C | G85: Une peine d'emprisonnement maximale d'un an
F86: D | G86: Je ne sais pas
B88: 1-1_016 | C88: C | D88: E | F88: Préalablement à des travaux urgents, je dois toujours contacter par téléphone tous les exploitants :
C89: =IF(C88="C",IF(A89="P",IF(A88="I","p i","p"),IF(A88="I","i","")),"") | D89: =IF(D88="E",IF(A89="P",IF(A88="I","p i","p"),IF(A88="I","i"," ")),"") | E89: =IF(E88="O",IF(A89="P",IF(A88="I","p i","p"),IF(A88="I","i"," ")),"") | F89: A | G89: Mentionnés par le guichet unique
A90: R554-32 | F90: B | G90: De réseaux sensibles pour la sécurité
F91: C | G91: De réseaux de transport de gaz, d'hydrocarbures ou de produits chimiques (TMD)
F92: D | G92: Je ne sais pas
B94: 1-1_031 | C94: C | F94: Les dispositions réglementaires relatives à la prévention des dommages aux digues concernent :
C95: =IF(C94="C",IF(A95="P",IF(A94="I","p i","p"),IF(A94="I","i","")),"") | D95: =IF(D94="E",IF(A95="P",IF(A94="I","p i","p"),IF(A94="I","i"," ")),"") | E95: =IF(E94="O",IF(A95="P",IF(A94="I","p i","p"),IF(A94="I","i"," ")),"") | F95: A | G95: Toutes les digues
A96: R. 554-2 I | F96: B | G96: Uniquement les digues de rivière canalisée
F97: C | G97: Les digues de prévention des inondations et des submersions
F98: D | G98: Je ne sais pas
B100: 1-1_032 | C100: C | F100: Lorsque je reçois les resultats des investigations complémentaires (IC) :
C101: =IF(C100="C",IF(A101="P",IF(A100="I","p i","p"),IF(A100="I","i","")),"") | D101: =IF(D100="E",IF(A101="P",IF(A100="I","p i","p"),IF(A100="I","i"," ")),"") | E101: =IF(E100="O",IF(A101="P",IF(A100="I","p i","p"),IF(A100="I","i"," ")),"") | F101: A | G101: J'en prends compte uniquement dans la réalisation de mon étude
F102: B | G102: J'en prends compte dans la réalisation de mon étude et je les transmets aux entreprises de travaux
F103: C | G103: J'en prends compte dans la réalisation de mon étude et je les transmets aux entreprises de travaux ainsi qu'aux exploitants qui les ont demandées
F104: D | G104: Je ne sais pas
B106: 1-1_033 | C106: C | F106: Pour un projet de travaux dans l'emprise du domaine ferroviaire, je dois, le plus en amont possible des travaux:
C107: =IF(C106="C",IF(A107="P",IF(A106="I","p i","p"),IF(A106="I","i","")),"") | D107: =IF(D106="E",IF(A107="P",IF(A106="I","p i","p"),IF(A106="I","i"," ")),"") | E107: =IF(E106="O",IF(A107="P",IF(A106="I","p i","p"),IF(A106="I","i"," ")),"") | F107: A | G107: Uniquement faire une DT
A108: GT - 5.2.8 | F108: B | G108: Faire une DT et contacter la SNCF afin d'établir une convention "Etudes & Travaux" si nécessaire
F109: C | G109: Uniquement faire une convention "Etudes & Travaux" avec la SNCF
F110: D | G110: Je ne sais pas
C156: =IF(C155="C",IF(A156="P",IF(A155="I","p i","p"),IF(A155="I","i","")),"") | D156: =IF(D155="E",IF(A156="P",IF(A155="I","p i","p"),IF(A155="I","i"," ")),"") | E156: =IF(E155="O",IF(A156="P",IF(A155="I","p i","p"),IF(A155="I","i"," ")),"")
C163: =IF(C162="C",IF(A163="P",IF(A162="I","p i","p"),IF(A162="I","i","")),"") | D163: =IF(D162="E",IF(A163="P",IF(A162="I","p i","p"),IF(A162="I","i"," ")),"") | E163: =IF(E162="O",IF(A163="P",IF(A162="I","p i","p"),IF(A162="I","i"," ")),"")
C170: =IF(C169="C",IF(A170="P",IF(A169="I","p i","p"),IF(A169="I","i","")),"") | D170: =IF(D169="E",IF(A170="P",IF(A169="I","p i","p"),IF(A169="I","i"," ")),"") | E170: =IF(E169="O",IF(A170="P",IF(A169="I","p i","p"),IF(A169="I","i"," ")),"")
C177: =IF(C176="C",IF(A177="P",IF(A176="I","p i","p"),IF(A176="I","i","")),"") | D177: =IF(D176="E",IF(A177="P",IF(A176="I","p i","p"),IF(A176="I","i"," ")),"") | E177: =IF(E176="O",IF(A177="P",IF(A176="I","p i","p"),IF(A176="I","i"," ")),"")
C184: =IF(C183="C",IF(A184="P",IF(A183="I","p i","p"),IF(A183="I","i","")),"") | D184: =IF(D183="E",IF(A184="P",IF(A183="I","p i","p"),IF(A183="I","i"," ")),"") | E184: =IF(E183="O",IF(A184="P",IF(A183="I","p i","p"),IF(A183="I","i"," ")),"")
C191: =IF(C190="C",IF(A191="P",IF(A190="I","p i","p"),IF(A190="I","i","")),"") | D191: =IF(D190="E",IF(A191="P",IF(A190="I","p i","p"),IF(A190="I","i"," ")),"") | E191: =IF(E190="O",IF(A191="P",IF(A190="I","p i","p"),IF(A190="I","i"," ")),"")
C198: =IF(C197="C",IF(A198="P",IF(A197="I","p i","p"),IF(A197="I","i","")),"") | D198: =IF(D197="E",IF(A198="P",IF(A197="I","p i","p"),IF(A197="I","i"," ")),"") | E198: =IF(E197="O",IF(A198="P",IF(A197="I","p i","p"),IF(A197="I","i"," ")),"")
C205: =IF(C204="C",IF(A205="P",IF(A204="I","p i","p"),IF(A204="I","i","")),"") | D205: =IF(D204="E",IF(A205="P",IF(A204="I","p i","p"),IF(A204="I","i"," ")),"") | E205: =IF(E204="O",IF(A205="P",IF(A204="I","p i","p"),IF(A204="I","i"," ")),"")
C212: =IF(C211="C",IF(A212="P",IF(A211="I","p i","p"),IF(A211="I","i","")),"") | D212: =IF(D211="E",IF(A212="P",IF(A211="I","p i","p"),IF(A211="I","i"," ")),"") | E212: =IF(E211="O",IF(A212="P",IF(A211="I","p i","p"),IF(A211="I","i"," ")),"")
C219: =IF(C218="C",IF(A219="P",IF(A218="I","p i","p"),IF(A218="I","i","")),"") | D219: =IF(D218="E",IF(A219="P",IF(A218="I","p i","p"),IF(A218="I","i"," ")),"") | E219: =IF(E218="O",IF(A219="P",IF(A218="I","p i","p"),IF(A218="I","i"," ")),"")
...

Sheet 1.2
A1: =Bilan!B8 -> 1.2 Analyse des réponses - IC - Cartographie
C3: C | D3: E | E3: O | F3: Total
B4: Nb quest. | C4: =COUNTIF(C8:C684,C3) -> 16 | D4: =COUNTIF(D8:D684,D3) -> 9 | E4: =COUNTIF(E8:E684,E3) -> 2 | F4: =COUNTA(B8:B684) -> 16
B5: Illust. | C5: =COUNTIF(C8:C684,"i")+COUNTIF(C8:C684,"p i") -> 2 | D5: =COUNTIF(D8:D684,"i")+COUNTIF(D8:D684,"p i") -> 2 | E5: =COUNTIF(E8:E684,"i")+COUNTIF(E8:E684,"p i") -> 2 | F5: =COUNTIF(A8:A684,"I") -> 2
B6: Prio | C6: =COUNTIF(C8:C684,"p")+COUNTIF(C8:C684,"p i") -> 1 | D6: =COUNTIF(D8:D684,"p")+COUNTIF(D8:D684,"p i") -> 0 | E6: =COUNTIF(E8:E684,"p")+COUNTIF(E8:E684,"p i") -> 0 | F6: =COUNTIF(A8:A684,"P") -> 1
B8: 1-2_001 | C8: C | F8: De combien de jours (sauf jours fériés) dispose l'exploitant pour répondre à une DT, dématérialisée (hors recours à des mesures de localisation) ?
C9: =IF(C8="C",IF(A9="P",IF(A8="I","p i","p"),IF(A8="I","i","")),"") | F9: A | G9: 7
A10: R554-22I | F10: B | G10: 9
F11: C | G11: 15
F12: D | G12: Je ne sais pas
B14: 1-2_002 | C14: C | F14: De combien de jours (sauf jours fériés) dispose l'exploitant pour répondre à une DT NON dématérialisée (envoi des formulaires par courrier) et hors recours à des mesures de localisation ?
C15: =IF(C14="C",IF(A15="P",IF(A14="I","p i","p"),IF(A14="I","i","")),"") | F15: A | G15: 7
A16: R554-22I | F16: B | G16: 9
F17: C | G17: 15
F18: E | G18: Je ne sais pas
B20: 1-2_003 | C20: C | F20: Quelle information doit obligatoirement être fournie par l'exploitant sur le récépissé de la déclaration de projet de travaux (DT) ?
C21: =IF(C20="C",IF(A21="P",IF(A20="I","p i","p"),IF(A20="I","i","")),"") | F21: A | G21: La profondeur maximale à laquelle les travaux peuvent être effectués
A22: A15-2-12/art5 | F22: B | G22: Les résultats des investigations complémentaires
F23: C | G23: La classe de précision des données de localisation des réseaux
F24: D | G24: Je ne sais pas
B26: 1-2_004 | C26: C | F26: Après réception du récépissé de déclaration de projet de travaux (DT), lorsque des investigations complémentaires sont demandées, qui doit les commander ?
A27: P | C27: =IF(C26="C",IF(A27="P",IF(A26="I","p i","p"),IF(A26="I","i","")),"") -> p | D27: =IF(D26="E",IF(A27="P",IF(A26="I","p i","p"),IF(A26="I","i"," ")),"") | F27: A | G27: Le responsable de projet
A28: A15-2-12/art7III | F28: B | G28: L'exploitant de réseau
F29: C | G29: L'exécutant des travaux
F30: D | G30: Je ne sais pas
B32: 1-2_006 | C32: C | F32: Après réception du récépissé de déclaration de projet de travaux (DT), laquelle de ces conditions permet d'être dispensé d'investigations complémentaires ?
F33: A | G33: Les travaux prévus sont des travaux sans tranchée
A34: R554-23III | F34: B | G34: La zone terrassée est supérieure à 100 m²
F35: C | G35: Les travaux prévus sont des travaux de surface ne dépassant pas 10 cm de profondeur
F36: D | G36: Je ne sais pas
B38: 1-2_007 | C38: C | F38: Pour un récolement, le responsable de projet (ou maître d'ouvrage) est dispensé de recourir à un prestataire certifié lorsque les relevés concernent un tronçon neuf :
F39: A | G39: Posé par une technique sans tranchée
A40: R554-34 | F40: B | G40: Qui sera exploité par le responsable de projet
F41: C | G41: Dont le responsable de projet confiera l’exploitation à un tiers
F42: D | G42: Je ne sais pas
B45: 1-2_009 | C45: C | D45: E | F45: Un exploitant de réseau mentionne la classe de précision C dans les plans envoyés en réponse à une DT ou une DICT. Cela signifie que l'incertitude maximale de localisation pour le réseau principal est :
C46: =IF(C45="C",IF(A46="P",IF(A45="I","p i","p"),IF(A45="I","i","")),"") | D46: =IF(D45="E",IF(A46="P",IF(A45="I","p i","p"),IF(A45="I","i"," ")),"") | F46: A | G46: Inférieure ou égale à 50 cm
A47: A15-2-12/art1-3° | F47: B | G47: Inférieure ou égale à 1,5 m
F48: C | G48: Supérieure à 1,5 m
F49: D | G49: Je ne sais pas
B51: 1-2_010 | C51: C | D51: E | F51: Un exploitant de réseau mentionne la classe de précision B dans les plans envoyés en réponse à une DT ou une DICT. Cela signifie que l'incertitude maximale de localisation pour le réseau principal est :
C52: =IF(C51="C",IF(A52="P",IF(A51="I","p i","p"),IF(A51="I","i","")),"") | D52: =IF(D51="E",IF(A52="P",IF(A51="I","p i","p"),IF(A51="I","i"," ")),"") | F52: A | G52: Inférieure ou égale à 50 cm
A53: A15-2-12/art1-3° | F53: B | G53: Inférieure ou égale à 1,5 m
F54: C | G54: Supérieure à 1,5 m
F55: D | G55: Je ne sais pas
B57: 1-2_011 | C57: C | D57: E | F57: Un exploitant de réseau flexible mentionne la classe de précision A dans les plans envoyés en réponse à une DT ou une DICT. Cela signifie que l'incertitude maximale de localisation est :
C58: =IF(C57="C",IF(A58="P",IF(A57="I","p i","p"),IF(A57="I","i","")),"") | D58: =IF(D57="E",IF(A58="P",IF(A57="I","p i","p"),IF(A57="I","i"," ")),"") | F58: A | G58: Inférieure ou égale à 40 cm
A59: A15-2-12/art1-3° | F59: B | G59: Inférieure ou égale à 50 cm
F60: C | G60: Inférieure ou égale à 1,5 m
F61: E | G61: Je ne sais pas
B63: 1-2_012 | C63: C | D63: E | F63: Un exploitant de réseau rigide mentionne la classe de précision A dans les plans envoyés en réponse à une DT ou une DICT. Cela signifie que l'incertitude maximale de localisation est :
C64: =IF(C63="C",IF(A64="P",IF(A63="I","p i","p"),IF(A63="I","i","")),"") | D64: =IF(D63="E",IF(A64="P",IF(A63="I","p i","p"),IF(A63="I","i"," ")),"") | F64: A | G64: Inférieure ou égale à 40 cm
A65: A15-2-12/art1-3° | F65: B | G65: Inférieure ou égale à 50 cm
F66: C | G66: Inférieure ou égale à 1,5 m
F67: E | G67: Je ne sais pas
B69: 1-2_013 | C69: C | D69: E | F69: En réponse à une DT ou une DICT, lorsqu'un exploitant de réseau fournit les données de localisation de son réseau lors d'une réunion sur site sans préciser la classe de précision de ces données, la classe de précision à retenir est :
C70: =IF(C69="C",IF(A70="P",IF(A69="I","p i","p"),IF(A69="I","i","")),"") | D70: =IF(D69="E",IF(A70="P",IF(A69="I","p i","p"),IF(A69="I","i"," ")),"") | F70: A | G70: Toujours la classe A
A71: A15-2-12/art5 | F71: B | G71: La classe A si le réseau est sensible, la classe B ou C si le réseau n'est pas sensible
F72: C | G72: La classe de précision doit toujours être précisée par l'exploitant
F73: D | G73: Je ne sais pas
A75: I | B75: 1-2_014 | C75: C | D75: E | E75: O | F75: Parmi les réseaux suivants, un seul est classé non sensible pour la sécurité par la règlementation. Lequel ?
C76: =IF(C75="C",IF(A76="P",IF(A75="I","p i","p"),IF(A75="I","i","")),"") -> i | D76: =IF(D75="E",IF(A76="P",IF(A75="I","p i","p"),IF(A75="I","i"," ")),"") -> i | E76: =IF(E75="O",IF(A76="P",IF(A75="I","p i","p"),IF(A75="I","i"," ")),"") -> i | F76: A | G76: Un réseau de chaleur
A77: R554-2 | F77: B | G77: Un réseau de tramway
F78: C | G78: Un réseau d'assainissement
F79: D | G79: Je ne sais pas
A81: I | B81: 1-2_015 | C81: C | D81: E | E81: O | F81: Parmi les réseaux suivants, un seul est classé sensible pour la sécurité par la règlementation. Lequel ?
C82: =IF(C81="C",IF(A82="P",IF(A81="I","p i","p"),IF(A81="I","i","")),"") -> i | D82: =IF(D81="E",IF(A82="P",IF(A81="I","p i","p"),IF(A81="I","i"," ")),"") -> i | E82: =IF(E81="O",IF(A82="P",IF(A81="I","p i","p"),IF(A81="I","i"," ")),"") -> i | F82: A | G82: Un réseau de télécommunication
A83: R554-2 | F83: B | G83: Un réseau électrique
F84: C | G84: Un réseau d'eau potable
F85: D | G85: Je ne sais pas
B87: 1-2_017 | C87: C | D87: E | F87: Qui est responsable de la justesse du classement de la cartographie d'un réseau dans la classe A, B ou C fournie en réponse à la DT ou à la DICT ?
C88: =IF(C87="C",IF(A88="P",IF(A87="I","p i","p"),IF(A87="I","i","")),"") | D88: =IF(D87="E",IF(A88="P",IF(A87="I","p i","p"),IF(A87="I","i"," ")),"") | E88: =IF(E87="O",IF(A88="P",IF(A87="I","p i","p"),IF(A87="I","i"," ")),"") | F88: A | G88: Le propriétaire du réseau concerné
A89: A15-2-12/art5 | F89: B | G89: L'exploitant du réseau concerné
F90: C | G90: Le prestataire certifié qui a effectué le récolement du réseau concerné
F91: D | G91: Je ne sais pas
B93: 1-2_021 | C93: C | F93: Après réception du récépissé de DT, lorsque des investigations complémentaires sont obligatoires, qui prend en charge les coûts associés à leur réalisation ?
C94: =IF(C93="C",IF(A94="P",IF(A93="I","p i","p"),IF(A93="I","i","")),"") | F94: A | G94: L’exécutant des travaux
A95: R554-23II | F95: B | G95: L’exploitant du réseau les ayant demandées
F96: C | G96: Le responsable de projet
F97: D | G97: Je ne sais pas
B99: 1-2_023 | C99: C | D99: E | F99: Lorsque l'exploitant demande dans son récépissé de DT, des investigations complémentaires, le responsable de projet est dispensé de les réaliser lorsque :
C100: =IF(C99="C",IF(A100="P",IF(A99="I","p i","p"),IF(A99="I","i","")),"") | D100: =IF(D99="E",IF(A100="P",IF(A99="I","p i","p"),IF(A99="I","i"," ")),"") | F100: A | G100: La zone d’emprise des travaux affectant le sol est supérieure à 100 m²
A101: A15-2-12/art6II | F101: B | G101: La zone d’emprise des travaux affectant le sol est inférieure à 100 m²
F102: C | G102: L’ensemble du personnel de l’exécutant des travaux dispose de l’AIPR
F103: D | G103: Je ne sais pas
C257: =IF(C256="C",IF(A257="P",IF(A256="I","p i","p"),IF(A256="I","i","")),"") | D257: =IF(D256="E",IF(A257="P",IF(A256="I","p i","p"),IF(A256="I","i"," ")),"") | E257: =IF(E256="O",IF(A257="P",IF(A256="I","p i","p"),IF(A256="I","i"," ")),"")
C264: =IF(C263="C",IF(A264="P",IF(A263="I","p i","p"),IF(A263="I","i","")),"") | D264: =IF(D263="E",IF(A264="P",IF(A263="I","p i","p"),IF(A263="I","i"," ")),"") | E264: =IF(E263="O",IF(A264="P",IF(A263="I","p i","p"),IF(A263="I","i"," ")),"")
C271: =IF(C270="C",IF(A271="P",IF(A270="I","p i","p"),IF(A270="I","i","")),"") | D271: =IF(D270="E",IF(A271="P",IF(A270="I","p i","p"),IF(A270="I","i"," ")),"") | E271: =IF(E270="O",IF(A271="P",IF(A270="I","p i","p"),IF(A270="I","i"," ")),"")
C278: =IF(C277="C",IF(A278="P",IF(A277="I","p i","p"),IF(A277="I","i","")),"") | D278: =IF(D277="E",IF(A278="P",IF(A277="I","p i","p"),IF(A277="I","i"," ")),"") | E278: =IF(E277="O",IF(A278="P",IF(A277="I","p i","p"),IF(A277="I","i"," ")),"")
C285: =IF(C284="C",IF(A285="P",IF(A284="I","p i","p"),IF(A284="I","i","")),"") | D285: =IF(D284="E",IF(A285="P",IF(A284="I","p i","p"),IF(A284="I","i"," ")),"") | E285: =IF(E284="O",IF(A285="P",IF(A284="I","p i","p"),IF(A284="I","i"," ")),"")
C292: =IF(C291="C",IF(A292="P",IF(A291="I","p i","p"),IF(A291="I","i","")),"") | D292: =IF(D291="E",IF(A292="P",IF(A291="I","p i","p"),IF(A291="I","i"," ")),"") | E292: =IF(E291="O",IF(A292="P",IF(A291="I","p i","p"),IF(A291="I","i"," ")),"")
C299: =IF(C298="C",IF(A299="P",IF(A298="I","p i","p"),IF(A298="I","i","")),"") | D299: =IF(D298="E",IF(A299="P",IF(A298="I","p i","p"),IF(A298="I","i"," ")),"") | E299: =IF(E298="O",IF(A299="P",IF(A298="I","p i","p"),IF(A298="I","i"," ")),"")
C306: =IF(C305="C",IF(A306="P",IF(A305="I","p i","p"),IF(A305="I","i","")),"") | D306: =IF(D305="E",IF(A306="P",IF(A305="I","p i","p"),IF(A305="I","i"," ")),"") | E306: =IF(E305="O",IF(A306="P",IF(A305="I","p i","p"),IF(A305="I","i"," ")),"")
C313: =IF(C312="C",IF(A313="P",IF(A312="I","p i","p"),IF(A312="I","i","")),"") | D313: =IF(D312="E",IF(A313="P",IF(A312="I","p i","p"),IF(A312="I","i"," ")),"") | E313: =IF(E312="O",IF(A313="P",IF(A312="I","p i","p"),IF(A312="I","i"," ")),"")
C320: =IF(C319="C",IF(A320="P",IF(A319="I","p i","p"),IF(A319="I","i","")),"") | D320: =IF(D319="E",IF(A320="P",IF(A319="I","p i","p"),IF(A319="I","i"," ")),"") | E320: =IF(E319="O",IF(A320="P",IF(A319="I","p i","p"),IF(A319="I","i"," ")),"")
C327: =IF(C326="C",IF(A327="P",IF(A326="I","p i","p"),IF(A326="I","i","")),"") | D327: =IF(D326="E",IF(A327="P",IF(A326="I","p i","p"),IF(A326="I","i"," ")),"") | E327: =IF(E326="O",IF(A327="P",IF(A326="I","p i","p"),IF(A326="I","i"," ")),"")
C334: =IF(C333="C",IF(A334="P",IF(A333="I","p i","p"),IF(A333="I","i","")),"") | D334: =IF(D333="E",IF(A334="P",IF(A333="I","p i","p"),IF(A333="I","i"," ")),"") | E334: =IF(E333="O",IF(A334="P",IF(A333="I","p i","p"),IF(A333="I","i"," ")),"")
... C481: =IF(C480="C",IF(A481="P",IF(A480="I","p i","p"),IF(A480="I","i","")),"") | D481: =IF(D480="E",IF(A481="P",IF(A480="I","p i","p"),IF(A480="I","i"," ")),"") | E481: =IF(E480="O",IF(A481="P",IF(A480="I","p i","p"),IF(A480="I","i"," ")),"")
C488: =IF(C487="C",IF(A488="Prioritaire",IF(A487="I","p i","p"),IF(A487="I","i","")),"") | D488: =IF(D487="E",IF(A488="Prioritaire",IF(A487="I","p i","p"),IF(A487="I","i"," ")),"") | E488: =IF(E487="O",IF(A488="Prioritaire",IF(A487="I","p i","p"),IF(A487="I","i"," ")),"")
C495: =IF(C494="C",IF(A495="Prioritaire",IF(A494="I","p i","p"),IF(A494="I","i","")),"") | D495: =IF(D494="E",IF(A495="Prioritaire",IF(A494="I","p i","p"),IF(A494="I","i"," ")),"") | E495: =IF(E494="O",IF(A495="Prioritaire",IF(A494="I","p i","p"),IF(A494="I","i"," ")),"")
...

Sheet 1.3
A1: =Bilan!B9 -> 1.3 Clauses dans les marchés et DCE
C3: C | D3: E | E3: O | F3: Total
B4: Nb quest. | C4: =COUNTIF(C8:C623,C3) -> 4 | D4: =COUNTIF(D8:D623,D3) -> 2 | E4: =COUNTIF(E8:E623,E3) -> 0 | F4: =COUNTA(B8:B623) -> 4
B5: Illust. | C5: =COUNTIF(C8:C623,"i")+COUNTIF(C8:C623,"p i") -> 0 | D5: =COUNTIF(D8:D623,"i")+COUNTIF(D8:D623,"p i") -> 0 | E5: =COUNTIF(E8:E623,"i")+COUNTIF(E8:E623,"p i") -> 0 | F5: =COUNTIF(A8:A623,"I") -> 0
B6: Prio | C6: =COUNTIF(C8:C623,"p")+COUNTIF(C8:C623,"p i") -> 0 | D6: =COUNTIF(D8:D623,"p")+COUNTIF(D8:D623,"p i") -> 0 | E6: =COUNTIF(E8:E623,"p")+COUNTIF(E8:E623,"p i") -> 0 | F6: =COUNTIF(A8:A623,"P") -> 0
B8: 1-3_001 | C8: C | D8: E | F8: Si le marché de travaux ne prévoit pas de clauses spécifiques, la DT :
A9: R554-22V | F9: A | G9: Reste valide sans limite de temps
F10: B | G10: Est seulement valide 3 mois
F11: C | G11: Est seulement valide 6 mois
F12: D | G12: Je ne sais pas
B14: 1-3_003 | C14: C | D14: E | F14: Dans le cas où un exploitant de réseau sensible ne répond pas dans le délai réglementaire à la DICT et à sa relance, l'exécutant :
C15: =IF(C14="C",IF(A15="P",IF(A14="I","p i","p"),IF(A14="I","i","")),"") | D15: =IF(D14="E",IF(A15="P",IF(A14="I","p i","p"),IF(A14="I","i"," ")),"") | E15: =IF(E14="O",IF(A15="P",IF(A14="I","p i","p"),IF(A14="I","i"," ")),"") | F15: A | G15: Ne démarre pas les travaux et ne subit pas de préjudice lié au report
A16: R554-26VI | F16: B | G16: Démarre les travaux après un délai complémentaire de 9 jours
F17: C | G17: Démarre les travaux en prenant les précautions particulières prévues par le guide technique
F18: D | G18: Je ne sais pas
B21: 1-3_011 | C21: C | F21: En cas de travaux dispensés d'investigations complémentaires, le responsable de projet doit prévoir des clauses techniques et financières dans le marché, s'il n'effectue pas d'opérations de localisation, lorsque les réseaux situés dans l'emprise du projet sont :
C22: =IF(C21="C",IF(A22="P",IF(A21="I","p i","p"),IF(A21="I","i","")),"") | D22: =IF(D21="E",IF(A22="P",IF(A21="I","p i","p"),IF(A21="I","i"," ")),"") | E22: =IF(E21="O",IF(A22="P",IF(A21="I","p i","p"),IF(A21="I","i"," ")),"") | F22: A | G22: En classe de précision A
A23: R554-23 | F23: B | G23: En classe de précision B ou C
F24: C | G24: En arrêt définitif d'exploitation
F25: D | G25: Je ne sais pas
B27: 1-3_012 | C27: C | F27: Le responsable de projet doit prévoir des clauses techniques et financières dans le marché lorsque des réseaux situés dans l'emprise du projet sont en classe de précision B ou C et sont :
C28: =IF(C27="C",IF(A28="P",IF(A27="I","p i","p"),IF(A27="I","i","")),"") | D28: =IF(D27="E",IF(A28="P",IF(A27="I","p i","p"),IF(A27="I","i"," ")),"") | E28: =IF(E27="O",IF(A28="P",IF(A27="I","p i","p"),IF(A27="I","i"," ")),"") | F28: A | G28: Uniquement des réseaux sensibles
A29: R554-23 | F29: B | G29: Uniquement des réseaux non sensibles
F30: C | G30: Des réseaux sensibles ou non sensibles
F31: D | G31: Je ne sais pas
C70: =IF(C69="C",IF(A70="P",IF(A69="I","p i","p"),IF(A69="I","i","")),"") | D70: =IF(D69="E",IF(A70="P",IF(A69="I","p i","p"),IF(A69="I","i"," ")),"") | E70: =IF(E69="O",IF(A70="P",IF(A69="I","p i","p"),IF(A69="I","i"," ")),"")
C77: =IF(C76="C",IF(A77="P",IF(A76="I","p i","p"),IF(A76="I","i","")),"") | D77: =IF(D76="E",IF(A77="P",IF(A76="I","p i","p"),IF(A76="I","i"," ")),"") | E77: =IF(E76="O",IF(A77="P",IF(A76="I","p i","p"),IF(A76="I","i"," ")),"")
C84: =IF(C83="C",IF(A84="P",IF(A83="I","p i","p"),IF(A83="I","i","")),"") | D84: =IF(D83="E",IF(A84="P",IF(A83="I","p i","p"),IF(A83="I","i"," ")),"") | E84: =IF(E83="O",IF(A84="P",IF(A83="I","p i","p"),IF(A83="I","i"," ")),"")
C91: =IF(C90="C",IF(A91="P",IF(A90="I","p i","p"),IF(A90="I","i","")),"") | D91: =IF(D90="E",IF(A91="P",IF(A90="I","p i","p"),IF(A90="I","i"," ")),"") | E91: =IF(E90="O",IF(A91="P",IF(A90="I","p i","p"),IF(A90="I","i"," ")),"")
C98: =IF(C97="C",IF(A98="P",IF(A97="I","p i","p"),IF(A97="I","i","")),"") | D98: =IF(D97="E",IF(A98="P",IF(A97="I","p i","p"),IF(A97="I","i"," ")),"") | E98: =IF(E97="O",IF(A98="P",IF(A97="I","p i","p"),IF(A97="I","i"," ")),"")
C105: =IF(C104="C",IF(A105="P",IF(A104="I","p i","p"),IF(A104="I","i","")),"") | D105: =IF(D104="E",IF(A105="P",IF(A104="I","p i","p"),IF(A104="I","i"," ")),"") | E105: =IF(E104="O",IF(A105="P",IF(A104="I","p i","p"),IF(A104="I","i"," ")),"")
C112: =IF(C111="C",IF(A112="P",IF(A111="I","p i","p"),IF(A111="I","i","")),"") | D112: =IF(D111="E",IF(A112="P",IF(A111="I","p i","p"),IF(A111="I","i"," ")),"") | E112: =IF(E111="O",IF(A112="P",IF(A111="I","p i","p"),IF(A111="I","i"," ")),"")
C119: =IF(C118="C",IF(A119="P",IF(A118="I","p i","p"),IF(A118="I","i","")),"") | D119: =IF(D118="E",IF(A119="P",IF(A118="I","p i","p"),IF(A118="I","i"," ")),"") | E119: =IF(E118="O",IF(A119="P",IF(A118="I","p i","p"),IF(A118="I","i"," ")),"")
C126: =IF(C125="C",IF(A126="P",IF(A125="I","p i","p"),IF(A125="I","i","")),"") | D126: =IF(D125="E",IF(A126="P",IF(A125="I","p i","p"),IF(A125="I","i"," ")),"") | E126: =IF(E125="O",IF(A126="P",IF(A125="I","p i","p"),IF(A125="I","i"," ")),"")
C133: =IF(C132="C",IF(A133="P",IF(A132="I","p i","p"),IF(A132="I","i","")),"") | D133: =IF(D132="E",IF(A133="P",IF(A132="I","p i","p"),IF(A132="I","i"," ")),"") | E133: =IF(E132="O",IF(A133="P",IF(A132="I","p i","p"),IF(A132="I","i"," ")),"")
C140: =IF(C139="C",IF(A140="P",IF(A139="I","p i","p"),IF(A139="I","i","")),"") | D140: =IF(D139="E",IF(A140="P",IF(A139="I","p i","p"),IF(A139="I","i"," ")),"") | E140: =IF(E139="O",IF(A140="P",IF(A139="I","p i","p"),IF(A139="I","i"," ")),"")
C147: =IF(C146="C",IF(A147="P",IF(A146="I","p i","p"),IF(A146="I","i","")),"") | D147: =IF(D146="E",IF(A147="P",IF(A146="I","p i","p"),IF(A146="I","i"," ")),"") | E147: =IF(E146="O",IF(A147="P",IF(A146="I","p i","p"),IF(A146="I","i"," ")),"")
C154: =IF(C153="C",IF(A154="P",IF(A153="I","p i","p"),IF(A153="I","i","")),"") | D154: =IF(D153="E",IF(A154="P",IF(A153="I","p i","p"),IF(A153="I","i"," ")),"") | E154: =IF(E153="O",IF(A154="P",IF(A153="I","p i","p"),IF(A153="I","i"," ")),"")
C155: =IF(C154="C",IF(A155="Prioritaire",IF(A154="I","p i","p"),IF(A154="I","i","")),"") | D155: =IF(D154="E",IF(A155="Prioritaire",IF(A154="I","p i","p"),IF(A154="I","i"," ")),"") | E155: =IF(E154="O",IF(A155="Prioritaire",IF(A154="I","p i","p"),IF(A154="I","i"," ")),"")
C161: =IF(C160="C",IF(A161="P",IF(A160="I","p i","p"),IF(A160="I","i","")),"") | D161: =IF(D160="E",IF(A161="P",IF(A160="I","p i","p"),IF(A160="I","i"," ")),"") | E161: =IF(E160="O",IF(A161="P",IF(A160="I","p i","p"),IF(A160="I","i"," ")),"")
C168: =IF(C167="C",IF(A168="P",IF(A167="I","p i","p"),IF(A167="I","i","")),"") | D168: =IF(D167="E",IF(A168="P",IF(A167="I","p i","p"),IF(A167="I","i"," ")),"") | E168: =IF(E167="O",IF(A168="P",IF(A167="I","p i","p"),IF(A167="I","i"," ")),"")
C175: =IF(C174="C",IF(A175="P",IF(A174="I","p i","p"),IF(A174="I","i","")),"") | D175: =IF(D174="E",IF(A175="P",IF(A174="I","p i","p"),IF(A174="I","i"," ")),"") | E175: =IF(E174="O",IF(A175="P",IF(A174="I","p i","p"),IF(A174="I","i"," ")),"")
C182: =IF(C181="C",IF(A182="P",IF(A181="I","p i","p"),IF(A181="I","i","")),"") | D182: =IF(D181="E",IF(A182="P",IF(A181="I","p i","p"),IF(A181="I","i"," ")),"") | E182: =IF(E181="O",IF(A182="P",IF(A181="I","p i","p"),IF(A181="I","i"," ")),"")
C189: =IF(C188="C",IF(A189="P",IF(A188="I","p i","p"),IF(A188="I","i","")),"") | D189: =IF(D188="E",IF(A189="P",IF(A188="I","p i","p"),IF(A188="I","i"," ")),"") | E189: =IF(E188="O",IF(A189="P",IF(A188="I","p i","p"),IF(A188="I","i"," ")),"")
C196: =IF(C195="C",IF(A196="P",IF(A195="I","p i","p"),IF(A195="I","i","")),"") | D196: =IF(D195="E",IF(A196="P",IF(A195="I","p i","p"),IF(A195="I","i"," ")),"") | E196: =IF(E195="O",IF(A196="P",IF(A195="I","p i","p"),IF(A195="I","i"," ")),"")
C203: =IF(C202="C",IF(A203="P",IF(A202="I","p i","p"),IF(A202="I","i","")),"") | D203: =IF(D202="E",IF(A203="P",IF(A202="I","p i","p"),IF(A202="I","i"," ")),"") | E203: =IF(E202="O",IF(A203="P",IF(A202="I","p i","p"),IF(A202="I","i"," ")),"")
C210: =IF(C209="C",IF(A210="P",IF(A209="I","p i","p"),IF(A209="I","i","")),"") | D210: =IF(D209="E",IF(A210="P",IF(A209="I","p i","p"),IF(A209="I","i"," ")),"") | E210: =IF(E209="O",IF(A210="P",IF(A209="I","p i","p"),IF(A209="I","i"," ")),"")
C217: =IF(C216="C",IF(A217="P",IF(A216="I","p i","p"),IF(A216="I","i","")),"") | D217: =IF(D216="E",IF(A217="P",IF(A216="I","p i","p"),IF(A216="I","i"," ")),"") | E217: =IF(E216="O",IF(A217="P",IF(A216="I","p i","p"),IF(A216="I","i"," ")),"")
C224: =IF(C223="C",IF(A224="P",IF(A223="I","p i","p"),IF(A223="I","i","")),"") | D224: =IF(D223="E",IF(A224="P",IF(A223="I","p i","p"),IF(A223="I","i"," ")),"") | E224: =IF(E223="O",IF(A224="P",IF(A223="I","p i","p"),IF(A223="I","i"," ")),"")
C231: =IF(C230="C",IF(A231="P",IF(A230="I","p i","p"),IF(A230="I","i","")),"") | D231: =IF(D230="E",IF(A231="P",IF(A230="I","p i","p"),IF(A230="I","i"," ")),"") | E231: =IF(E230="O",IF(A231="P",IF(A230="I","p i","p"),IF(A230="I","i"," ")),"")
C238: =IF(C237="C",IF(A238="P",IF(A237="I","p i","p"),IF(A237="I","i","")),"") | D238: =IF(D237="E",IF(A238="P",IF(A237="I","p i","p"),IF(A237="I","i"," ")),"") | E238: =IF(E237="O",IF(A238="P",IF(A237="I","p i","p"),IF(A237="I","i"," ")),"")
... C420: =IF(C419="C",IF(A420="P",IF(A419="I","p i","p"),IF(A419="I","i","")),"") | D420: =IF(D419="E",IF(A420="P",IF(A419="I","p i","p"),IF(A419="I","i"," ")),"") | E420: =IF(E419="O",IF(A420="P",IF(A419="I","p i","p"),IF(A419="I","i"," ")),"")
C427: =IF(C426="C",IF(A427="Prioritaire",IF(A426="I","p i","p"),IF(A426="I","i","")),"") | D427: =IF(D426="E",IF(A427="Prioritaire",IF(A426="I","p i","p"),IF(A426="I","i"," ")),"") | E427: =IF(E426="O",IF(A427="Prioritaire",IF(A426="I","p i","p"),IF(A426="I","i"," ")),"")
C434: =IF(C433="C",IF(A434="Prioritaire",IF(A433="I","p i","p"),IF(A433="I","i","")),"") | D434: =IF(D433="E",IF(A434="Prioritaire",IF(A433="I","p i","p"),IF(A433="I","i"," ")),"") | E434: =IF(E433="O",IF(A434="Prioritaire",IF(A433="I","p i","p"),IF(A433="I","i"," ")),"")
C441: =IF(C440="C",IF(A441="Prioritaire",IF(A440="I","p i","p"),IF(A440="I","i","")),"") | D441: =IF(D440="E",IF(A441="Prioritaire",IF(A440="I","p i","p"),IF(A440="I","i"," ")),"") | E441: =IF(E440="O",IF(A441="Prioritaire",IF(A440="I","p i","p"),IF(A440="I","i"," ")),"")

Sheet 1.4
A1: =Bilan!B10 -> 1.4 Marquage - Piquetage
C3: C | D3: E | E3: O | F3: Total
B4: Nb quest. | C4: =COUNTIF(C8:C646,C3) -> 7 | D4: =COUNTIF(D8:D646,D3) -> 7 | E4: =COUNTIF(E8:E646,E3) -> 4 | F4: =COUNTA(B8:B646) -> 8
B5: Illust. | C5: =COUNTIF(C8:C646,"i")+COUNTIF(C8:C646,"p i") -> 3 | D5: =COUNTIF(D8:D646,"i")+COUNTIF(D8:D646,"p i") -> 3 | E5: =COUNTIF(E8:E646,"i")+COUNTIF(E8:E646,"p i") -> 4 | F5: =COUNTIF(A8:A646,"I") -> 4
B6: Prio | C6: =COUNTIF(C8:C646,"p")+COUNTIF(C8:C646,"p i") -> 1 | D6: =COUNTIF(D8:D646,"p")+COUNTIF(D8:D646,"p i") -> 1 | E6: =COUNTIF(E8:E646,"p")+COUNTIF(E8:E646,"p i") -> 0 | F6: =COUNTIF(A8:A646,"P") -> 1
B8: 1-4_001 | C8: C | D8: E | F8: Lorsque l’exploitant de réseau ne fournit pas de plan en réponse à la DICT, qui a la responsabilité du marquage-piquetage dans le cadre d'une réunion sur site ?
C9: =IF(C8="C",IF(A9="P",IF(A8="I","p i","p"),IF(A8="I","i","")),"") | D9: =IF(D8="E",IF(A9="P",IF(A8="I","p i","p"),IF(A8="I","i"," ")),"") | E9: =IF(E8="O",IF(A9="P",IF(A8="I","p i","p"),IF(A8="I","i"," ")),"") | F9: A | G9: L’entreprise de travaux
A10: R554-27III | F10: B | G10: Le responsable du projet (ou maître d'ouvrage)
F11: C | G11: L’exploitant du réseau
F12: D | G12: Je ne sais pas
B14: 1-4_002 | C14: C | D14: E | F14: Lorsque l’exploitant a joint un plan au récépissé de DICT, qui a la responsabilité d'effectuer le marquage-piquetage ? | Q14: Prioritaire
A15: P | C15: =IF(C14="C",IF(A15="P",IF(A14="I","p i","p"),IF(A14="I","i","")),"") -> p | D15: =IF(D14="E",IF(A15="P",IF(A14="I","p i","p"),IF(A14="I","i"," ")),"") -> p | E15: =IF(E14="O",IF(A15="P",IF(A14="I","p i","p"),IF(A14="I","i"," ")),"") | F15: A | G15: L’entreprise de travaux
A16: R554-27I | F16: B | G16: Le responsable du projet (ou maître d'ouvrage)
F17: C | G17: L’exploitant
F18: E | G18: Je ne sais pas
B20: 1-4_004 | C20: C | D20: E | F20: Pourquoi le compte rendu de marquage-piquetage doit être transmis à l’exécutant des travaux ?
F21: A | G21: Pour assurer la traçabilité des informations de localisation des réseaux existants
A22: R554-27 | F22: B | G22: Pour permettre à l'exécutant de produire un plan projet du réseau neuf à poser
F23: C | G23: Pour transférer à l'exécutant toute la responsabilité des travaux réalisés
F24: D | G24: Je ne sais pas
B27: 1-4_005 | C27: C | D27: E | F27: Le marquage piquetage doit être effectué pour tout réseau situé dans l'emprise des travaux augmentée de :
C28: =IF(C27="C",IF(A28="P",IF(A27="I","p i","p"),IF(A27="I","i","")),"") | D28: =IF(D27="E",IF(A28="P",IF(A27="I","p i","p"),IF(A27="I","i"," ")),"") | E28: =IF(E27="O",IF(A28="P",IF(A27="I","p i","p"),IF(A27="I","i"," ")),"") | F28: A | G28: 1,5 mètres
A29: R554-27I | F29: B | G29: 2 mètres
F30: C | G30: 3 mètres
F31: D | G31: Je ne sais pas
A33: I | B33: 1-4_006 | C33: C | D33: E | E33: O | F33: Qui doit maintenir en état le marquage piquetage pendant toute la durée des travaux ?
C34: =IF(C33="C",IF(A34="P",IF(A33="I","p i","p"),IF(A33="I","i","")),"") -> i | D34: =IF(D33="E",IF(A34="P",IF(A33="I","p i","p"),IF(A33="I","i"," ")),"") -> i | E34: =IF(E33="O",IF(A34="P",IF(A33="I","p i","p"),IF(A33="I","i"," ")),"") -> i | F34: A | G34: Le service technique de la commune
A35: R554-27IV | F35: B | G35: L’exploitant du réseau
F36: C | G36: L'exécutant des travaux
F37: D | G37: Je ne sais pas
A39: I | B39: 1-4_006b | E39: O | F39: Pendant combien de temps faut-il maintenir en bon état le marquage piquetage ?
C40: =IF(C39="C",IF(A40="P",IF(A39="I","p i","p"),IF(A39="I","i","")),"") | D40: =IF(D39="E",IF(A40="P",IF(A39="I","p i","p"),IF(A39="I","i"," ")),"") | E40: =IF(E39="O",IF(A40="P",IF(A39="I","p i","p"),IF(A39="I","i"," ")),"") -> i | F40: A | G40: Jusqu'à l'enlèvement de la couche dure de la chaussée
A41: R554-27IV | F41: B | G41: Jusqu'à la fin du terrassement avec les engins lourds
F42: C | G42: Pendant toute la durée du chantier
F43: D | G43: Je ne sais pas
A45: I | B45: 1-4_007 | C45: C | D45: E | E45: O | F45: Sur un chantier, un marquage au sol de couleur jaune signale un réseau :
C46: =IF(C45="C",IF(A46="P",IF(A45="I","p i","p"),IF(A45="I","i","")),"") -> i | D46: =IF(D45="E",IF(A46="P",IF(A45="I","p i","p"),IF(A45="I","i"," ")),"") -> i | E46: =IF(E45="O",IF(A46="P",IF(A45="I","p i","p"),IF(A45="I","i"," ")),"") -> i | F46: A | G46: D'eaux usées
A47: NF S 70-003-1 | F47: B | G47: De gaz
A48: annexe E | F48: C | G48: De télécommunication
F49: D | G49: Je ne sais pas
A51: I | B51: 1-4_008 | C51: C | D51: E | E51: O | F51: Quelle mesure permet de prévenir un risque d'endommagement d'une canalisation électrique enterrée ?
C52: =IF(C51="C",IF(A52="P",IF(A51="I","p i","p"),IF(A51="I","i","")),"") -> i | D52: =IF(D51="E",IF(A52="P",IF(A51="I","p i","p"),IF(A51="I","i"," ")),"") -> i | E52: =IF(E51="O",IF(A52="P",IF(A51="I","p i","p"),IF(A51="I","i"," ")),"") -> i | F52: A | G52: La mise hors tension de la canalisation électrique
A53: NF C 18-510 | F53: B | G53: La consignation de la canalisation électrique
F54: C | G54: La localisation précise de la canalisation et son marquage au sol
F55: D | G55: Je ne sais pas
C86: =IF(C85="C",IF(A86="P",IF(A85="I","p i","p"),IF(A85="I","i","")),"") | D86: =IF(D85="E",IF(A86="P",IF(A85="I","p i","p"),IF(A85="I","i"," ")),"") | E86: =IF(E85="O",IF(A86="P",IF(A85="I","p i","p"),IF(A85="I","i"," ")),"")
C93: =IF(C92="C",IF(A93="P",IF(A92="I","p i","p"),IF(A92="I","i","")),"") | D93: =IF(D92="E",IF(A93="P",IF(A92="I","p i","p"),IF(A92="I","i"," ")),"") | E93: =IF(E92="O",IF(A93="P",IF(A92="I","p i","p"),IF(A92="I","i"," ")),"")
C100: =IF(C99="C",IF(A100="P",IF(A99="I","p i","p"),IF(A99="I","i","")),"") | D100: =IF(D99="E",IF(A100="P",IF(A99="I","p i","p"),IF(A99="I","i"," ")),"") | E100: =IF(E99="O",IF(A100="P",IF(A99="I","p i","p"),IF(A99="I","i"," ")),"")
C107: =IF(C106="C",IF(A107="P",IF(A106="I","p i","p"),IF(A106="I","i","")),"") | D107: =IF(D106="E",IF(A107="P",IF(A106="I","p i","p"),IF(A106="I","i"," ")),"") | E107: =IF(E106="O",IF(A107="P",IF(A106="I","p i","p"),IF(A106="I","i"," ")),"")
C114: =IF(C113="C",IF(A114="P",IF(A113="I","p i","p"),IF(A113="I","i","")),"") | D114: =IF(D113="E",IF(A114="P",IF(A113="I","p i","p"),IF(A113="I","i"," ")),"") | E114: =IF(E113="O",IF(A114="P",IF(A113="I","p i","p"),IF(A113="I","i"," ")),"")
C121: =IF(C120="C",IF(A121="P",IF(A120="I","p i","p"),IF(A120="I","i","")),"") | D121: =IF(D120="E",IF(A121="P",IF(A120="I","p i","p"),IF(A120="I","i"," ")),"") | E121: =IF(E120="O",IF(A121="P",IF(A120="I","p i","p"),IF(A120="I","i"," ")),"")
C128: =IF(C127="C",IF(A128="P",IF(A127="I","p i","p"),IF(A127="I","i","")),"") | D128: =IF(D127="E",IF(A128="P",IF(A127="I","p i","p"),IF(A127="I","i"," ")),"") | E128: =IF(E127="O",IF(A128="P",IF(A127="I","p i","p"),IF(A127="I","i"," ")),"")
C135: =IF(C134="C",IF(A135="P",IF(A134="I","p i","p"),IF(A134="I","i","")),"") | D135: =IF(D134="E",IF(A135="P",IF(A134="I","p i","p"),IF(A134="I","i"," ")),"") | E135: =IF(E134="O",IF(A135="P",IF(A134="I","p i","p"),IF(A134="I","i"," ")),"")
C142: =IF(C141="C",IF(A142="P",IF(A141="I","p i","p"),IF(A141="I","i","")),"") | D142: =IF(D141="E",IF(A142="P",IF(A141="I","p i","p"),IF(A141="I","i"," ")),"") | E142: =IF(E141="O",IF(A142="P",IF(A141="I","p i","p"),IF(A141="I","i"," ")),"")
C149: =IF(C148="C",IF(A149="P",IF(A148="I","p i","p"),IF(A148="I","i","")),"") | D149: =IF(D148="E",IF(A149="P",IF(A148="I","p i","p"),IF(A148="I","i"," ")),"") | E149: =IF(E148="O",IF(A149="P",IF(A148="I","p i","p"),IF(A148="I","i"," ")),"")
C156: =IF(C155="C",IF(A156="P",IF(A155="I","p i","p"),IF(A155="I","i","")),"") | D156: =IF(D155="E",IF(A156="P",IF(A155="I","p i","p"),IF(A155="I","i"," ")),"") | E156: =IF(E155="O",IF(A156="P",IF(A155="I","p i","p"),IF(A155="I","i"," ")),"")
C163: =IF(C162="C",IF(A163="P",IF(A162="I","p i","p"),IF(A162="I","i","")),"") | D163: =IF(D162="E",IF(A163="P",IF(A162="I","p i","p"),IF(A162="I","i"," ")),"") | E163: =IF(E162="O",IF(A163="P",IF(A162="I","p i","p"),IF(A162="I","i"," ")),"")
... C177: =IF(C176="C",IF(A177="P",IF(A176="I","p i","p"),IF(A176="I","i","")),"") | D177: =IF(D176="E",IF(A177="P",IF(A176="I","p i","p"),IF(A176="I","i"," ")),"") | E177: =IF(E176="O",IF(A177="P",IF(A176="I","p i","p"),IF(A176="I","i"," ")),"")
C178: =IF(C177="C",IF(A178="Prioritaire",IF(A177="I","p i","p"),IF(A177="I","i","")),"") | D178: =IF(D177="E",IF(A178="Prioritaire",IF(A177="I","p i","p"),IF(A177="I","i"," ")),"") | E178: =IF(E177="O",IF(A178="Prioritaire",IF(A177="I","p i","p"),IF(A177="I","i"," ")),"")
C184: =IF(C183="C",IF(A184="P",IF(A183="I","p i","p"),IF(A183="I","i","")),"") | D184: =IF(D183="E",IF(A184="P",IF(A183="I","p i","p"),IF(A183="I","i"," ")),"") | E184: =IF(E183="O",IF(A184="P",IF(A183="I","p i","p"),IF(A183="I","i"," ")),"")
C191: =IF(C190="C",IF(A191="P",IF(A190="I","p i","p"),IF(A190="I","i","")),"") | D191: =IF(D190="E",IF(A191="P",IF(A190="I","p i","p"),IF(A190="I","i"," ")),"") | E191: =IF(E190="O",IF(A191="P",IF(A190="I","p i","p"),IF(A190="I","i"," ")),"")
C198: =IF(C197="C",IF(A198="P",IF(A197="I","p i","p"),IF(A197="I","i","")),"") | D198: =IF(D197="E",IF(A198="P",IF(A197="I","p i","p"),IF(A197="I","i"," ")),"") | E198: =IF(E197="O",IF(A198="P",IF(A197="I","p i","p"),IF(A197="I","i"," ")),"")
C205: =IF(C204="C",IF(A205="P",IF(A204="I","p i","p"),IF(A204="I","i","")),"") | D205: =IF(D204="E",IF(A205="P",IF(A204="I","p i","p"),IF(A204="I","i"," ")),"") | E205: =IF(E204="O",IF(A205="P",IF(A204="I","p i","p"),IF(A204="I","i"," ")),"")
C212: =IF(C211="C",IF(A212="P",IF(A211="I","p i","p"),IF(A211="I","i","")),"") | D212: =IF(D211="E",IF(A212="P",IF(A211="I","p i","p"),IF(A211="I","i"," ")),"") | E212: =IF(E211="O",IF(A212="P",IF(A211="I","p i","p"),IF(A211="I","i"," ")),"")
C219: =IF(C218="C",IF(A219="P",IF(A218="I","p i","p"),IF(A218="I","i","")),"") | D219: =IF(D218="E",IF(A219="P",IF(A218="I","p i","p"),IF(A218="I","i"," ")),"") | E219: =IF(E218="O",IF(A219="P",IF(A218="I","p i","p"),IF(A218="I","i"," ")),"")
C226: =IF(C225="C",IF(A226="P",IF(A225="I","p i","p"),IF(A225="I","i","")),"") | D226: =IF(D225="E",IF(A226="P",IF(A225="I","p i","p"),IF(A225="I","i"," ")),"") | E226: =IF(E225="O",IF(A226="P",IF(A225="I","p i","p"),IF(A225="I","i"," ")),"")
C233: =IF(C232="C",IF(A233="P",IF(A232="I","p i","p"),IF(A232="I","i","")),"") | D233: =IF(D232="E",IF(A233="P",IF(A232="I","p i","p"),IF(A232="I","i"," ")),"") | E233: =IF(E232="O",IF(A233="P",IF(A232="I","p i","p"),IF(A232="I","i"," ")),"")
C240: =IF(C239="C",IF(A240="P",IF(A239="I","p i","p"),IF(A239="I","i","")),"") | D240: =IF(D239="E",IF(A240="P",IF(A239="I","p i","p"),IF(A239="I","i"," ")),"") | E240: =IF(E239="O",IF(A240="P",IF(A239="I","p i","p"),IF(A239="I","i"," ")),"")
C247: =IF(C246="C",IF(A247="P",IF(A246="I","p i","p"),IF(A246="I","i","")),"") | D247: =IF(D246="E",IF(A247="P",IF(A246="I","p i","p"),IF(A246="I","i"," ")),"") | E247: =IF(E246="O",IF(A247="P",IF(A246="I","p i","p"),IF(A246="I","i"," ")),"")
C254: =IF(C253="C",IF(A254="P",IF(A253="I","p i","p"),IF(A253="I","i","")),"") | D254: =IF(D253="E",IF(A254="P",IF(A253="I","p i","p"),IF(A253="I","i"," ")),"") | E254: =IF(E253="O",IF(A254="P",IF(A253="I","p i","p"),IF(A253="I","i"," ")),"")
C261: =IF(C260="C",IF(A261="P",IF(A260="I","p i","p"),IF(A260="I","i","")),"") | D261: =IF(D260="E",IF(A261="P",IF(A260="I","p i","p"),IF(A260="I","i"," ")),"") | E261: =IF(E260="O",IF(A261="P",IF(A260="I","p i","p"),IF(A260="I","i"," ")),"")
... C443: =IF(C442="C",IF(A443="P",IF(A442="I","p i","p"),IF(A442="I","i","")),"") | D443: =IF(D442="E",IF(A443="P",IF(A442="I","p i","p"),IF(A442="I","i"," ")),"") | E443: =IF(E442="O",IF(A443="P",IF(A442="I","p i","p"),IF(A442="I","i"," ")),"")
C450: =IF(C449="C",IF(A450="Prioritaire",IF(A449="I","p i","p"),IF(A449="I","i","")),"") | D450: =IF(D449="E",IF(A450="Prioritaire",IF(A449="I","p i","p"),IF(A449="I","i"," ")),"") | E450: =IF(E449="O",IF(A450="Prioritaire",IF(A449="I","p i","p"),IF(A449="I","i"," ")),"")
C457: =IF(C456="C",IF(A457="Prioritaire",IF(A456="I","p i","p"),IF(A456="I","i","")),"") | D457: =IF(D456="E",IF(A457="Prioritaire",IF(A456="I","p i","p"),IF(A456="I","i"," ")),"") | E457: =IF(E456="O",IF(A457="Prioritaire",IF(A456="I","p i","p"),IF(A456="I","i"," ")),"")
C464: =IF(C463="C",IF(A464="Prioritaire",IF(A463="I","p i","p"),IF(A463="I","i","")),"") | D464: =IF(D463="E",IF(A464="Prioritaire",IF(A463="I","p i","p"),IF(A463="I","i"," ")),"") | E464: =IF(E463="O",IF(A464="Prioritaire",IF(A463="I","p i","p"),IF(A463="I","i"," ")),"")

Sheet 1.5
A1: =Bilan!B11 -> 1.5 Compétences des personnels
C3: C | D3: E | E3: O | F3: Total
B4: Nb quest. | C4: =COUNTIF(C14:C624,C3) -> 2 | D4: =COUNTIF(D14:D624,D3) -> 0 | E4: =COUNTIF(E14:E624,E3) -> 0 | F4: =COUNTA(B14:B624) -> 2
B5: Illust. | C5: =COUNTIF(C14:C624,"i")+COUNTIF(C14:C624,"p i") -> 0 | D5: =COUNTIF(D14:D624,"i")+COUNTIF(D14:D624,"p i") -> 0 | E5: =COUNTIF(E14:E624,"i")+COUNTIF(E14:E624,"p i") -> 0 | F5: =COUNTIF(A14:A624,"I") -> 0
B6: Prio | C6: =COUNTIF(C14:C624,"p")+COUNTIF(C14:C624,"p i") -> 0 | D6: =COUNTIF(D14:D624,"p")+COUNTIF(D14:D624,"p i") -> 0 | E6: =COUNTIF(E14:E624,"p")+COUNTIF(E14:E624,"p i") -> 0 | F6: =COUNTIF(A14:A624,"P") -> 0
B8: 1-5_001 | C8: C | D8: E | F8: Lequel de ces éléments ne permet pas la délivrance de l'Autorisation d'Intervention à Proximité des Réseaux ?
F9: A | G9: Un diplôme obtenu depuis plus de 5 ans
A10: A15-2-12/art21I-3° | F10: B | G10: Une attestation de compétences en cours de validité
F11: C | G11: Un CACES en cours de validité prenant en compte la réforme anti-endommagement
F12: D | G12: Je ne sais pas
B14: 1-5_002 | C14: C | F14: Un responsable de projet (ou maître d'ouvrage) prévoit de faire intervenir plusieurs entreprises sur un même chantier de travaux. L'autorisation d'intervention à proximité des réseaux (AIPR) niveau concepteur est requise pour au moins :
C15: =IF(C14="C",IF(A15="P",IF(A14="I","p i","p"),IF(A14="I","i","")),"") | D15: =IF(D14="E",IF(A15="P",IF(A14="I","p i","p"),IF(A14="I","i"," ")),"") | E15: =IF(E14="O",IF(A15="P",IF(A14="I","p i","p"),IF(A14="I","i"," ")),"") | F15: A | G15: Une personne chargée par le responsable de projet (ou maître d'ouvrage) de préparer et suivre le projet de travaux
A16: A15-2-12/art21I | F16: B | G16: Deux personnes chargées par le responsable de projet (ou maître d'ouvrage) de préparer et suivre le projet de travaux
F17: C | G17: L'ensemble des personnes chargées par le responsable de projet (ou maître d'ouvrage) de préparer et suivre le projet de travaux
F18: D | G18: Je ne sais pas
B21: 1-5_011 | C21: C | F21: L'exploitant de réseau doit-il prévoir, pour au moins une personne travaillant pour son compte, une AIPR "concepteur" ?
C22: =IF(C21="C",IF(A22="P",IF(A21="I","p i","p"),IF(A21="I","i","")),"") | D22: =IF(D21="E",IF(A22="P",IF(A21="I","p i","p"),IF(A21="I","i"," ")),"") | E22: =IF(E21="O",IF(A22="P",IF(A21="I","p i","p"),IF(A21="I","i"," ")),"") | F22: A | G22: Jamais
A23: A15-2-12/art21I | F23: B | G23: Toujours, pour répondre aux DICT qu'il reçoit
F24: C | G24: Uniquement lorsqu'il intervient comme responsable de projet de travaux
F25: D | G25: Je ne sais pas
C36: =IF(C35="C",IF(A36="P",IF(A35="I","p i","p"),IF(A35="I","i","")),"") | D36: =IF(D35="E",IF(A36="P",IF(A35="I","p i","p"),IF(A35="I","i"," ")),"") | E36: =IF(E35="O",IF(A36="P",IF(A35="I","p i","p"),IF(A35="I","i"," ")),"")
C43: =IF(C42="C",IF(A43="P",IF(A42="I","p i","p"),IF(A42="I","i","")),"") | D43: =IF(D42="E",IF(A43="P",IF(A42="I","p i","p"),IF(A42="I","i"," ")),"") | E43: =IF(E42="O",IF(A43="P",IF(A42="I","p i","p"),IF(A42="I","i"," ")),"")
C50: =IF(C49="C",IF(A50="P",IF(A49="I","p i","p"),IF(A49="I","i","")),"") | D50: =IF(D49="E",IF(A50="P",IF(A49="I","p i","p"),IF(A49="I","i"," ")),"") | E50: =IF(E49="O",IF(A50="P",IF(A49="I","p i","p"),IF(A49="I","i"," ")),"")
C57: =IF(C56="C",IF(A57="P",IF(A56="I","p i","p"),IF(A56="I","i","")),"") | D57: =IF(D56="E",IF(A57="P",IF(A56="I","p i","p"),IF(A56="I","i"," ")),"") | E57: =IF(E56="O",IF(A57="P",IF(A56="I","p i","p"),IF(A56="I","i"," ")),"")
C64: =IF(C63="C",IF(A64="P",IF(A63="I","p i","p"),IF(A63="I","i","")),"") | D64: =IF(D63="E",IF(A64="P",IF(A63="I","p i","p"),IF(A63="I","i"," ")),"") | E64: =IF(E63="O",IF(A64="P",IF(A63="I","p i","p"),IF(A63="I","i"," ")),"")
C71: =IF(C70="C",IF(A71="P",IF(A70="I","p i","p"),IF(A70="I","i","")),"") | D71: =IF(D70="E",IF(A71="P",IF(A70="I","p i","p"),IF(A70="I","i"," ")),"") | E71: =IF(E70="O",IF(A71="P",IF(A70="I","p i","p"),IF(A70="I","i"," ")),"")
C78: =IF(C77="C",IF(A78="P",IF(A77="I","p i","p"),IF(A77="I","i","")),"") | D78: =IF(D77="E",IF(A78="P",IF(A77="I","p i","p"),IF(A77="I","i"," ")),"") | E78: =IF(E77="O",IF(A78="P",IF(A77="I","p i","p"),IF(A77="I","i"," ")),"")
C85: =IF(C84="C",IF(A85="P",IF(A84="I","p i","p"),IF(A84="I","i","")),"") | D85: =IF(D84="E",IF(A85="P",IF(A84="I","p i","p"),IF(A84="I","i"," ")),"") | E85: =IF(E84="O",IF(A85="P",IF(A84="I","p i","p"),IF(A84="I","i"," ")),"")
C92: =IF(C91="C",IF(A92="P",IF(A91="I","p i","p"),IF(A91="I","i","")),"") | D92: =IF(D91="E",IF(A92="P",IF(A91="I","p i","p"),IF(A91="I","i"," ")),"") | E92: =IF(E91="O",IF(A92="P",IF(A91="I","p i","p"),IF(A91="I","i"," ")),"")
C99: =IF(C98="C",IF(A99="P",IF(A98="I","p i","p"),IF(A98="I","i","")),"") | D99: =IF(D98="E",IF(A99="P",IF(A98="I","p i","p"),IF(A98="I","i"," ")),"") | E99: =IF(E98="O",IF(A99="P",IF(A98="I","p i","p"),IF(A98="I","i"," ")),"")
C106: =IF(C105="C",IF(A106="P",IF(A105="I","p i","p"),IF(A105="I","i","")),"") | D106: =IF(D105="E",IF(A106="P",IF(A105="I","p i","p"),IF(A105="I","i"," ")),"") | E106: =IF(E105="O",IF(A106="P",IF(A105="I","p i","p"),IF(A105="I","i"," ")),"")
C113: =IF(C112="C",IF(A113="P",IF(A112="I","p i","p"),IF(A112="I","i","")),"") | D113: =IF(D112="E",IF(A113="P",IF(A112="I","p i","p"),IF(A112="I","i"," ")),"") | E113: =IF(E112="O",IF(A113="P",IF(A112="I","p i","p"),IF(A112="I","i"," ")),"")
... C155: =IF(C154="C",IF(A155="P",IF(A154="I","p i","p"),IF(A154="I","i","")),"") | D155: =IF(D154="E",IF(A155="P",IF(A154="I","p i","p"),IF(A154="I","i"," ")),"") | E155: =IF(E154="O",IF(A155="P",IF(A154="I","p i","p"),IF(A154="I","i"," ")),"")
C156: =IF(C155="C",IF(A156="Prioritaire",IF(A155="I","p i","p"),IF(A155="I","i","")),"") | D156: =IF(D155="E",IF(A156="Prioritaire",IF(A155="I","p i","p"),IF(A155="I","i"," ")),"") | E156: =IF(E155="O",IF(A156="Prioritaire",IF(A155="I","p i","p"),IF(A155="I","i"," ")),"")
C162: =IF(C161="C",IF(A162="P",IF(A161="I","p i","p"),IF(A161="I","i","")),"") | D162: =IF(D161="E",IF(A162="P",IF(A161="I","p i","p"),IF(A161="I","i"," ")),"") | E162: =IF(E161="O",IF(A162="P",IF(A161="I","p i","p"),IF(A161="I","i"," ")),"")
C169: =IF(C168="C",IF(A169="P",IF(A168="I","p i","p"),IF(A168="I","i","")),"") | D169: =IF(D168="E",IF(A169="P",IF(A168="I","p i","p"),IF(A168="I","i"," ")),"") | E169: =IF(E168="O",IF(A169="P",IF(A168="I","p i","p"),IF(A168="I","i"," ")),"")
C176: =IF(C175="C",IF(A176="P",IF(A175="I","p i","p"),IF(A175="I","i","")),"") | D176: =IF(D175="E",IF(A176="P",IF(A175="I","p i","p"),IF(A175="I","i"," ")),"") | E176: =IF(E175="O",IF(A176="P",IF(A175="I","p i","p"),IF(A175="I","i"," ")),"")
C183: =IF(C182="C",IF(A183="P",IF(A182="I","p i","p"),IF(A182="I","i","")),"") | D183: =IF(D182="E",IF(A183="P",IF(A182="I","p i","p"),IF(A182="I","i"," ")),"") | E183: =IF(E182="O",IF(A183="P",IF(A182="I","p i","p"),IF(A182="I","i"," ")),"")
C190: =IF(C189="C",IF(A190="P",IF(A189="I","p i","p"),IF(A189="I","i","")),"") | D190: =IF(D189="E",IF(A190="P",IF(A189="I","p i","p"),IF(A189="I","i"," ")),"") | E190: =IF(E189="O",IF(A190="P",IF(A189="I","p i","p"),IF(A189="I","i"," ")),"")
C197: =IF(C196="C",IF(A197="P",IF(A196="I","p i","p"),IF(A196="I","i","")),"") | D197: =IF(D196="E",IF(A197="P",IF(A196="I","p i","p"),IF(A196="I","i"," ")),"") | E197: =IF(E196="O",IF(A197="P",IF(A196="I","p i","p"),IF(A196="I","i"," ")),"")
C204: =IF(C203="C",IF(A204="P",IF(A203="I","p i","p"),IF(A203="I","i","")),"") | D204: =IF(D203="E",IF(A204="P",IF(A203="I","p i","p"),IF(A203="I","i"," ")),"") | E204: =IF(E203="O",IF(A204="P",IF(A203="I","p i","p"),IF(A203="I","i"," ")),"")
C211: =IF(C210="C",IF(A211="P",IF(A210="I","p i","p"),IF(A210="I","i","")),"") | D211: =IF(D210="E",IF(A211="P",IF(A210="I","p i","p"),IF(A210="I","i"," ")),"") | E211: =IF(E210="O",IF(A211="P",IF(A210="I","p i","p"),IF(A210="I","i"," ")),"")
C218: =IF(C217="C",IF(A218="P",IF(A217="I","p i","p"),IF(A217="I","i","")),"") | D218: =IF(D217="E",IF(A218="P",IF(A217="I","p i","p"),IF(A217="I","i"," ")),"") | E218: =IF(E217="O",IF(A218="P",IF(A217="I","p i","p"),IF(A217="I","i"," ")),"")
C225: =IF(C224="C",IF(A225="P",IF(A224="I","p i","p"),IF(A224="I","i","")),"") | D225: =IF(D224="E",IF(A225="P",IF(A224="I","p i","p"),IF(A224="I","i"," ")),"") | E225: =IF(E224="O",IF(A225="P",IF(A224="I","p i","p"),IF(A224="I","i"," ")),"")
C232: =IF(C231="C",IF(A232="P",IF(A231="I","p i","p"),IF(A231="I","i","")),"") | D232: =IF(D231="E",IF(A232="P",IF(A231="I","p i","p"),IF(A231="I","i"," ")),"") | E232: =IF(E231="O",IF(A232="P",IF(A231="I","p i","p"),IF(A231="I","i"," ")),"")
C239: =IF(C238="C",IF(A239="P",IF(A238="I","p i","p"),IF(A238="I","i","")),"") | D239: =IF(D238="E",IF(A239="P",IF(A238="I","p i","p"),IF(A238="I","i"," ")),"") | E239: =IF(E238="O",IF(A239="P",IF(A238="I","p i","p"),IF(A238="I","i"," ")),"")
... C421: =IF(C420="C",IF(A421="P",IF(A420="I","p i","p"),IF(A420="I","i","")),"") | D421: =IF(D420="E",IF(A421="P",IF(A420="I","p i","p"),IF(A420="I","i"," ")),"") | E421: =IF(E420="O",IF(A421="P",IF(A420="I","p i","p"),IF(A420="I","i"," ")),"")
C428: =IF(C427="C",IF(A428="Prioritaire",IF(A427="I","p i","p"),IF(A427="I","i","")),"") | D428: =IF(D427="E",IF(A428="Prioritaire",IF(A427="I","p i","p"),IF(A427="I","i"," ")),"") | E428: =IF(E427="O",IF(A428="Prioritaire",IF(A427="I","p i","p"),IF(A427="I","i"," ")),"")
C435: =IF(C434="C",IF(A435="Prioritaire",IF(A434="I","p i","p"),IF(A434="I","i","")),"") | D435: =IF(D434="E",IF(A435="Prioritaire",IF(A434="I","p i","p"),IF(A434="I","i"," ")),"") | E435: =IF(E434="O",IF(A435="Prioritaire",IF(A434="I","p i","p"),IF(A434="I","i"," ")),"")
C442: =IF(C441="C",IF(A442="Prioritaire",IF(A441="I","p i","p"),IF(A441="I","i","")),"") | D442: =IF(D441="E",IF(A442="Prioritaire",IF(A441="I","p i","p"),IF(A441="I","i"," ")),"") | E442: =IF(E441="O",IF(A442="Prioritaire",IF(A441="I","p i","p"),IF(A441="I","i"," ")),"")

Sheet 1.6
A1: =Bilan!B12 -> 1.6 Cartographie
C3: C | D3: E | E3: O | F3: Total
B4: Nb quest. | C4: =COUNTIF(C8:C545,C3) -> 8 | D4: =COUNTIF(D8:D545,D3) -> 8 | E4: =COUNTIF(E8:E545,E3) -> 1 | F4: =COUNTA(B8:B545) -> 9
B5: Illust. | C5: =COUNTIF(C8:C545,"i")+COUNTIF(C8:C545,"p i") -> 1 | D5: =COUNTIF(D8:D545,"i")+COUNTIF(D8:D545,"p i") -> 1 | E5: =COUNTIF(E8:E545,"i")+COUNTIF(E8:E545,"p i") -> 1 | F5: =COUNTIF(A8:A545,"I") -> 2
B6: Prio | C6: =COUNTIF(C8:C545,"p")+COUNTIF(C8:C545,"p i") -> 1 | D6: =COUNTIF(D8:D545,"p")+COUNTIF(D8:D545,"p i") -> 1 | E6: =COUNTIF(E8:E545,"p")+COUNTIF(E8:E545,"p i") -> 0 | F6: =COUNTIF(A8:A545,"P") -> 1
B8: 1-6_001 | C8: C | D8: E | F8: En matière de cartographie, laquelle de ces affirmations est exacte ?
C9: =IF(C8="C",IF(A9="P",IF(A8="I","p i","p"),IF(A8="I","i","")),"") | D9: =IF(D8="E",IF(A9="P",IF(A8="I","p i","p"),IF(A8="I","i"," ")),"") | E9: =IF(E8="O",IF(A9="P",IF(A8="I","p i","p"),IF(A8="I","i"," ")),"") | F9: A | G9: La classe de précision figure dans le récépissé de l’exploitant à une DT ou DICT
A10: A15-2-12/art5 | F10: B | G10: Tous les branchements gaz sont reportés sur la cartographie
F11: C | G11: Les indications quant à la position des ouvrages enterrés figurant sur les plans sont précises à plus ou moins 40 cm
F12: D | G12: Je ne sais pas
B14: 1-6_003 | C14: C | D14: E | F14: En topographie, le terme planimétrie se rapporte à la localisation d'un point :
C15: =IF(C14="C",IF(A15="P",IF(A14="I","p i","p"),IF(A14="I","i","")),"") | D15: =IF(D14="E",IF(A15="P",IF(A14="I","p i","p"),IF(A14="I","i"," ")),"") | E15: =IF(E14="O",IF(A15="P",IF(A14="I","p i","p"),IF(A14="I","i"," ")),"") | F15: A | G15: A l'horizontale
A16: NFS70-003-3 | F16: B | G16: A la verticale
F17: C | G17: Sur une droite
F18: D | G18: Je ne sais pas
B20: 1-6_004 | C20: C | D20: E | F20: La génératrice supérieure d'un réseau enterré est :
C21: =IF(C20="C",IF(A21="P",IF(A20="I","p i","p"),IF(A20="I","i","")),"") | D21: =IF(D20="E",IF(A21="P",IF(A20="I","p i","p"),IF(A20="I","i"," ")),"") | E21: =IF(E20="O",IF(A21="P",IF(A20="I","p i","p"),IF(A20="I","i"," ")),"") | F21: A | G21: Le point le plus haut de la paroi extérieure de ce réseau ou de son fourreau
A22: A15-2-12/art15 | F22: B | G22: Le fil d'eau de ce réseau ou de son fourreau
F23: C | G23: L'axe central de ce réseau ou de son fourreau
F24: D | G24: Je ne sais pas
B27: 1-6_011 | C27: C | D27: E | F27: L'échelle d'un plan est :
C28: =IF(C27="C",IF(A28="P",IF(A27="I","p i","p"),IF(A27="I","i","")),"") | D28: =IF(D27="E",IF(A28="P",IF(A27="I","p i","p"),IF(A27="I","i"," ")),"") | E28: =IF(E27="O",IF(A28="P",IF(A27="I","p i","p"),IF(A27="I","i"," ")),"") | F28: A | G28: Le rapport entre la longueur réelle d'un objet sur le terrain et la longueur de cet objet sur le plan
A29: NFS70-003-3 | F29: B | G29: La précision du plan
F30: C | G30: Le rapport entre la longueur d'un objet sur le plan et la longueur réelle de cet objet sur le terrain
F31: D | G31: Je ne sais pas
A33: I | B33: 1-6_016ce | C33: C | D33: E | F33: Lorsque la profondeur d'un réseau est marquée au sol, elle indique la profondeur :
A34: P | C34: =IF(C33="C",IF(A34="P",IF(A33="I","p i","p"),IF(A33="I","i","")),"") -> p i | D34: =IF(D33="E",IF(A34="P",IF(A33="I","p i","p"),IF(A33="I","i"," ")),"") -> p i | E34: =IF(E33="O",IF(A34="P",IF(A33="I","p i","p"),IF(A33="I","i"," ")),"") | F34: A | G34: Du fil de l'eau du réseau ou de son fourreau
A35: NFS70-003-3 | F35: B | G35: De la génératrice supérieure du réseau ou de son fourreau
F36: C | G36: Du grillage avertisseur du réseau
F37: D | G37: Je ne sais pas
A39: I | B39: 1-6_016o | E39: O | F39: Lorsque la profondeur d'un réseau est marquée au sol, elle indique la profondeur :
C40: =IF(C39="C",IF(A40="P",IF(A39="I","p i","p"),IF(A39="I","i","")),"") | D40: =IF(D39="E",IF(A40="P",IF(A39="I","p i","p"),IF(A39="I","i"," ")),"") | E40: =IF(E39="O",IF(A40="P",IF(A39="I","p i","p"),IF(A39="I","i"," ")),"") -> i | F40: A | G40: Du fond de fouille (sous le tuyau)
A41: NFS70-003-3 | F41: B | G41: De la génératrice supérieure du réseau (au dessus du tuyau)
F42: C | G42: Du grillage avertisseur du réseau
F43: D | G43: Je ne sais pas
B45: 1-6_018 | C45: C | D45: E | F45: Pour une échelle de plan au 1/200, 20 mètres sur le terrain correspondent sur le plan à :
F46: A | G46: 2 cm
A47: NFS70-003-3 | F47: B | G47: 10 cm
F48: C | G48: 20 cm
F49: D | G49: Je ne sais pas
B52: 1-6_027 | C52: C | D52: E | F52: Pour une échelle de plan au 1/200, 1 cm sur le plan représente combien sur le terrain ?
C53: =IF(C52="C",IF(A53="P",IF(A52="I","p i","p"),IF(A52="I","i","")),"") | D53: =IF(D52="E",IF(A53="P",IF(A52="I","p i","p"),IF(A52="I","i"," ")),"") | E53: =IF(E52="O",IF(A53="P",IF(A52="I","p i","p"),IF(A52="I","i"," ")),"") | F53: A | G53: Deux mètres
A54: NFS70-003-3 | F54: B | G54: Vingt mètres
F55: C | G55: Deux cents mètres
F56: D | G56: Je ne sais pas
B58: 1-6_035 | C58: C | D58: E | F58: En topographie, le terme altimétrie se rapporte à la localisation d'un point :
C59: =IF(C58="C",IF(A59="P",IF(A58="I","p i","p"),IF(A58="I","i","")),"") | D59: =IF(D58="E",IF(A59="P",IF(A58="I","p i","p"),IF(A58="I","i"," ")),"") | E59: =IF(E58="O",IF(A59="P",IF(A58="I","p i","p"),IF(A58="I","i"," ")),"") | F59: A | G59: A l'horizontale
A60: NFS70-003-3 | F60: B | G60: A la verticale
F61: C | G61: A l'axe du réseau
F62: D | G62: Je ne sais pas
C293: =IF(C292="C",IF(A293="P",IF(A292="I","p i","p"),IF(A292="I","i","")),"") | D293: =IF(D292="E",IF(A293="P",IF(A292="I","p i","p"),IF(A292="I","i"," ")),"") | E293: =IF(E292="O",IF(A293="P",IF(A292="I","p i","p"),IF(A292="I","i"," ")),"")
C300: =IF(C299="C",IF(A300="P",IF(A299="I","p i","p"),IF(A299="I","i","")),"") | D300: =IF(D299="E",IF(A300="P",IF(A299="I","p i","p"),IF(A299="I","i"," ")),"") | E300: =IF(E299="O",IF(A300="P",IF(A299="I","p i","p"),IF(A299="I","i"," ")),"")
C307: =IF(C306="C",IF(A307="P",IF(A306="I","p i","p"),IF(A306="I","i","")),"") | D307: =IF(D306="E",IF(A307="P",IF(A306="I","p i","p"),IF(A306="I","i"," ")),"") | E307: =IF(E306="O",IF(A307="P",IF(A306="I","p i","p"),IF(A306="I","i"," ")),"")
C314: =IF(C313="C",IF(A314="P",IF(A313="I","p i","p"),IF(A313="I","i","")),"") | D314: =IF(D313="E",IF(A314="P",IF(A313="I","p i","p"),IF(A313="I","i"," ")),"") | E314: =IF(E313="O",IF(A314="P",IF(A313="I","p i","p"),IF(A313="I","i"," ")),"")
C321: =IF(C320="C",IF(A321="P",IF(A320="I","p i","p"),IF(A320="I","i","")),"") | D321: =IF(D320="E",IF(A321="P",IF(A320="I","p i","p"),IF(A320="I","i"," ")),"") | E321: =IF(E320="O",IF(A321="P",IF(A320="I","p i","p"),IF(A320="I","i"," ")),"")
C328: =IF(C327="C",IF(A328="P",IF(A327="I","p i","p"),IF(A327="I","i","")),"") | D328: =IF(D327="E",IF(A328="P",IF(A327="I","p i","p"),IF(A327="I","i"," ")),"") | E328: =IF(E327="O",IF(A328="P",IF(A327="I","p i","p"),IF(A327="I","i"," ")),"")
C335: =IF(C334="C",IF(A335="P",IF(A334="I","p i","p"),IF(A334="I","i","")),"") | D335: =IF(D334="E",IF(A335="P",IF(A334="I","p i","p"),IF(A334="I","i"," ")),"") | E335: =IF(E334="O",IF(A335="P",IF(A334="I","p i","p"),IF(A334="I","i"," ")),"")
C342: =IF(C341="C",IF(A342="P",IF(A341="I","p i","p"),IF(A341="I","i","")),"") | D342: =IF(D341="E",IF(A342="P",IF(A341="I","p i","p"),IF(A341="I","i"," ")),"") | E342: =IF(E341="O",IF(A342="P",IF(A341="I","p i","p"),IF(A341="I","i"," ")),"")
C349: =IF(C348="C",IF(A349="P",IF(A348="I","p i","p"),IF(A348="I","i","")),"") | D349: =IF(D348="E",IF(A349="P",IF(A348="I","p i","p"),IF(A348="I","i"," ")),"") | E349: =IF(E348="O",IF(A349="P",IF(A348="I","p i","p"),IF(A348="I","i"," ")),"")
C356: =IF(C355="C",IF(A356="P",IF(A355="I","p i","p"),IF(A355="I","i","")),"") | D356: =IF(D355="E",IF(A356="P",IF(A355="I","p i","p"),IF(A355="I","i"," ")),"") | E356: =IF(E355="O",IF(A356="P",IF(A355="I","p i","p"),IF(A355="I","i"," ")),"")
C363: =IF(C362="C",IF(A363="P",IF(A362="I","p i","p"),IF(A362="I","i","")),"") | D363: =IF(D362="E",IF(A363="P",IF(A362="I","p i","p"),IF(A362="I","i"," ")),"") | E363: =IF(E362="O",IF(A363="P",IF(A362="I","p i","p"),IF(A362="I","i"," ")),"")
C370: =IF(C369="C",IF(A370="P",IF(A369="I","p i","p"),IF(A369="I","i","")),"") | D370: =IF(D369="E",IF(A370="P",IF(A369="I","p i","p"),IF(A369="I","i"," ")),"") | E370: =IF(E369="O",IF(A370="P",IF(A369="I","p i","p"),IF(A369="I","i"," ")),"")
... C398: =IF(C397="C",IF(A398="P",IF(A397="I","p i","p"),IF(A397="I","i","")),"") | D398: =IF(D397="E",IF(A398="P",IF(A397="I","p i","p"),IF(A397="I","i"," ")),"") | E398: =IF(E397="O",IF(A398="P",IF(A397="I","p i","p"),IF(A397="I","i"," ")),"")

Sheet 2.1
A1: =Bilan!B14 -> 2.1 DICT
C3: C | D3: E | E3: O | F3: Total
B4: Nb quest. | C4: =COUNTIF(C8:C629,C3) -> 3 | D4: =COUNTIF(D8:D629,D3) -> 3 | E4: =COUNTIF(E8:E629,E3) -> 0 | F4: =COUNTA(B8:B629) -> 3
B5: Illust. | C5: =COUNTIF(C8:C629,"i")+COUNTIF(C8:C629,"p i") -> 0 | D5: =COUNTIF(D8:D629,"i")+COUNTIF(D8:D629,"p i") -> 0 | E5: =COUNTIF(E8:E629,"i")+COUNTIF(E8:E629,"p i") -> 0 | F5: =COUNTIF(A8:A629,"I") -> 0
B6: Prio | C6: =COUNTIF(C8:C629,"p")+COUNTIF(C8:C629,"p i") -> 1 | D6: =COUNTIF(D8:D629,"p")+COUNTIF(D8:D629,"p i") -> 1 | E6: =COUNTIF(E8:E629,"p")+COUNTIF(E8:E629,"p i") -> 0 | F6: =COUNTIF(A8:A629,"P") -> 1
B8: 2-1_004 | C8: C | D8: E | F8: Qui doit établir la DICT ?
A9: P | C9: =IF(C8="C",IF(A9="P",IF(A8="I","p i","p"),IF(A8="I","i","")),"") -> p | D9: =IF(D8="E",IF(A9="P",IF(A8="I","p i","p"),IF(A8="I","i"," ")),"") -> p | E9: =IF(E8="O",IF(A9="P",IF(A8="I","p i","p"),IF(A8="I","i"," ")),"") | F9: A | G9: Le maître d’ouvrage
A10: R554-25I | F10: B | G10: L’exécutant des travaux
F11: C | G11: L’exploitant de réseau
F12: D | G12: Je ne sais pas
B14: 2-1_005 | C14: C | D14: E | F14: Qui doit envoyer la DICT aux exploitants d'ouvrages ?
F15: A | G15: L'exécutant des travaux ou son Prestataire d'Aide à la Déclaration
A16: R554-25I | F16: B | G16: Le téléservice du guichet unique
F17: C | G17: Le responsable de projet ou son Prestataire d'Aide à la Déclaration
F18: D | G18: Je ne sais pas
B20: 2-1_008 | C20: C | D20: E | F20: Je dois réaliser des travaux à l'aplomb d'une ligne aérienne et je dois prendre en compte la hauteur des conducteurs. Que faire ?
C21: =IF(C20="C",IF(A21="P",IF(A20="I","p i","p"),IF(A20="I","i","")),"") | D21: =IF(D20="E",IF(A21="P",IF(A20="I","p i","p"),IF(A20="I","i"," ")),"") | E21: =IF(E20="O",IF(A21="P",IF(A20="I","p i","p"),IF(A20="I","i"," ")),"") | F21: A | G21: Je me réfère au récépissé de DICT et au guide technique
A22: R554-25 | F22: B | G22: Je vérifie visuellement que la hauteur de surplomb est suffisante
F23: C | G23: J'utilise une perche graduée isolante pour mesurer la hauteur de la ligne
F24: D | G24: Je ne sais pas
C83: =IF(C82="C",IF(A83="P",IF(A82="I","p i","p"),IF(A82="I","i","")),"") | D83: =IF(D82="E",IF(A83="P",IF(A82="I","p i","p"),IF(A82="I","i"," ")),"") | E83: =IF(E82="O",IF(A83="P",IF(A82="I","p i","p"),IF(A82="I","i"," ")),"")
C90: =IF(C89="C",IF(A90="P",IF(A89="I","p i","p"),IF(A89="I","i","")),"") | D90: =IF(D89="E",IF(A90="P",IF(A89="I","p i","p"),IF(A89="I","i"," ")),"") | E90: =IF(E89="O",IF(A90="P",IF(A89="I","p i","p"),IF(A89="I","i"," ")),"")
C97: =IF(C96="C",IF(A97="P",IF(A96="I","p i","p"),IF(A96="I","i","")),"") | D97: =IF(D96="E",IF(A97="P",IF(A96="I","p i","p"),IF(A96="I","i"," ")),"") | E97: =IF(E96="O",IF(A97="P",IF(A96="I","p i","p"),IF(A96="I","i"," ")),"")
C104: =IF(C103="C",IF(A104="P",IF(A103="I","p i","p"),IF(A103="I","i","")),"") | D104: =IF(D103="E",IF(A104="P",IF(A103="I","p i","p"),IF(A103="I","i"," ")),"") | E104: =IF(E103="O",IF(A104="P",IF(A103="I","p i","p"),IF(A103="I","i"," ")),"")
C111: =IF(C110="C",IF(A111="P",IF(A110="I","p i","p"),IF(A110="I","i","")),"") | D111: =IF(D110="E",IF(A111="P",IF(A110="I","p i","p"),IF(A110="I","i"," ")),"") | E111: =IF(E110="O",IF(A111="P",IF(A110="I","p i","p"),IF(A110="I","i"," ")),"")
C118: =IF(C117="C",IF(A118="P",IF(A117="I","p i","p"),IF(A117="I","i","")),"") | D118: =IF(D117="E",IF(A118="P",IF(A117="I","p i","p"),IF(A117="I","i"," ")),"") | E118: =IF(E117="O",IF(A118="P",IF(A117="I","p i","p"),IF(A117="I","i"," ")),"")
C125: =IF(C124="C",IF(A125="P",IF(A124="I","p i","p"),IF(A124="I","i","")),"") | D125: =IF(D124="E",IF(A125="P",IF(A124="I","p i","p"),IF(A124="I","i"," ")),"") | E125: =IF(E124="O",IF(A125="P",IF(A124="I","p i","p"),IF(A124="I","i"," ")),"")
C132: =IF(C131="C",IF(A132="P",IF(A131="I","p i","p"),IF(A131="I","i","")),"") | D132: =IF(D131="E",IF(A132="P",IF(A131="I","p i","p"),IF(A131="I","i"," ")),"") | E132: =IF(E131="O",IF(A132="P",IF(A131="I","p i","p"),IF(A131="I","i"," ")),"")
C139: =IF(C138="C",IF(A139="P",IF(A138="I","p i","p"),IF(A138="I","i","")),"") | D139: =IF(D138="E",IF(A139="P",IF(A138="I","p i","p"),IF(A138="I","i"," ")),"") | E139: =IF(E138="O",IF(A139="P",IF(A138="I","p i","p"),IF(A138="I","i"," ")),"")
C146: =IF(C145="C",IF(A146="P",IF(A145="I","p i","p"),IF(A145="I","i","")),"") | D146: =IF(D145="E",IF(A146="P",IF(A145="I","p i","p"),IF(A145="I","i"," ")),"") | E146: =IF(E145="O",IF(A146="P",IF(A145="I","p i","p"),IF(A145="I","i"," ")),"")
C153: =IF(C152="C",IF(A153="P",IF(A152="I","p i","p"),IF(A152="I","i","")),"") | D153: =IF(D152="E",IF(A153="P",IF(A152="I","p i","p"),IF(A152="I","i"," ")),"") | E153: =IF(E152="O",IF(A153="P",IF(A152="I","p i","p"),IF(A152="I","i"," ")),"")
C160: =IF(C159="C",IF(A160="P",IF(A159="I","p i","p"),IF(A159="I","i","")),"") | D160: =IF(D159="E",IF(A160="P",IF(A159="I","p i","p"),IF(A159="I","i"," ")),"") | E160: =IF(E159="O",IF(A160="P",IF(A159="I","p i","p"),IF(A159="I","i"," ")),"")
C161: =IF(C160="C",IF(A161="Prioritaire",IF(A160="I","p i","p"),IF(A160="I","i","")),"") | D161: =IF(D160="E",IF(A161="Prioritaire",IF(A160="I","p i","p"),IF(A160="I","i"," ")),"") | E161: =IF(E160="O",IF(A161="Prioritaire",IF(A160="I","p i","p"),IF(A160="I","i"," ")),"")
C167: =IF(C166="C",IF(A167="P",IF(A166="I","p i","p"),IF(A166="I","i","")),"") | D167: =IF(D166="E",IF(A167="P",IF(A166="I","p i","p"),IF(A166="I","i"," ")),"") | E167: =IF(E166="O",IF(A167="P",IF(A166="I","p i","p"),IF(A166="I","i"," ")),"")
C174: =IF(C173="C",IF(A174="P",IF(A173="I","p i","p"),IF(A173="I","i","")),"") | D174: =IF(D173="E",IF(A174="P",IF(A173="I","p i","p"),IF(A173="I","i"," ")),"") | E174: =IF(E173="O",IF(A174="P",IF(A173="I","p i","p"),IF(A173="I","i"," ")),"")
C181: =IF(C180="C",IF(A181="P",IF(A180="I","p i","p"),IF(A180="I","i","")),"") | D181: =IF(D180="E",IF(A181="P",IF(A180="I","p i","p"),IF(A180="I","i"," ")),"") | E181: =IF(E180="O",IF(A181="P",IF(A180="I","p i","p"),IF(A180="I","i"," ")),"")
C188: =IF(C187="C",IF(A188="P",IF(A187="I","p i","p"),IF(A187="I","i","")),"") | D188: =IF(D187="E",IF(A188="P",IF(A187="I","p i","p"),IF(A187="I","i"," ")),"") | E188: =IF(E187="O",IF(A188="P",IF(A187="I","p i","p"),IF(A187="I","i"," ")),"")
C195: =IF(C194="C",IF(A195="P",IF(A194="I","p i","p"),IF(A194="I","i","")),"") | D195: =IF(D194="E",IF(A195="P",IF(A194="I","p i","p"),IF(A194="I","i"," ")),"") | E195: =IF(E194="O",IF(A195="P",IF(A194="I","p i","p"),IF(A194="I","i"," ")),"")
C202: =IF(C201="C",IF(A202="P",IF(A201="I","p i","p"),IF(A201="I","i","")),"") | D202: =IF(D201="E",IF(A202="P",IF(A201="I","p i","p"),IF(A201="I","i"," ")),"") | E202: =IF(E201="O",IF(A202="P",IF(A201="I","p i","p"),IF(A201="I","i"," ")),"")
C209: =IF(C208="C",IF(A209="P",IF(A208="I","p i","p"),IF(A208="I","i","")),"") | D209: =IF(D208="E",IF(A209="P",IF(A208="I","p i","p"),IF(A208="I","i"," ")),"") | E209: =IF(E208="O",IF(A209="P",IF(A208="I","p i","p"),IF(A208="I","i"," ")),"")
C216: =IF(C215="C",IF(A216="P",IF(A215="I","p i","p"),IF(A215="I","i","")),"") | D216: =IF(D215="E",IF(A216="P",IF(A215="I","p i","p"),IF(A215="I","i"," ")),"") | E216: =IF(E215="O",IF(A216="P",IF(A215="I","p i","p"),IF(A215="I","i"," ")),"")
C223: =IF(C222="C",IF(A223="P",IF(A222="I","p i","p"),IF(A222="I","i","")),"") | D223: =IF(D222="E",IF(A223="P",IF(A222="I","p i","p"),IF(A222="I","i"," ")),"") | E223: =IF(E222="O",IF(A223="P",IF(A222="I","p i","p"),IF(A222="I","i"," ")),"")
C230: =IF(C229="C",IF(A230="P",IF(A229="I","p i","p"),IF(A229="I","i","")),"") | D230: =IF(D229="E",IF(A230="P",IF(A229="I","p i","p"),IF(A229="I","i"," ")),"") | E230: =IF(E229="O",IF(A230="P",IF(A229="I","p i","p"),IF(A229="I","i"," ")),"")
C237: =IF(C236="C",IF(A237="P",IF(A236="I","p i","p"),IF(A236="I","i","")),"") | D237: =IF(D236="E",IF(A237="P",IF(A236="I","p i","p"),IF(A236="I","i"," ")),"") | E237: =IF(E236="O",IF(A237="P",IF(A236="I","p i","p"),IF(A236="I","i"," ")),"")
C244: =IF(C243="C",IF(A244="P",IF(A243="I","p i","p"),IF(A243="I","i","")),"") | D244: =IF(D243="E",IF(A244="P",IF(A243="I","p i","p"),IF(A243="I","i"," ")),"") | E244: =IF(E243="O",IF(A244="P",IF(A243="I","p i","p"),IF(A243="I","i"," ")),"")
... C440: =IF(C439="C",IF(A440="P",IF(A439="I","p i","p"),IF(A439="I","i","")),"") | D440: =IF(D439="E",IF(A440="P",IF(A439="I","p i","p"),IF(A439="I","i"," ")),"") | E440: =IF(E439="O",IF(A440="P",IF(A439="I","p i","p"),IF(A439="I","i"," ")),"")
C447: =IF(C446="C",IF(A447="Prioritaire",IF(A446="I","p i","p"),IF(A446="I","i","")),"") | D447: =IF(D446="E",IF(A447="Prioritaire",IF(A446="I","p i","p"),IF(A446="I","i"," ")),"") | E447: =IF(E446="O",IF(A447="Prioritaire",IF(A446="I","p i","p"),IF(A446="I","i"," ")),"")

Sheet 2.2
A1: =Bilan!B15 -> 2.2 Analyse des réponses, du DCE et du marché
C3: C | D3: E | E3: O | F3: Total
B4: Nb quest. | C4: =COUNTIF(C8:C708,C3) -> 18 | D4: =COUNTIF(D8:D708,D3) -> 17 | E4: =COUNTIF(E8:E708,E3) -> 0 | F4: =COUNTA(B8:B708) -> 18
B5: Illust. | C5: =COUNTIF(C8:C708,"i")+COUNTIF(C8:C708,"p i") -> 4 | D5: =COUNTIF(D8:D708,"i")+COUNTIF(D8:D708,"p i") -> 4 | E5: =COUNTIF(E8:E708,"i")+COUNTIF(E8:E708,"p i") -> 0 | F5: =COUNTIF(A8:A708,"I") -> 4
B6: Prio | C6: =COUNTIF(C8:C708,"p")+COUNTIF(C8:C708,"p i") -> 3 | D6: =COUNTIF(D8:D708,"p")+COUNTIF(D8:D708,"p i") -> 3 | E6: =COUNTIF(E8:E708,"p")+COUNTIF(E8:E708,"p i") -> 0 | F6: =COUNTIF(A8:A708,"P") -> 3
B8: 2-2_001 | C8: C | D8: E | F8: Si un déclarant n'a pas reçu de réponse à sa DICT dans les délais, pour quel réseau parmi les suivants doit-il attendre avant de commencer les travaux ?
A9: P | C9: =IF(C8="C",IF(A9="P",IF(A8="I","p i","p"),IF(A8="I","i","")),"") -> p | D9: =IF(D8="E",IF(A9="P",IF(A8="I","p i","p"),IF(A8="I","i"," ")),"") -> p | E9: =IF(E8="O",IF(A9="P",IF(A8="I","p i","p"),IF(A8="I","i"," ")),"") | F9: A | G9: Eclairage public
A10: R554-26VI | F10: B | G10: Télécommunication
F11: C | G11: Adduction d'eau
F12: D | G12: Je ne sais pas
B14: 2-2_002 | C14: C | D14: E | F14: Après avoir relancé les exploitants n'ayant pas répondu dans le délai réglementaire à la DICT, je peux commencer les travaux 2 jours après cette relance même sans réponse d'un exploitant :
C15: =IF(C14="C",IF(A15="P",IF(A14="I","p i","p"),IF(A14="I","i","")),"") | D15: =IF(D14="E",IF(A15="P",IF(A14="I","p i","p"),IF(A14="I","i"," ")),"") | E15: =IF(E14="O",IF(A15="P",IF(A14="I","p i","p"),IF(A14="I","i"," ")),"") | F15: A | G15: D'un réseau de transport d'hydrocarbures
A16: R554-26VI | F16: B | G16: D'un réseau électrique
F17: C | G17: D'un réseau téléphonique
F18: D | G18: Je ne sais pas
B20: 2-2_004 | C20: C | D20: E | F20: De combien de jours (sauf jours fériés) dispose l'exploitant pour répondre à une DICT dématérialisée ?
A21: P | C21: =IF(C20="C",IF(A21="P",IF(A20="I","p i","p"),IF(A20="I","i","")),"") -> p | D21: =IF(D20="E",IF(A21="P",IF(A20="I","p i","p"),IF(A20="I","i"," ")),"") -> p | E21: =IF(E20="O",IF(A21="P",IF(A20="I","p i","p"),IF(A20="I","i"," ")),"") | F21: A | G21: 7 jours
A22: R554-26I | C22: =IF(C21="C",IF(A22="P",IF(A21="I","p i","p"),IF(A21="I","i","")),"") | D22: =IF(D21="E",IF(A22="P",IF(A21="I","p i","p"),IF(A21="I","i"," ")),"") | E22: =IF(E21="O",IF(A22="P",IF(A21="I","p i","p"),IF(A21="I","i"," ")),"") | F22: B | G22: 9 jours
F23: C | G23: 15 jours
F24: D | G24: Je ne sais pas
B26: 2-2_005 | C26: C | D26: E | F26: De combien de jours (sauf jours fériés) dispose l'exploitant pour répondre à une DICT NON dématérialisée (courrier, fax...) ?
A27: P | C27: =IF(C26="C",IF(A27="P",IF(A26="I","p i","p"),IF(A26="I","i","")),"") -> p | D27: =IF(D26="E",IF(A27="P",IF(A26="I","p i","p"),IF(A26="I","i"," ")),"") -> p | E27: =IF(E26="O",IF(A27="P",IF(A26="I","p i","p"),IF(A26="I","i"," ")),"") | F27: A | G27: 7 jours
A28: R554-26I | F28: B | G28: 9 jours
F29: C | G29: 15 jours
F30: D | G30: Je ne sais pas
B32: 2-2_006 | C32: C | D32: E | F32: Suite à une relance pour non réponse à une DICT, l'exploitant doit répondre dans un délai de :
C33: =IF(C32="C",IF(A33="P",IF(A32="I","p i","p"),IF(A32="I","i","")),"") | D33: =IF(D32="E",IF(A33="P",IF(A32="I","p i","p"),IF(A32="I","i"," ")),"") | E33: =IF(E32="O",IF(A33="P",IF(A32="I","p i","p"),IF(A32="I","i"," ")),"") | F33: A | G33: 2 jours ouvrés
A34: R554-26VI | F34: B | G34: 7 jours ouvrés
F35: C | G35: 9 jours ouvrés
F36: D | G36: Je ne sais pas
B38: 2-2_007 | C38: C | D38: E | F38: Suite à une DICT, dans quel cas les plans des réseaux peuvent ne pas être joints au récépissé fourni par l'exploitant ?
F39: A | G39: L'exploitant prévoit une réunion sur site
A40: R554-26I | F40: B | G40: Aucun réseau sensible pour la sécurité n'est présent dans l'emprise des travaux
F41: C | G41: Un seul réseau est présent dans l'emprise des travaux
F42: D | G42: Je ne sais pas
B44: 2-2_008 | C44: C | F44: Lorsque le dossier de consultation d’un marché de travaux ne contient pas les récépissés de DT, le responsable de projet (ou maître d'ouvrage) :
C45: =IF(C44="C",IF(A45="P",IF(A44="I","p i","p"),IF(A44="I","i","")),"") | F45: A | G45: Attribue son marché en l’état, dès lors que les entreprises candidates n’ont pas demandé à disposer de ces éléments
A46: R554-23I | F46: B | G46: Fait les DT en vue de transmettre leurs récépissés aux candidats avant attribution du marché
F47: C | G47: Précise que la responsabilité d'identification des réseaux est du ressort exclusif de l'exécutant des travaux
F48: D | G48: Je ne sais pas
B50: 2-2_009 | C50: C | D50: E | F50: Je reçois l'ordre de démarrage des travaux d'un marché pour lequel aucun réseau sensible pour la sécurité n'est présent dans l'emprise des travaux :
C51: =IF(C50="C",IF(A51="P",IF(A50="I","p i","p"),IF(A50="I","i","")),"") | D51: =IF(D50="E",IF(A51="P",IF(A50="I","p i","p"),IF(A50="I","i"," ")),"") | F51: A | G51: Je demande au maître d'ouvrage de réaliser des investigations complémentaires pour vérifier l'exactitude des renseignements donnés par les plans et ne démarre pas les travaux tant que je n'ai pas de réponse
A52: R554-23III | F52: B | G52: Je démarre les travaux en appliquant les précautions prévues dans les clauses techniques et financières
F53: C | G53: Je démarre les travaux sans précaution particulière puisqu'il n'y a pas de réseau sensible pour la sécurité
F54: D | G54: Je ne sais pas
B57: 2-2_010 | C57: C | D57: E | F57: Si la rubrique "Distance minimale entre les travaux et la ligne électrique" de la DICT est remplie, l'exploitant :
C58: =IF(C57="C",IF(A58="P",IF(A57="I","p i","p"),IF(A57="I","i","")),"") | D58: =IF(D57="E",IF(A58="P",IF(A57="I","p i","p"),IF(A57="I","i"," ")),"") | E58: =IF(E57="O",IF(A58="P",IF(A57="I","p i","p"),IF(A57="I","i"," ")),"") | F58: A | G58: Met automatiquement la ligne considérée hors tension
A59: Cerfa14435*01Notice | F59: B | G59: Indique dans sa réponse les possibilités de mise hors tension de la ligne ou à défaut les autres moyens de mise en sécurité
F60: C | G60: Mentionne dans sa réponse les horaires de mise hors tension de la ligne
F61: D | G61: Je ne sais pas
B63: 2-2_011 | C63: C | D63: E | F63: En cas d’impossibilité de procéder à la mise hors tension d’une ligne électrique par l’exploitant, les entreprises intervenantes doivent :
C64: =IF(C63="C",IF(A64="P",IF(A63="I","p i","p"),IF(A63="I","i","")),"") | D64: =IF(D63="E",IF(A64="P",IF(A63="I","p i","p"),IF(A63="I","i"," ")),"") | E64: =IF(E63="O",IF(A64="P",IF(A63="I","p i","p"),IF(A63="I","i"," ")),"") | F64: A | G64: Sous-traiter à l'exploitant de la ligne électrique les travaux concernés
A65: R4534-119CT | F65: B | G65: Effectuer elles-mêmes la mise hors tension
F66: C | G66: Définir avec l’exploitant les mesures à mettre en place pour assurer la protection des intervenants
F67: D | G67: Je ne sais pas
B69: 2-2_012 | C69: C | D69: E | F69: Afin de préparer son offre en réponse à la consultation du responsable de projet, l’entreprise :
C70: =IF(C69="C",IF(A70="P",IF(A69="I","p i","p"),IF(A69="I","i","")),"") | D70: =IF(D69="E",IF(A70="P",IF(A69="I","p i","p"),IF(A69="I","i"," ")),"") | E70: =IF(E69="O",IF(A70="P",IF(A69="I","p i","p"),IF(A69="I","i"," ")),"") | F70: A | G70: N’examine pas les aspects relatifs aux réseaux présents dans l'emprise du projet car ils seront traités lors de la DICT
A71: R554-23I | F71: B | G71: Procède à des investigations par sondage de sol et marque les réseaux dans l’emprise du projet
F72: C | G72: Tient compte des informations contenues dans le DCE au sujet des réseaux présents dans l’emprise du projet
F73: D | G73: Je ne sais pas
B75: 2-2_014 | C75: C | D75: E | F75: Lorsque l’exploitant ne fournit pas de plan avec le récépissé de DICT, une réunion sur site doit-elle être organisée ?
C76: =IF(C75="C",IF(A76="P",IF(A75="I","p i","p"),IF(A75="I","i","")),"") | D76: =IF(D75="E",IF(A76="P",IF(A75="I","p i","p"),IF(A75="I","i"," ")),"") | F76: A | G76: Oui, par l'exploitant qui procède au marquage-piquetage de ses ouvrages
A77: R554-26II | F77: B | G77: Oui, par le prestataire de détection certifié du responsable de projet (ou maître d'ouvrage)
F78: C | G78: Non, certains exploitants de réseaux sont autorisés à ne fournir aucune information sur leurs ouvrages
F79: D | G79: Je ne sais pas
B81: 2-2_015 | C81: C | D81: E | F81: Lorsque l’exploitant ne fournit pas de plan avec le récépissé de DICT, qui doit réaliser le marquage-piquetage ?
C82: =IF(C81="C",IF(A82="P",IF(A81="I","p i","p"),IF(A81="I","i","")),"") | D82: =IF(D81="E",IF(A82="P",IF(A81="I","p i","p"),IF(A81="I","i"," ")),"") | F82: A | G82: Le marquage-piquetage est réalisé sous la responsabilité de l'exploitant et à ses frais
A83: R554-27III | F83: B | G83: L’encadrement de chantier doit procéder à des investigations et réaliser ensuite le marquage-piquetage
F84: C | G84: Le marquage-piquetage est réalisé sous la responsabilité du maître d’ouvrage et à ses frais
F85: D | G85: Je ne sais pas
A88: I | B88: 2-2_017 | C88: C | D88: E | F88: Sur ce schéma, le réseau jaune est en :
C89: =IF(C88="C",IF(A89="P",IF(A88="I","p i","p"),IF(A88="I","i","")),"") -> i | D89: =IF(D88="E",IF(A89="P",IF(A88="I","p i","p"),IF(A88="I","i"," ")),"") -> i | E89: =IF(E88="O",IF(A89="P",IF(A88="I","p i","p"),IF(A88="I","i"," ")),"") | F89: A | G89: Classe A
A90: A15-2-12/art1-3° | F90: B | G90: Classe B
F91: C | G91: Classe C
F92: D | G92: Je ne sais pas
A94: I | B94: 2-2_018 | C94: C | D94: E | F94: Sur ce schéma, le réseau jaune est en :
C95: =IF(C94="C",IF(A95="P",IF(A94="I","p i","p"),IF(A94="I","i","")),"") -> i | D95: =IF(D94="E",IF(A95="P",IF(A94="I","p i","p"),IF(A94="I","i"," ")),"") -> i | E95: =IF(E94="O",IF(A95="P",IF(A94="I","p i","p"),IF(A94="I","i"," ")),"") | F95: A | G95: Classe A
A96: A15-2-12/art1-3° | F96: B | G96: Classe B
F97: C | G97: Classe C
F98: D | G98: Je ne sais pas
A100: I | B100: 2-2_019 | C100: C | D100: E | F100: Sur ce schéma, le réseau jaune est en :
C101: =IF(C100="C",IF(A101="P",IF(A100="I","p i","p"),IF(A100="I","i","")),"") -> i | D101: =IF(D100="E",IF(A101="P",IF(A100="I","p i","p"),IF(A100="I","i"," ")),"") -> i | E101: =IF(E100="O",IF(A101="P",IF(A100="I","p i","p"),IF(A100="I","i"," ")),"") | F101: A | G101: Classe A
A102: A15-2-12/art1-3° | F102: B | G102: Classe B
F103: C | G103: Classe C
F104: D | G104: Je ne sais pas
A106: I | B106: 2-2_020 | C106: C | D106: E | F106: Sur ce schéma, le réseau jaune est en :
C107: =IF(C106="C",IF(A107="P",IF(A106="I","p i","p"),IF(A106="I","i","")),"") -> i | D107: =IF(D106="E",IF(A107="P",IF(A106="I","p i","p"),IF(A106="I","i"," ")),"") -> i | E107: =IF(E106="O",IF(A107="P",IF(A106="I","p i","p"),IF(A106="I","i"," ")),"") | F107: A | G107: Classe A
A108: A15-2-12/art1-3° | F108: B | G108: Classe B
F109: C | G109: Classe C
F110: D | G110: Je ne sais pas
B112: 2-2_022 | C112: C | D112: E | F112: Comment savoir qu'il existe ou peut exister dans l'emprise des travaux prévus des branchements électriques ou de gaz non cartographiés et non pourvus d'affleurant visible ?
C113: =IF(C112="C",IF(A113="P",IF(A112="I","p i","p"),IF(A112="I","i","")),"") | D113: =IF(D112="E",IF(A113="P",IF(A112="I","p i","p"),IF(A112="I","i"," ")),"") | E113: =IF(E112="O",IF(A113="P",IF(A112="I","p i","p"),IF(A112="I","i"," ")),"") | F113: A | G113: En adressant au préalable une demande écrite à la mairie
A114: Cerfa14435*01 | F114: B | G114: En allant chercher l'information sur le site internet des exploitants concernés
F115: C | G115: L'exploitant du réseau concerné doit le mentionner dans le récépissé
F116: D | G116: Je ne sais pas
C253: =IF(C252="C",IF(A253="P",IF(A252="I","p i","p"),IF(A252="I","i","")),"") | D253: =IF(D252="E",IF(A253="P",IF(A252="I","p i","p"),IF(A252="I","i"," ")),"") | E253: =IF(E252="O",IF(A253="P",IF(A252="I","p i","p"),IF(A252="I","i"," ")),"")
C260: =IF(C259="C",IF(A260="P",IF(A259="I","p i","p"),IF(A259="I","i","")),"") | D260: =IF(D259="E",IF(A260="P",IF(A259="I","p i","p"),IF(A259="I","i"," ")),"") | E260: =IF(E259="O",IF(A260="P",IF(A259="I","p i","p"),IF(A259="I","i"," ")),"")
C267: =IF(C266="C",IF(A267="P",IF(A266="I","p i","p"),IF(A266="I","i","")),"") | D267: =IF(D266="E",IF(A267="P",IF(A266="I","p i","p"),IF(A266="I","i"," ")),"") | E267: =IF(E266="O",IF(A267="P",IF(A266="I","p i","p"),IF(A266="I","i"," ")),"")
C274: =IF(C273="C",IF(A274="P",IF(A273="I","p i","p"),IF(A273="I","i","")),"") | D274: =IF(D273="E",IF(A274="P",IF(A273="I","p i","p"),IF(A273="I","i"," ")),"") | E274: =IF(E273="O",IF(A274="P",IF(A273="I","p i","p"),IF(A273="I","i"," ")),"")
C281: =IF(C280="C",IF(A281="P",IF(A280="I","p i","p"),IF(A280="I","i","")),"") | D281: =IF(D280="E",IF(A281="P",IF(A280="I","p i","p"),IF(A280="I","i"," ")),"") | E281: =IF(E280="O",IF(A281="P",IF(A280="I","p i","p"),IF(A280="I","i"," ")),"")
...

Sheet 2.3
A1: =Bilan!B16 -> 2.3 Compétences des personnels
C3: C | D3: E | E3: O | F3: Total
B4: Nb quest. | C4: =COUNTIF(C8:C632,C3) -> 5 | D4: =COUNTIF(D8:D632,D3) -> 16 | E4: =COUNTIF(E8:E632,E3) -> 14 | F4: =COUNTA(B8:B632) -> 18
B5: Illust. | C5: =COUNTIF(C8:C632,"i")+COUNTIF(C8:C632,"p i") -> 3 | D5: =COUNTIF(D8:D632,"i")+COUNTIF(D8:D632,"p i") -> 14 | E5: =COUNTIF(E8:E632,"i")+COUNTIF(E8:E632,"p i") -> 14 | F5: =COUNTIF(A8:A632,"I") -> 16
B6: Prio | C6: =COUNTIF(C8:C632,"p")+COUNTIF(C8:C632,"p i") -> 1 | D6: =COUNTIF(D8:D632,"p")+COUNTIF(D8:D632,"p i") -> 4 | E6: =COUNTIF(E8:E632,"p")+COUNTIF(E8:E632,"p i") -> 1 | F6: =COUNTIF(A8:A632,"P") -> 4
A8: I | B8: 2-3_003 | D8: E | E8: O | F8: Que dois-je faire si je découvre un câble électrique dénudé ?
C9: =IF(C8="C",IF(A9="P",IF(A8="I","p i","p"),IF(A8="I","i","")),"") | D9: =IF(D8="E",IF(A9="P",IF(A8="I","p i","p"),IF(A8="I","i"," ")),"") -> i | E9: =IF(E8="O",IF(A9="P",IF(A8="I","p i","p"),IF(A8="I","i"," ")),"") -> i | F9: A | G9: Je mets des lunettes de protection
A10: R554-31II | F10: B | G10: Je m'écarte tout de suite de la zone
F11: C | G11: Je dégage le câble en évitant de le toucher
F12: D | G12: Je ne sais pas
B14: 2-3_004 | C14: C | D14: E | F14: Une entreprise exécutant des travaux non urgents doit délivrer une autorisation d'intervention à proximité des réseaux (AIPR) :
A15: P | C15: =IF(C14="C",IF(A15="P",IF(A14="I","p i","p"),IF(A14="I","i","")),"") -> p | D15: =IF(D14="E",IF(A15="P",IF(A14="I","p i","p"),IF(A14="I","i"," ")),"") -> p | E15: =IF(E14="O",IF(A15="P",IF(A14="I","p i","p"),IF(A14="I","i"," ")),"") | F15: A | G15: Uniquement à l'encadrant des travaux
A16: A15-2-12/art21I | F16: B | G16: A l'encadrant des travaux et aux conducteurs d'engins intervenant sur le chantier
F17: C | G17: Uniquement aux conducteurs d'engins intervenant sur le chantier
F18: D | G18: Je ne sais pas
A20: I | B20: 2-3_011 | D20: E | E20: O | F20: Quels sont les risques principaux liés à un réseau d'assainissement ?
C21: =IF(C20="C",IF(A21="P",IF(A20="I","p i","p"),IF(A20="I","i","")),"") | D21: =IF(D20="E",IF(A21="P",IF(A20="I","p i","p"),IF(A20="I","i"," ")),"") -> i | E21: =IF(E20="O",IF(A21="P",IF(A20="I","p i","p"),IF(A20="I","i"," ")),"") -> i | F21: A | G21: Asphyxie et intoxication
A22: § 3.9 du GT | F22: B | G22: Electrisation et électrocution
F23: C | G23: Hydrocution
F24: D | G24: Je ne sais pas
A26: I | B26: 2-3_013e | D26: E | F26: Pendant toute la durée de travaux à proximité d'un réseau de gaz, il faut dans tous les cas :
A27: P | C27: =IF(C26="C",IF(A27="P",IF(A26="I","p i","p"),IF(A26="I","i","")),"") | D27: =IF(D26="E",IF(A27="P",IF(A26="I","p i","p"),IF(A26="I","i"," ")),"") -> p i | E27: =IF(E26="O",IF(A27="P",IF(A26="I","p i","p"),IF(A26="I","i"," ")),"") | F27: A | G27: Maintenir les accès aux vannes d’arrêt
A28: R554-31II | F28: B | G28: Interdire tout matériel électrique
F29: C | G29: Porter un masque respiratoire
F30: D | G30: Je ne sais pas
A32: I | B32: 2-3_013o | E32: O | F32: Pendant toute la durée de travaux à proximité d'un réseau de gaz, il faut dans tous les cas :
C33: =IF(C32="C",IF(A33="P",IF(A32="I","p i","p"),IF(A32="I","i","")),"") | D33: =IF(D32="E",IF(A33="P",IF(A32="I","p i","p"),IF(A32="I","i"," ")),"") | E33: =IF(E32="O",IF(A33="P",IF(A32="I","p i","p"),IF(A32="I","i"," ")),"") -> i | F33: A | G33: Maintenir les accès aux vannes d’arrêt
A34: R554-31II | F34: B | G34: Interdire tout matériel électrique
F35: C | G35: Porter un masque respiratoire
F36: D | G36: Je ne sais pas
A38: I | B38: 2-3_015e | D38: E | F38: Un conducteur d'engin peut démarrer le terrassement dès qu'il a les informations sur :
A39: P | C39: =IF(C38="C",IF(A39="P",IF(A38="I","p i","p"),IF(A38="I","i","")),"") | D39: =IF(D38="E",IF(A39="P",IF(A38="I","p i","p"),IF(A38="I","i"," ")),"") -> p i | E39: =IF(E38="O",IF(A39="P",IF(A38="I","p i","p"),IF(A38="I","i"," ")),"") | F39: A | G39: L' ouvrage souterrain sur lequel il doit travailler
A40: R554-27 I | F40: B | G40: Les réseaux dangereux situés dans la zone de travail (gaz, électricité)
F41: C | G41: Tous les ouvrages souterrains signalés par le marquage-piquetage
F42: D | G42: Je ne sais pas
A44: I | B44: 2-3_015o | E44: O | F44: Un conducteur d'engin peut démarrer le terrassement dès qu'il a les informations sur :
C45: =IF(C44="C",IF(A45="P",IF(A44="I","p i","p"),IF(A44="I","i","")),"") | D45: =IF(D44="E",IF(A45="P",IF(A44="I","p i","p"),IF(A44="I","i"," ")),"") | E45: =IF(E44="O",IF(A45="P",IF(A44="I","p i","p"),IF(A44="I","i"," ")),"") -> i | F45: A | G45: L' ouvrage souterrain sur lequel il doit travailler
A46: R554-27 I | F46: B | G46: Les réseaux dangereux situés dans la zone de travail (gaz, électricité)
F47: C | G47: Tous les ouvrages souterrains signalés par le marquage-piquetage
F48: D | G48: Je ne sais pas
A50: I | B50: 2-3_016 | C50: C | D50: E | E50: O | F50: Lorsque le réseau annoncé et marqué n'a pas été trouvé dans l'emprise des travaux mentionnée dans la DICT, peut-on creuser en dehors de cette emprise ?
C51: =IF(C50="C",IF(A51="P",IF(A50="I","p i","p"),IF(A50="I","i","")),"") -> i | D51: =IF(D50="E",IF(A51="P",IF(A50="I","p i","p"),IF(A50="I","i"," ")),"") -> i | E51: =IF(E50="O",IF(A51="P",IF(A50="I","p i","p"),IF(A50="I","i"," ")),"") -> i | F51: A | G51: Oui, mais uniquement dans l'environnement immédiat de cette zone (moins de 3 mètres)
A52: R. 554-25 II | F52: B | G52: Oui, lorsqu'aucun élément ne signale de réseau (pas de coffret, de borne incendie…)
F53: C | G53: Non
F54: E | G54: Je ne sais pas
B56: 2-3_018 | C56: C | D56: E | F56: Dans le cadre d'un avis de travaux urgents (ATU) et en présence d'un réseau de transport de matières dangereuses (TMD). Il faut :
F57: A | G57: Uniquement appeler l'exploitant du réseau de TMD avant le démarrage des travaux
A58: R554-32 / art3 A | F58: B | G58: Appeler l'exploitant du réseau de TMD avant le démarrage des travaux et lui envoyer l'ATU
F59: C | G59: Uniquement envoyer l'ATU à l'exploitant du réseau deTMD si les travaux démarrent plus de 24h après cet envoi.
F60: D | G60: Je ne sais pas
A62: I | B62: 2-3_019 | D62: E | E62: O | F62: Sans protection particulière, l'écart minimum entre un câble électrique et une canalisation de gaz est de:
C63: =IF(C62="C",IF(A63="P",IF(A62="I","p i","p"),IF(A62="I","i","")),"") | D63: =IF(D62="E",IF(A63="P",IF(A62="I","p i","p"),IF(A62="I","i"," ")),"") -> i | E63: =IF(E62="O",IF(A63="P",IF(A62="I","p i","p"),IF(A62="I","i"," ")),"") -> i | F63: A | G63: 10 cm
A64: § 3.4.5 du GT | F64: B | G64: 15 cm
A65: NF P 98-333 | F65: C | G65: 20 cm
F66: D | G66: Je ne sais pas
A68: I | B68: 2-3_020 | C68: C | D68: E | E68: O | F68: Pour ouvrir un coffret électrique, il faut avoir l'accord :
C69: =IF(C68="C",IF(A69="P",IF(A68="I","p i","p"),IF(A68="I","i","")),"") -> i | D69: =IF(D68="E",IF(A69="P",IF(A68="I","p i","p"),IF(A68="I","i"," ")),"") -> i | E69: =IF(E68="O",IF(A69="P",IF(A68="I","p i","p"),IF(A68="I","i"," ")),"") -> i | F69: A | G69: De l'exploitant
A70: § 4.2.3 du GT | F70: B | G70: Des pompiers
F71: C | G71: De l'usager
F72: D | G72: Je ne sais pas
A74: I | B74: 2-3_023 | D74: E | E74: O | F74: Les butées en béton des canalisations d'eau doivent être préservées lors des travaux car elles servent à:
D75: =IF(D74="E",IF(A75="P",IF(A74="I","p i","p"),IF(A74="I","i"," ")),"") -> i | E75: =IF(E74="O",IF(A75="P",IF(A74="I","p i","p"),IF(A74="I","i"," ")),"") -> i | F75: A | G75: Assembler les canalisations
A76: § 3.8.5 du GT | F76: B | G76: Eviter que la pression ne déplace les canalisations
F77: C | G77: Protéger du gel
F78: D | G78: Je ne sais pas
A80: I | B80: 2-3_023b | D80: E | E80: O | F80: La protection cathodique des canalisations en acier doit être préservée lors des travaux car elle sert à protéger :
C81: =IF(C80="C",IF(A81="P",IF(A80="I","p i","p"),IF(A80="I","i","")),"") | D81: =IF(D80="E",IF(A81="P",IF(A80="I","p i","p"),IF(A80="I","i"," ")),"") -> i | E81: =IF(E80="O",IF(A81="P",IF(A80="I","p i","p"),IF(A80="I","i"," ")),"") -> i | F81: A | G81: Des incendies
A82: § 3.1.1.5 du GT | F82: B | G82: De la corrosion
F83: C | G83: Du gel
F84: D | G84: Je ne sais pas
A86: I | B86: 2-3_025 | D86: E | E86: O | F86: Lorsqu'une tranchée est remblayée, mais pas encore compactée, à quelle condition peut-on rouler au dessus du réseau ?
C87: =IF(C86="C",IF(A87="P",IF(A86="I","p i","p"),IF(A86="I","i","")),"") | D87: =IF(D86="E",IF(A87="P",IF(A86="I","p i","p"),IF(A86="I","i"," ")),"") -> i | E87: =IF(E86="O",IF(A87="P",IF(A86="I","p i","p"),IF(A86="I","i"," ")),"") -> i | F87: A | G87: Le sol doit être totalement sec
A88: Fiche TX-RBL2 du GT | F88: B | G88: L'écart de niveau entre le remblaiement et le sol fini ne doit pas excéder 15 cm
F89: C | G89: En aucun cas de figure
F90: D | G90: Je ne sais pas
A92: I | B92: 2-3_026 | D92: E | E92: O | F92: Lequel de ces éléments est un affleurant indiquant la présence d'un réseau sous la chaussée ?
C93: =IF(C92="C",IF(A93="P",IF(A92="I","p i","p"),IF(A92="I","i","")),"") | D93: =IF(D92="E",IF(A93="P",IF(A92="I","p i","p"),IF(A92="I","i"," ")),"") -> i | E93: =IF(E92="O",IF(A93="P",IF(A92="I","p i","p"),IF(A92="I","i"," ")),"") -> i | F93: A | G93: Panneau de signalisation routière
A94: § 3.4.2 du GT | F94: B | G94: Bouche à clé
F95: C | G95: Bordure de trottoir
F96: D | G96: Je ne sais pas
A98: I | B98: 2-3_027 | D98: E | E98: O | F98: Lequel de ces éléments est un affleurant indiquant la présence d'un réseau sous le trottoir ?
A99: P | C99: =IF(C98="C",IF(A99="P",IF(A98="I","p i","p"),IF(A98="I","i","")),"") | D99: =IF(D98="E",IF(A99="P",IF(A98="I","p i","p"),IF(A98="I","i"," ")),"") -> p i | E99: =IF(E98="O",IF(A99="P",IF(A98="I","p i","p"),IF(A98="I","i"," ")),"") -> p i | F99: A | G99: Potelet de signalisation
A100: § 3.4.2 du GT | F100: B | G100: Coffret de gaz
F101: C | G101: Bordure de trottoir
F102: D | G102: Je ne sais pas
A104: I | B104: 2-3_028 | C104: C | D104: E | E104: O | F104: L'électricité :
C105: =IF(C104="C",IF(A105="P",IF(A104="I","p i","p"),IF(A104="I","i","")),"") -> i | D105: =IF(D104="E",IF(A105="P",IF(A104="I","p i","p"),IF(A104="I","i"," ")),"") -> i | E105: =IF(E104="O",IF(A105="P",IF(A104="I","p i","p"),IF(A104="I","i"," ")),"") -> i | F105: A | G105: N'est pas dangereuse pour le corps humain
A106: NF C 18-510 | F106: B | G106: Est dangereuse seulement en haute tension
F107: C | G107: Peut provoquer une électrisation même en basse tension
F108: D | G108: Je ne sais pas
A110: I | B110: 2-3_029 | D110: E | E110: O | F110: L'isolant d'un câble électrique assure une protection :
C111: =IF(C110="C",IF(A111="P",IF(A110="I","p i","p"),IF(A110="I","i","")),"") | D111: =IF(D110="E",IF(A111="P",IF(A110="I","p i","p"),IF(A110="I","i"," ")),"") -> i | E111: =IF(E110="O",IF(A111="P",IF(A110="I","p i","p"),IF(A110="I","i"," ")),"") -> i | F111: A | G111: Contre la perforation d'outils
A112: NF C 18-510 | F112: B | G112: Contre la pénétration d'eau
F113: C | G113: Contre les dents d'un godet d'une pelle mécanique
F114: D | G114: Je ne sais pas
C266: =IF(C265="C",IF(A266="P",IF(A265="I","p i","p"),IF(A265="I","i","")),"") | D266: =IF(D265="E",IF(A266="P",IF(A265="I","p i","p"),IF(A265="I","i"," ")),"") | E266: =IF(E265="O",IF(A266="P",IF(A265="I","p i","p"),IF(A265="I","i"," ")),"")
C273: =IF(C272="C",IF(A273="P",IF(A272="I","p i","p"),IF(A272="I","i","")),"") | D273: =IF(D272="E",IF(A273="P",IF(A272="I","p i","p"),IF(A272="I","i"," ")),"") | E273: =IF(E272="O",IF(A273="P",IF(A272="I","p i","p"),IF(A272="I","i"," ")),"")
C280: =IF(C279="C",IF(A280="P",IF(A279="I","p i","p"),IF(A279="I","i","")),"") | D280: =IF(D279="E",IF(A280="P",IF(A279="I","p i","p"),IF(A279="I","i"," ")),"") | E280: =IF(E279="O",IF(A280="P",IF(A279="I","p i","p"),IF(A279="I","i"," ")),"")
C287: =IF(C286="C",IF(A287="P",IF(A286="I","p i","p"),IF(A286="I","i","")),"") | D287: =IF(D286="E",IF(A287="P",IF(A286="I","p i","p"),IF(A286="I","i"," ")),"") | E287: =IF(E286="O",IF(A287="P",IF(A286="I","p i","p"),IF(A286="I","i"," ")),"")
C294: =IF(C293="C",IF(A294="P",IF(A293="I","p i","p"),IF(A293="I","i","")),"") | D294: =IF(D293="E",IF(A294="P",IF(A293="I","p i","p"),IF(A293="I","i"," ")),"") | E294: =IF(E293="O",IF(A294="P",IF(A293="I","p i","p"),IF(A293="I","i"," ")),"")
...

Sheet 2.4
A1: =Bilan!B17 -> 2.4 Application du guide technique
C3: C | D3: E | E3: O | F3: Total
B4: Nb quest. | C4: =COUNTIF(C8:C706,C3) -> 23 | D4: =COUNTIF(D8:D706,D3) -> 28 | E4: =COUNTIF(E8:E706,E3) -> 23 | F4: =COUNTA(B8:B706) -> 38
B5: Illust. | C5: =COUNTIF(C8:C706,"i")+COUNTIF(C8:C706,"p i") -> 12 | D5: =COUNTIF(D8:D706,"i")+COUNTIF(D8:D706,"p i") -> 16 | E5: =COUNTIF(E8:E706,"i")+COUNTIF(E8:E706,"p i") -> 19 | F5: =COUNTIF(A8:A706,"I") -> 26
B6: Prio | C6: =COUNTIF(C8:C706,"p")+COUNTIF(C8:C706,"p i") -> 3 | D6: =COUNTIF(D8:D706,"p")+COUNTIF(D8:D706,"p i") -> 4 | E6: =COUNTIF(E8:E706,"p")+COUNTIF(E8:E706,"p i") -> 2 | F6: =COUNTIF(A8:A706,"P") -> 5
A8: I | B8: 2-4_002 | C8: C | D8: E | E8: O | F8: Si l'on ne connaît pas la tension de la ligne électrique, il faut que le godet se trouve toujours à plus de :
A9: P | C9: =IF(C8="C",IF(A9="P",IF(A8="I","p i","p"),IF(A8="I","i","")),"") -> p i | D9: =IF(D8="E",IF(A9="P",IF(A8="I","p i","p"),IF(A8="I","i"," ")),"") -> p i | E9: =IF(E8="O",IF(A9="P",IF(A8="I","p i","p"),IF(A8="I","i"," ")),"") -> p i | F9: A | G9: 1 mètre
A10: § 6 du GT | F10: B | G10: 2 mètres
A11: TC OPERATEUR | F11: C | G11: 5 mètres
F12: D | G12: Je ne sais pas
A14: I | B14: 2-4_003 | C14: C | D14: E | E14: O | F14: Quand je travaille près d'une ligne aérienne à très haute tension (plus de 50 000 Volts), je dois rester à plus de 5 mètres : | H14: x
C15: =IF(C14="C",IF(A15="P",IF(A14="I","p i","p"),IF(A14="I","i","")),"") -> i | D15: =IF(D14="E",IF(A15="P",IF(A14="I","p i","p"),IF(A14="I","i"," ")),"") -> i | E15: =IF(E14="O",IF(A15="P",IF(A14="I","p i","p"),IF(A14="I","i"," ")),"") -> i | F15: A | G15: Du fil électrique le plus proche
A16: § 6.1 du GT | F16: B | G16: Du sol
F17: C | G17: Du pylône
F18: D | G18: Je ne sais pas
A20: I | B20: 2-4_004 | C20: C | D20: E | E20: O | F20: Quand je travaille près d'une ligne aérienne haute tension (plus de 1000 Volts), le godet doit toujours se trouver à plus de :
C21: =IF(C20="C",IF(A21="P",IF(A20="I","p i","p"),IF(A20="I","i","")),"") -> i | D21: =IF(D20="E",IF(A21="P",IF(A20="I","p i","p"),IF(A20="I","i"," ")),"") -> i | E21: =IF(E20="O",IF(A21="P",IF(A20="I","p i","p"),IF(A20="I","i"," ")),"") -> i | F21: A | G21: 3 mètres
A22: § 6 du GT | F22: B | G22: 5 mètres
F23: C | G23: 7 mètres
F24: D | G24: Je ne sais pas
B26: 2-4_007 | C26: C | D26: E | E26: O | F26: Avec une pelle hydraulique (précision annoncée : 0,15 m), jusqu'à quelle distance du marquage d'un réseau rigide de diamètre 60 mm et de classe de précision A peut-on terrasser sans précaution particulière ?
C27: =IF(C26="C",IF(A27="P",IF(A26="I","p i","p"),IF(A26="I","i","")),"") | D27: =IF(D26="E",IF(A27="P",IF(A26="I","p i","p"),IF(A26="I","i"," ")),"") | F27: A | G27: 0,40 + 0,15 = 0,55 m
A28: GT - 5.2.5 | F28: B | G28: 0,40 m
F29: C | G29: 0,40 - 0,15 = 0,25 m
F30: D | G30: Je ne sais pas
B32: 2-4_008 | C32: C | D32: E | E32: O | F32: Avec une pelle hydraulique (précision annoncée : 0,15 m), jusqu'à quelle distance du marquage d'un réseau souple de diamètre 60 mm et de classe de précision A peut-on terrasser sans précaution particulière ?
F33: A | G33: 0,50 - 0,15 = 0,35 m
A34: GT - 5.2.5 | F34: B | G34: 0,50 m
F35: C | G35: 0,50 + 0,15 = 0,65 m
F36: D | G36: Je ne sais pas
A39: I | B39: 2-4_009 | C39: C | D39: E | E39: O | F39: Au dessus d'un réseau, on peut utiliser un engin lourd (pelle hydraulique, raboteuse, BRH…) :
C40: =IF(C39="C",IF(A40="P",IF(A39="I","p i","p"),IF(A39="I","i","")),"") -> i | D40: =IF(D39="E",IF(A40="P",IF(A39="I","p i","p"),IF(A39="I","i"," ")),"") -> i | E40: =IF(E39="O",IF(A40="P",IF(A39="I","p i","p"),IF(A39="I","i"," ")),"") -> i | F40: A | G40: Jusqu'à la découverte du grillage avertisseur
A41: Fiche AT-PEL du GT | F41: B | G41: Pour enlever la couche de surface dure
A42: TC OPERATEUR | F42: C | G42: Jusqu'à 10 cm du réseau enterré
F43: D | G43: Je ne sais pas
B45: 2-4_010 | C45: C | D45: E | F45: Le remplacement d'un potelet sans élargissement de la fouille initiale est dispensé de DT et DICT lorsqu'il s'effectue :
C46: =IF(C45="C",IF(A46="P",IF(A45="I","p i","p"),IF(A45="I","i","")),"") | D46: =IF(D45="E",IF(A46="P",IF(A45="I","p i","p"),IF(A45="I","i"," ")),"") | F46: A | G46: A moins de 70 cm de profondeur et à plus d'1 mètre de tout affleurant
A47: R554-1b) | F47: B | G47: A moins de 40 cm de profondeur et à plus de 50 cm de tout affleurant
F48: C | G48: A moins de 40 cm de profondeur et à plus d'1 mètre de tout affleurant
F49: D | G49: Je ne sais pas
B52: 2-4_011 | C52: C | D52: E | F52: Je dois poser, sous un trottoir à revêtement dur, un branchement d'eau neuf dans la zone d'incertitude de localisation d'un réseau de gaz existant. Je peux employer :
C53: =IF(C52="C",IF(A53="P",IF(A52="I","p i","p"),IF(A52="I","i","")),"") | D53: =IF(D52="E",IF(A53="P",IF(A52="I","p i","p"),IF(A52="I","i"," ")),"") | E53: =IF(E52="O",IF(A53="P",IF(A52="I","p i","p"),IF(A52="I","i"," ")),"") | F53: A | G53: Une fusée non guidée à partir d'un regard existant
A54: Fiche RX-TMD du GT | F54: B | G54: Un marteau piqueur pour le revêtement de surface, puis un camion aspirateur muni d'un embout souple, une pioche à air ou une pelle à main
F55: C | G55: Une mini-pelle jusqu'à ce que je trouve le grillage avertisseur jaune du réseau de gaz, puis un camion aspirateur, une pioche à air ou une pelle à main
F56: D | G56: Je ne sais pas
B58: 2-4_012 | D58: E | E58: O | F58: J'utilise un camion aspirateur équipé d'un jet haute pression (eau ou air) près d'un réseau, que puis-je faire ?
C59: =IF(C58="C",IF(A59="P",IF(A58="I","p i","p"),IF(A58="I","i","")),"") | D59: =IF(D58="E",IF(A59="P",IF(A58="I","p i","p"),IF(A58="I","i"," ")),"") | E59: =IF(E58="O",IF(A59="P",IF(A58="I","p i","p"),IF(A58="I","i"," ")),"") | F59: A | G59: Je peux mettre l'embout d'aspiration en contact avec le réseau
A60: Fiche AT-TED du GT | F60: B | G60: Je peux mettre le jet d'air ou d'eau à haute pression en contact avec le réseau
F61: C | G61: Je peux approcher l'embout d'aspiration jusqu'à 10 cm du réseau, et uniquement s'il s'agit d'un embout souple
F62: D | G62: Je ne sais pas
B64: 2-4_014 | C64: C | D64: E | E64: O | F64: Lors de l'utilisation d'un camion aspirateur à proximité d'un réseau, l'embout souple d'aspiration doit toujours être à plus de 10 cm de l'ouvrage et le jet d'air ou d'eau haute pression peut être utilisé :
C65: =IF(C64="C",IF(A65="P",IF(A64="I","p i","p"),IF(A64="I","i","")),"") | D65: =IF(D64="E",IF(A65="P",IF(A64="I","p i","p"),IF(A64="I","i"," ")),"") | F65: A | G65: Sans être dirigé directement sur l'ouvrage
A66: GT - Fiche AT-TED | F66: B | G66: Comme une barre à mine
F67: C | G67: A moins de 5 cm de l'ouvrage
F68: D | G68: Je ne sais pas
A71: I | B71: 2-4_019o | E71: O | F71: A proximité d'une canalisation principale, je peux utiliser une mini-pelle par passes successives de faible épaisseur :
C72: =IF(C71="C",IF(A72="P",IF(A71="I","p i","p"),IF(A71="I","i","")),"") | D72: =IF(D71="E",IF(A72="P",IF(A71="I","p i","p"),IF(A71="I","i"," ")),"") | E72: =IF(E71="O",IF(A72="P",IF(A71="I","p i","p"),IF(A71="I","i"," ")),"") -> i | F72: A | G72: Si je suis aidé d'un suiveur et que j'ai une visibilité sur mon godet
A73: Fiche AT-PEL du GT | F73: B | G73: Si je vois le grillage avertisseur
A74: Fiche RX-TMD | F74: C | G74: Si le marquage-piquetage est visible
F75: D | G75: Je ne sais pas
A77: I | B77: 2-4_019ce | C77: C | D77: E | F77: A proximité d'une canalisation principale, l'usage d'une mini-pelle par passes successives de faible épaisseur est possible:
C78: =IF(C77="C",IF(A78="P",IF(A77="I","p i","p"),IF(A77="I","i","")),"") -> i | D78: =IF(D77="E",IF(A78="P",IF(A77="I","p i","p"),IF(A77="I","i"," ")),"") -> i | E78: =IF(E77="O",IF(A78="P",IF(A77="I","p i","p"),IF(A77="I","i"," ")),"") | F78: A | G78: Si l'opérateur est aidé d'un suiveur et a une visibilité sur le godet
A79: Fiche AT-PEL du GT | F79: B | G79: Si l'opérateur voit le grillage avertisseur
F80: C | G80: Si le marquage-piquetage est visible
F81: D | G81: Je ne sais pas
A83: I | B83: 2-4_021 | E83: O | F83: En creusant dans une zone où aucun réseau n'est signalé, je rencontre un remblai différent. Que dois-je faire ?
C84: =IF(C83="C",IF(A84="P",IF(A83="I","p i","p"),IF(A83="I","i","")),"") | D84: =IF(D83="E",IF(A84="P",IF(A83="I","p i","p"),IF(A83="I","i"," ")),"") | E84: =IF(E83="O",IF(A84="P",IF(A83="I","p i","p"),IF(A83="I","i"," ")),"") -> i | F84: A | G84: Je continue à creuser
A85: Fiche TX-TER2/TER3 du GT | F85: B | G85: Je change le tracé
F86: C | G86: Je continue avec un outil manuel et je préviens mon chef
F87: D | G87: Je ne sais pas
A90: I | B90: 2-4_022 | E90: O | F90: Lors de la pose d'un nouveau réseau, en creusant, je découvre un bloc de béton :
C91: =IF(C90="C",IF(A91="P",IF(A90="I","p i","p"),IF(A90="I","i","")),"") | D91: =IF(D90="E",IF(A91="P",IF(A90="I","p i","p"),IF(A90="I","i"," ")),"") | E91: =IF(E90="O",IF(A91="P",IF(A90="I","p i","p"),IF(A90="I","i"," ")),"") -> i | F91: A | G91: J'utilise un BRH pour le casser
A92: Fiche TX-TER1 du GT | F92: B | G92: Je décide de changer le tracé
F93: C | G93: Je demande les consignes
F94: D | G94: Je ne sais pas
A96: I | B96: 2-4_023 | C96: C | D96: E | E96: O | F96: Je pose un réseau de gaz. Quel doit être l'écart minimum avec le réseau électrique existant ?
C97: =IF(C96="C",IF(A97="P",IF(A96="I","p i","p"),IF(A96="I","i","")),"") -> i | D97: =IF(D96="E",IF(A97="P",IF(A96="I","p i","p"),IF(A96="I","i"," ")),"") -> i | E97: =IF(E96="O",IF(A97="P",IF(A96="I","p i","p"),IF(A96="I","i"," ")),"") -> i | F97: A | G97: 20 cm
A98: GT - 3.4.5 | F98: B | G98: 5 cm
F99: C | G99: 40 cm
F100: D | G100: Je ne sais pas
A102: I | B102: 2-4_024 | C102: C | D102: E | E102: O | F102: Pendant combien de temps peut on entreposer des déblais sur une bouche à clé ?
C103: =IF(C102="C",IF(A103="P",IF(A102="I","p i","p"),IF(A102="I","i","")),"") -> i | D103: =IF(D102="E",IF(A103="P",IF(A102="I","p i","p"),IF(A102="I","i"," ")),"") -> i | E103: =IF(E102="O",IF(A103="P",IF(A102="I","p i","p"),IF(A102="I","i"," ")),"") -> i | F103: A | G103: Une demi-journée maximum
A104: GT - | F104: B | G104: Une heure maximum
A105: R534 31 | F105: C | G105: Jamais
F106: D | G106: Je ne sais pas
A108: I | B108: 2-4_025ce | C108: C | D108: E | F108: Quelle distance minimale de précaution doit-on prévoir de part et d'autre du marquage quand on creuse à coté d'un branchement de gaz qui n'apparaît pas sur le plan ?
A109: P | C109: =IF(C108="C",IF(A109="P",IF(A108="I","p i","p"),IF(A108="I","i","")),"") -> p i | D109: =IF(D108="E",IF(A109="P",IF(A108="I","p i","p"),IF(A108="I","i"," ")),"") -> p i | E109: =IF(E108="O",IF(A109="P",IF(A108="I","p i","p"),IF(A108="I","i"," ")),"") | F109: A | G109: 0,5 m
A110: GT - § 5.2.7.2 | F110: B | G110: 1,0 m
F111: C | G111: 1,5 m
F112: D | G112: Je ne sais pas
A114: I | B114: 2-4_025o | E114: O | F114: A partir de quelle distance minimale du marquage d'un branchement de gaz dois-je prendre des précautions pour creuser ?
A115: P | C115: =IF(C114="C",IF(A115="P",IF(A114="I","p i","p"),IF(A114="I","i","")),"") | D115: =IF(D114="E",IF(A115="P",IF(A114="I","p i","p"),IF(A114="I","i"," ")),"") | E115: =IF(E114="O",IF(A115="P",IF(A114="I","p i","p"),IF(A114="I","i"," ")),"") -> p i | F115: A | G115: 2,0 m
A116: GT - § 5.2.7 | F116: B | G116: 1,0 m
A117: TC OPERATEUR | F117: C | G117: 1,5 m
F118: D | G118: Je ne sais pas
B120: 2-4_028 | C120: C | D120: E | F120: Où peut-on trouver les fiches du guide technique mentionnées dans le récépissé d'une DT ou d'une DICT ?
C121: =IF(C120="C",IF(A121="P",IF(A120="I","p i","p"),IF(A120="I","i","")),"") | D121: =IF(D120="E",IF(A121="P",IF(A120="I","p i","p"),IF(A120="I","i"," ")),"") | E121: =IF(E120="O",IF(A121="P",IF(A120="I","p i","p"),IF(A120="I","i"," ")),"") | F121: A | G121: Elles sont obligatoirement jointes par l'exploitant de ce réseau au récépissé de DICT
A122: R554-5-5° | F122: B | G122: Elles sont téléchargeables sur le site du guichet unique www.reseaux-et-canalisations.gouv.fr
F123: C | G123: Elles sont téléchargeables sur le site internet de l'exploitant de ce réseau
F124: D | G124: Je ne sais pas
...

Sheet 2.5
A1: =Bilan!B18 -> 2.5 Lecture des indices et affleurants
C3: C | D3: E | E3: O | F3: Total
B4: Nb quest. | C4: =COUNTIF(C8:C631,C3) -> 21 | D4: =COUNTIF(D8:D631,D3) -> 25 | E4: =COUNTIF(E8:E631,E3) -> 24 | F4: =COUNTA(B8:B631) -> 28
B5: Illust. | C5: =COUNTIF(C8:C631,"i")+COUNTIF(C8:C631,"p i") -> 19 | D5: =COUNTIF(D8:D631,"i")+COUNTIF(D8:D631,"p i") -> 23 | E5: =COUNTIF(E8:E631,"i")+COUNTIF(E8:E631,"p i") -> 24 | F5: =COUNTIF(A8:A631,"I") -> 26
B6: Prio | C6: =COUNTIF(C8:C631,"p")+COUNTIF(C8:C631,"p i") -> 1 | D6: =COUNTIF(D8:D631,"p")+COUNTIF(D8:D631,"p i") -> 1 | E6: =COUNTIF(E8:E631,"p")+COUNTIF(E8:E631,"p i") -> 0 | F6: =COUNTIF(A8:A631,"P") -> 1
A8: I | B8: 2-5_001 | D8: E | E8: O | F8: Quelles canalisations peuvent changer brusquement de profondeur ?
C9: =IF(C8="C",IF(A9="P",IF(A8="I","p i","p"),IF(A8="I","i","")),"") | D9: =IF(D8="E",IF(A9="P",IF(A8="I","p i","p"),IF(A8="I","i"," ")),"") -> i | E9: =IF(E8="O",IF(A9="P",IF(A8="I","p i","p"),IF(A8="I","i"," ")),"") -> i | F9: A | G9: Uniquement les réseaux de gaz
A10: GT - § 2.2 | F10: B | G10: Uniquement les réseaux électriques
F11: C | G11: Tous les types de réseaux
F12: E | G12: Je ne sais pas
A14: I | B14: 2-5_003ce | C14: C | D14: E | F14: Lors d'un terrassement au dessus d'une canalisation, le grillage avertisseur risque d'être absent :
A15: P | C15: =IF(C14="C",IF(A15="P",IF(A14="I","p i","p"),IF(A14="I","i","")),"") -> p i | D15: =IF(D14="E",IF(A15="P",IF(A14="I","p i","p"),IF(A14="I","i"," ")),"") -> p i | E15: =IF(E14="O",IF(A15="P",IF(A14="I","p i","p"),IF(A14="I","i"," ")),"") | F15: A | G15: Lorsque la canalisation est classée non sensible pour la sécurité (assainissement par exemple)
A16: A13-7-00/art12 | F16: B | G16: Lorsque la canalisation est flexible
F17: C | G17: Pour tous les types de canalisation
F18: D | G18: Je ne sais pas
A20: I | B20: 2-5_003o | E20: O | F20: Lors d'un terrassement au dessus d'une canalisation, le grillage avertisseur peut être absent :
C21: =IF(C20="C",IF(A21="P",IF(A20="I","p i","p"),IF(A20="I","i","")),"") | D21: =IF(D20="E",IF(A21="P",IF(A20="I","p i","p"),IF(A20="I","i"," ")),"") | E21: =IF(E20="O",IF(A21="P",IF(A20="I","p i","p"),IF(A20="I","i"," ")),"") -> i | F21: A | G21: Lorsque la canalisation est classée non sensible pour la sécurité (assainissement par exemple)
A22: A13-7-00/art12 | F22: B | G22: Lorsque la canalisation est flexible
F23: C | G23: Pour tous les types de canalisation
F24: D | G24: Je ne sais pas
G25: A B C C
A26: I | B26: 2-5_004 | C26: C | D26: E | E26: O | F26: Laquelle de ces bornes signale un réseau enterré sensible pour la sécurité ?
C27: =IF(C26="C",IF(A27="P",IF(A26="I","p i","p"),IF(A26="I","i","")),"") -> i | D27: =IF(D26="E",IF(A27="P",IF(A26="I","p i","p"),IF(A26="I","i"," ")),"") -> i | E27: =IF(E26="O",IF(A27="P",IF(A26="I","p i","p"),IF(A26="I","i"," ")),"") -> i | F27: A | G27: -
A28: A5-3-14/art7-3 | F28: B | G28: -
F29: C | G29: -
F30: D | G30: Je ne sais pas
A32: I | B32: 2-5_005 | E32: O | F32: Je vais creuser dans une zone sans marquage au sol et je vois ce coffret sur un mur :
C33: =IF(C32="C",IF(A33="P",IF(A32="I","p i","p"),IF(A32="I","i","")),"") | D33: =IF(D32="E",IF(A33="P",IF(A32="I","p i","p"),IF(A32="I","i"," ")),"") | E33: =IF(E32="O",IF(A33="P",IF(A32="I","p i","p"),IF(A32="I","i"," ")),"") -> i | F33: A | G33: Je ne commence pas à creuser
A34: GT - 3.1.2.2/3.4.2 | F34: B | G34: Je l’ouvre pour connaître la direction du branchement
F35: C | G35: Je commence à creuser
F36: D | G36: Je ne sais pas
A40: I | B40: 2-5_006 | D40: E | E40: O | F40: Je vais creuser dans une zone sans marquage à proximité de ce bâtiment :
C41: =IF(C40="C",IF(A41="P",IF(A40="I","p i","p"),IF(A40="I","i","")),"") | D41: =IF(D40="E",IF(A41="P",IF(A40="I","p i","p"),IF(A40="I","i"," ")),"") -> i | E41: =IF(E40="O",IF(A41="P",IF(A40="I","p i","p"),IF(A40="I","i"," ")),"") -> i | F41: A | G41: J’ouvre la porte pour connaître les réseaux et leurs directions
A42: GT - § 3.1.2 | F42: B | G42: Je creuse en faisant attention
F43: C | G43: Je demande une vérification des réseaux et de leur emplacement
F44: D | G44: Je ne sais pas
B46: 2-5_007 | C46: C | D46: E | F46: Lorsqu'un indice ou affleurant (coffret…) montre l’existence d’un branchement souterrain, comment prendre en compte ce branchement ?
C47: =IF(C46="C",IF(A47="P",IF(A46="I","p i","p"),IF(A46="I","i","")),"") | D47: =IF(D46="E",IF(A47="P",IF(A46="I","p i","p"),IF(A46="I","i"," ")),"") | E47: =IF(E46="O",IF(A47="P",IF(A46="I","p i","p"),IF(A46="I","i"," ")),"") | F47: A | G47: Le branchement se trouve forcément sur le chemin le plus court entre l’affleurant et le réseau principal
A48: GT - § 5.2.7 | F48: B | G48: J’applique des précautions particulières de fouille dans une bande de 2 m de large centrée sur le marquage du branchement
F49: C | G49: J'ouvre l'affleurant pour connaître la direction du branchement
F50: D | G50: Je ne sais pas
A52: I | B52: 2-5_008 | C52: C | D52: E | E52: O | F52: En creusant, je rencontre un grillage avertisseur jaune. Il signale généralement un réseau :
C53: =IF(C52="C",IF(A53="P",IF(A52="I","p i","p"),IF(A52="I","i","")),"") -> i | D53: =IF(D52="E",IF(A53="P",IF(A52="I","p i","p"),IF(A52="I","i"," ")),"") -> i | E53: =IF(E52="O",IF(A53="P",IF(A52="I","p i","p"),IF(A52="I","i"," ")),"") -> i | F53: A | G53: D’électricité
A54: A13-7-00/art12 | F54: B | G54: De téléphone
A55: TC OPERATEUR | F55: C | G55: De gaz
F56: E | G56: Je ne sais pas
A57: I | B57: 2-5_009 | C57: C | D57: E | E57: O | F57: En creusant, je rencontre un grillage avertisseur rouge. Il signale généralement un réseau :
C58: =IF(C57="C",IF(A58="P",IF(A57="I","p i","p"),IF(A57="I","i","")),"") -> i | D58: =IF(D57="E",IF(A58="P",IF(A57="I","p i","p"),IF(A57="I","i"," ")),"") -> i | E58: =IF(E57="O",IF(A58="P",IF(A57="I","p i","p"),IF(A57="I","i"," ")),"") -> i | F58: A | G58: D’électricité
A59: D14-11-88/art19 | F59: B | G59: De téléphone
A60: TC OPERATEUR | F60: C | G60: De gaz
F61: D | G61: Je ne sais pas
A63: I | B63: 2-5_010 | C63: C | D63: E | E63: O | F63: En creusant, je rencontre un grillage avertisseur vert. Il signale généralement un réseau :
C64: =IF(C63="C",IF(A64="P",IF(A63="I","p i","p"),IF(A63="I","i","")),"") -> i | D64: =IF(D63="E",IF(A64="P",IF(A63="I","p i","p"),IF(A63="I","i"," ")),"") -> i | E64: =IF(E63="O",IF(A64="P",IF(A63="I","p i","p"),IF(A63="I","i"," ")),"") -> i | F64: A | G64: D’électricité
A65: NFS70-003-1/AnG2 | F65: B | G65: De télécommunication
F66: C | G66: D’eau potable
F67: D | G67: Je ne sais pas
A69: I | B69: 2-5_011 | C69: C | D69: E | E69: O | F69: En creusant, je rencontre un grillage avertisseur marron. Il signale généralement un réseau :
C70: =IF(C69="C",IF(A70="P",IF(A69="I","p i","p"),IF(A69="I","i","")),"") -> i | D70: =IF(D69="E",IF(A70="P",IF(A69="I","p i","p"),IF(A69="I","i"," ")),"") -> i | E70: =IF(E69="O",IF(A70="P",IF(A69="I","p i","p"),IF(A69="I","i"," ")),"") -> i | F70: A | G70: D’eau potable
A71: NFS70-003-1/AnG2 | F71: B | G71: D’eaux usées ou pluviales
F72: C | G72: De gaz
F73: D | G73: Je ne sais pas
A75: I | B75: 2-5_012 | C75: C | D75: E | E75: O | F75: En creusant, je rencontre un grillage avertisseur bleu. Il signale généralement un réseau :
C76: =IF(C75="C",IF(A76="P",IF(A75="I","p i","p"),IF(A75="I","i","")),"") -> i | D76: =IF(D75="E",IF(A76="P",IF(A75="I","p i","p"),IF(A75="I","i"," ")),"") -> i | E76: =IF(E75="O",IF(A76="P",IF(A75="I","p i","p"),IF(A75="I","i"," ")),"") -> i | F76: A | G76: D’eau potable
A77: NFS70-003-1/AnG2 | F77: B | G77: D’eaux usées ou pluviales
F78: C | G78: D’électricité
F79: D | G79: Je ne sais pas
A81: I | B81: 2-5_013 | C81: C | D81: E | E81: O | F81: En creusant, je rencontre un grillage avertisseur violet. Il signale généralement un réseau :
C82: =IF(C81="C",IF(A82="P",IF(A81="I","p i","p"),IF(A81="I","i","")),"") -> i | D82: =IF(D81="E",IF(A82="P",IF(A81="I","p i","p"),IF(A81="I","i"," ")),"") -> i | E82: =IF(E81="O",IF(A82="P",IF(A81="I","p i","p"),IF(A81="I","i"," ")),"") -> i | F82: A | G82: De chaleur
A83: NFS70-003-1/AnG2 | F83: B | G83: D’eaux usées ou pluviales
F84: C | G84: D’électricité
F85: D | G85: Je ne sais pas
A87: I | B87: 2-5_015 | D87: E | E87: O | F87: En creusant, je découvre un grillage avertisseur. La canalisation :
C88: =IF(C87="C",IF(A88="P",IF(A87="I","p i","p"),IF(A87="I","i","")),"") | D88: =IF(D87="E",IF(A88="P",IF(A87="I","p i","p"),IF(A87="I","i"," ")),"") -> i | E88: =IF(E87="O",IF(A88="P",IF(A87="I","p i","p"),IF(A87="I","i"," ")),"") -> i | F88: A | G88: Peut se trouver immédiatement sous le grillage
A89: NFS70-003-1/AnG2 | F89: B | G89: Se situe au minimum à 20 cm sous le grillage
F90: C | G90: Se situe au minimum à 40 cm sous le grillage
F91: D | G91: Je ne sais pas
A93: I | B93: 2-5_016 | C93: C | D93: E | E93: O | F93: Ce coffret est un affleurant de réseau:
C94: =IF(C93="C",IF(A94="P",IF(A93="I","p i","p"),IF(A93="I","i","")),"") -> i | D94: =IF(D93="E",IF(A94="P",IF(A93="I","p i","p"),IF(A93="I","i"," ")),"") -> i | E94: =IF(E93="O",IF(A94="P",IF(A93="I","p i","p"),IF(A93="I","i"," ")),"") -> i | F94: A | G94: De gaz
A95: GT - § 3.4 | F95: B | G95: D’eau potable
F96: C | G96: Electrique
F97: D | G97: Je ne sais pas
A99: I | B99: 2-5_017 | C99: C | D99: E | E99: O | F99: Ce coffret est un affleurant de réseau :
C100: =IF(C99="C",IF(A100="P",IF(A99="I","p i","p"),IF(A99="I","i","")),"") -> i | D100: =IF(D99="E",IF(A100="P",IF(A99="I","p i","p"),IF(A99="I","i"," ")),"") -> i | E100: =IF(E99="O",IF(A100="P",IF(A99="I","p i","p"),IF(A99="I","i"," ")),"") -> i | F100: A | G100: De gaz
A101: GT - § 3.1.2 | F101: B | G101: D’eau potable
F102: C | G102: Electrique
F103: D | G103: Je ne sais pas
A105: I | B105: 2-5_018 | C105: C | D105: E | E105: O | F105: Ce coffret est un affleurant de réseau :
C106: =IF(C105="C",IF(A106="P",IF(A105="I","p i","p"),IF(A105="I","i","")),"") -> i | D106: =IF(D105="E",IF(A106="P",IF(A105="I","p i","p"),IF(A105="I","i"," ")),"") -> i | E106: =IF(E105="O",IF(A106="P",IF(A105="I","p i","p"),IF(A105="I","i"," ")),"") -> i | F106: A | G106: De gaz
A107: GT - § 3.7 | F107: B | G107: D’eau potable
F108: C | G108: De télécommunications
F109: D | G109: Je ne sais pas
A111: I | B111: 2-5_019 | C111: C | D111: E | E111: O | F111: Ces deux types de bornes signalent un réseau :
C112: =IF(C111="C",IF(A112="P",IF(A111="I","p i","p"),IF(A111="I","i","")),"") -> i | D112: =IF(D111="E",IF(A112="P",IF(A111="I","p i","p"),IF(A111="I","i"," ")),"") -> i | E112: =IF(E111="O",IF(A112="P",IF(A111="I","p i","p"),IF(A111="I","i"," ")),"") -> i | F112: A | G112: De gaz
A113: GT - § 3.4 | F113: B | G113: Postal
F114: C | G114: D’hydrocarbures
F115: D | G115: Je ne sais pas
A117: I | B117: 2-5_020 | C117: C | D117: E | E117: O | F117: Ces repères indiquent un réseau :
C118: =IF(C117="C",IF(A118="P",IF(A117="I","p i","p"),IF(A117="I","i","")),"") -> i | D118: =IF(D117="E",IF(A118="P",IF(A117="I","p i","p"),IF(A117="I","i"," ")),"") -> i | E118: =IF(E117="O",IF(A118="P",IF(A117="I","p i","p"),IF(A117="I","i"," ")),"") -> i | F118: A | G118: De distribution de gaz
A119: GT - § 3.3 | F119: B | G119: De transport de gaz
F120: C | G120: D’hydrocarbures
...

Sheet 2.6
A1: =Bilan!B19 -> 2.6 Travaux sans tranchée
C3: C | D3: E | E3: O | F3: Total
B4: Nb quest. | C4: =COUNTIF(C8:C613,C3) -> 1 | D4: =COUNTIF(D8:D613,D3) -> 1 | E4: =COUNTIF(E8:E613,E3) -> 1 | F4: =COUNTA(B8:B613) -> 1
B5: Illust. | C5: =COUNTIF(C8:C613,"i")+COUNTIF(C8:C613,"p i") -> 1 | D5: =COUNTIF(D8:D613,"i")+COUNTIF(D8:D613,"p i") -> 1 | E5: =COUNTIF(E8:E613,"i")+COUNTIF(E8:E613,"p i") -> 1 | F5: =COUNTIF(A8:A613,"I") -> 1
B6: Prio | C6: =COUNTIF(C8:C613,"p")+COUNTIF(C8:C613,"p i") -> 0 | D6: =COUNTIF(D8:D613,"p")+COUNTIF(D8:D613,"p i") -> 0 | E6: =COUNTIF(E8:E613,"p")+COUNTIF(E8:E613,"p i") -> 0 | F6: =COUNTIF(A8:A613,"P") -> 0
A8: I | B8: 2-6_002 | C8: C | D8: E | E8: O | F8: Lors de travaux sans tranchée avec fusée pneumatique, la trajectoire de la fusée doit être surveillée :
C9: =IF(C8="C",IF(A9="P",IF(A8="I","p i","p"),IF(A8="I","i","")),"") -> i | D9: =IF(D8="E",IF(A9="P",IF(A8="I","p i","p"),IF(A8="I","i"," ")),"") -> i | E9: =IF(E8="O",IF(A9="P",IF(A8="I","p i","p"),IF(A8="I","i"," ")),"") -> i | F9: A | G9: Au lancement
A10: Fiche ST-FUS1 du GT | F10: B | G10: A la fin du parcours
F11: C | G11: Durant tout le parcours
F12: D | G12: Je ne sais pas
C116: =IF(C115="C",IF(A116="P",IF(A115="I","p i","p"),IF(A115="I","i","")),"") | D116: =IF(D115="E",IF(A116="P",IF(A115="I","p i","p"),IF(A115="I","i"," ")),"") | E116: =IF(E115="O",IF(A116="P",IF(A115="I","p i","p"),IF(A115="I","i"," ")),"")
C123: =IF(C122="C",IF(A123="P",IF(A122="I","p i","p"),IF(A122="I","i","")),"") | D123: =IF(D122="E",IF(A123="P",IF(A122="I","p i","p"),IF(A122="I","i"," ")),"") | E123: =IF(E122="O",IF(A123="P",IF(A122="I","p i","p"),IF(A122="I","i"," ")),"")
C130: =IF(C129="C",IF(A130="P",IF(A129="I","p i","p"),IF(A129="I","i","")),"") | D130: =IF(D129="E",IF(A130="P",IF(A129="I","p i","p"),IF(A129="I","i"," ")),"") | E130: =IF(E129="O",IF(A130="P",IF(A129="I","p i","p"),IF(A129="I","i"," ")),"")
C137: =IF(C136="C",IF(A137="P",IF(A136="I","p i","p"),IF(A136="I","i","")),"") | D137: =IF(D136="E",IF(A137="P",IF(A136="I","p i","p"),IF(A136="I","i"," ")),"") | E137: =IF(E136="O",IF(A137="P",IF(A136="I","p i","p"),IF(A136="I","i"," ")),"")
C144: =IF(C143="C",IF(A144="P",IF(A143="I","p i","p"),IF(A143="I","i","")),"") | D144: =IF(D143="E",IF(A144="P",IF(A143="I","p i","p"),IF(A143="I","i"," ")),"") | E144: =IF(E143="O",IF(A144="P",IF(A143="I","p i","p"),IF(A143="I","i"," ")),"")
C145: =IF(C144="C",IF(A145="Prioritaire",IF(A144="I","p i","p"),IF(A144="I","i","")),"") | D145: =IF(D144="E",IF(A145="Prioritaire",IF(A144="I","p i","p"),IF(A144="I","i"," ")),"") | E145: =IF(E144="O",IF(A145="Prioritaire",IF(A144="I","p i","p"),IF(A144="I","i"," ")),"")
C151: =IF(C150="C",IF(A151="P",IF(A150="I","p i","p"),IF(A150="I","i","")),"") | D151: =IF(D150="E",IF(A151="P",IF(A150="I","p i","p"),IF(A150="I","i"," ")),"") | E151: =IF(E150="O",IF(A151="P",IF(A150="I","p i","p"),IF(A150="I","i"," ")),"")
C158: =IF(C157="C",IF(A158="P",IF(A157="I","p i","p"),IF(A157="I","i","")),"") | D158: =IF(D157="E",IF(A158="P",IF(A157="I","p i","p"),IF(A157="I","i"," ")),"") | E158: =IF(E157="O",IF(A158="P",IF(A157="I","p i","p"),IF(A157="I","i"," ")),"")
C165: =IF(C164="C",IF(A165="P",IF(A164="I","p i","p"),IF(A164="I","i","")),"") | D165: =IF(D164="E",IF(A165="P",IF(A164="I","p i","p"),IF(A164="I","i"," ")),"") | E165: =IF(E164="O",IF(A165="P",IF(A164="I","p i","p"),IF(A164="I","i"," ")),"")
C172: =IF(C171="C",IF(A172="P",IF(A171="I","p i","p"),IF(A171="I","i","")),"") | D172: =IF(D171="E",IF(A172="P",IF(A171="I","p i","p"),IF(A171="I","i"," ")),"") | E172: =IF(E171="O",IF(A172="P",IF(A171="I","p i","p"),IF(A171="I","i"," ")),"")
C179: =IF(C178="C",IF(A179="P",IF(A178="I","p i","p"),IF(A178="I","i","")),"") | D179: =IF(D178="E",IF(A179="P",IF(A178="I","p i","p"),IF(A178="I","i"," ")),"") | E179: =IF(E178="O",IF(A179="P",IF(A178="I","p i","p"),IF(A178="I","i"," ")),"")
C186: =IF(C185="C",IF(A186="P",IF(A185="I","p i","p"),IF(A185="I","i","")),"") | D186: =IF(D185="E",IF(A186="P",IF(A185="I","p i","p"),IF(A185="I","i"," ")),"") | E186: =IF(E185="O",IF(A186="P",IF(A185="I","p i","p"),IF(A185="I","i"," ")),"")
C193: =IF(C192="C",IF(A193="P",IF(A192="I","p i","p"),IF(A192="I","i","")),"") | D193: =IF(D192="E",IF(A193="P",IF(A192="I","p i","p"),IF(A192="I","i"," ")),"") | E193: =IF(E192="O",IF(A193="P",IF(A192="I","p i","p"),IF(A192="I","i"," ")),"")
C200: =IF(C199="C",IF(A200="P",IF(A199="I","p i","p"),IF(A199="I","i","")),"") | D200: =IF(D199="E",IF(A200="P",IF(A199="I","p i","p"),IF(A199="I","i"," ")),"") | E200: =IF(E199="O",IF(A200="P",IF(A199="I","p i","p"),IF(A199="I","i"," ")),"")
C207: =IF(C206="C",IF(A207="P",IF(A206="I","p i","p"),IF(A206="I","i","")),"") | D207: =IF(D206="E",IF(A207="P",IF(A206="I","p i","p"),IF(A206="I","i"," ")),"") | E207: =IF(E206="O",IF(A207="P",IF(A206="I","p i","p"),IF(A206="I","i"," ")),"")
C214: =IF(C213="C",IF(A214="P",IF(A213="I","p i","p"),IF(A213="I","i","")),"") | D214: =IF(D213="E",IF(A214="P",IF(A213="I","p i","p"),IF(A213="I","i"," ")),"") | E214: =IF(E213="O",IF(A214="P",IF(A213="I","p i","p"),IF(A213="I","i"," ")),"")
C221: =IF(C220="C",IF(A221="P",IF(A220="I","p i","p"),IF(A220="I","i","")),"") | D221: =IF(D220="E",IF(A221="P",IF(A220="I","p i","p"),IF(A220="I","i"," ")),"") | E221: =IF(E220="O",IF(A221="P",IF(A220="I","p i","p"),IF(A220="I","i"," ")),"")
C228: =IF(C227="C",IF(A228="P",IF(A227="I","p i","p"),IF(A227="I","i","")),"") | D228: =IF(D227="E",IF(A228="P",IF(A227="I","p i","p"),IF(A227="I","i"," ")),"") | E228: =IF(E227="O",IF(A228="P",IF(A227="I","p i","p"),IF(A227="I","i"," ")),"")
... C430: =IF(C429="C",IF(A430="P",IF(A429="I","p i","p"),IF(A429="I","i","")),"") | D430: =IF(D429="E",IF(A430="P",IF(A429="I","p i","p"),IF(A429="I","i"," ")),"") | E430: =IF(E429="O",IF(A430="P",IF(A429="I","p i","p"),IF(A429="I","i"," ")),"")
C431: =IF(C430="C",IF(A431="Prioritaire",IF(A430="I","p i","p"),IF(A430="I","i","")),"") | D431: =IF(D430="E",IF(A431="Prioritaire",IF(A430="I","p i","p"),IF(A430="I","i"," ")),"") | E431: =IF(E430="O",IF(A431="Prioritaire",IF(A430="I","p i","p"),IF(A430="I","i"," ")),"")

Sheet 3.1
A1: =Bilan!B21 -> 3.1 Constat d'arrêt ou de sursis
C3: C | D3: E | E3: O | F3: Total
B4: Nb quest. | C4: =COUNTIF(C8:C616,C3) -> 3 | D4: =COUNTIF(D8:D616,D3) -> 7 | E4: =COUNTIF(E8:E616,E3) -> 11 | F4: =COUNTA(B8:B616) -> 18
B5: Illust. | C5: =COUNTIF(C8:C616,"i")+COUNTIF(C8:C616,"p i") -> 1 | D5: =COUNTIF(D8:D616,"i")+COUNTIF(D8:D616,"p i") -> 5 | E5: =COUNTIF(E8:E616,"i")+COUNTIF(E8:E616,"p i") -> 11 | F5: =COUNTIF(A8:A616,"I") -> 16
B6: Prio | C6: =COUNTIF(C8:C616,"p")+COUNTIF(C8:C616,"p i") -> 1 | D6: =COUNTIF(D8:D616,"p")+COUNTIF(D8:D616,"p i") -> 1 | E6: =COUNTIF(E8:E616,"p")+COUNTIF(E8:E616,"p i") -> 1 | F6: =COUNTIF(A8:A616,"P") -> 2
A8: I | B8: 3-1_002 | C8: C | D8: E | F8: Si en cours de chantier, l'opérateur découvre un réseau sans marquage au sol susceptible de gêner les travaux, que doit-il faire ?
A9: P | C9: =IF(C8="C",IF(A9="P",IF(A8="I","p i","p"),IF(A8="I","i","")),"") -> p i | D9: =IF(D8="E",IF(A9="P",IF(A8="I","p i","p"),IF(A8="I","i"," ")),"") -> p i | E9: =IF(E8="O",IF(A9="P",IF(A8="I","p i","p"),IF(A8="I","i"," ")),"") | F9: A | G9: Arrêter immédiatement les travaux et en référer au responsable de projet
A10: R554-28I | F10: B | G10: Compléter le marquage et continuer les travaux
F11: C | G11: Couper la canalisation car elle est probablement abandonnée
F12: D | G12: Je ne sais pas
B14: 3-1_005 | C14: C | D14: E | F14: Suite à la découverte d'un réseau non identifié nécessitant un constat d'arrêt de travaux, celui-ci est signé par l'exécutant des travaux ainsi que par :
C15: =IF(C14="C",IF(A15="P",IF(A14="I","p i","p"),IF(A14="I","i","")),"") | D15: =IF(D14="E",IF(A15="P",IF(A14="I","p i","p"),IF(A14="I","i"," ")),"") | E15: =IF(E14="O",IF(A15="P",IF(A14="I","p i","p"),IF(A14="I","i"," ")),"") | F15: A | G15: L'exploitant du réseau concerné
A16: NFS70-003-1/AnC | F16: B | G16: Le responsable de projet
F17: C | G17: L'inspecteur du travail
F18: D | G18: Je ne sais pas
A20: I | B20: 3-1_006 | E20: O | F20: Quand je découvre un réseau non identifié en creusant dans une zone sans marquage au sol, que dois-je faire ?
C21: =IF(C20="C",IF(A21="P",IF(A20="I","p i","p"),IF(A20="I","i","")),"") | D21: =IF(D20="E",IF(A21="P",IF(A20="I","p i","p"),IF(A20="I","i"," ")),"") | E21: =IF(E20="O",IF(A21="P",IF(A20="I","p i","p"),IF(A20="I","i"," ")),"") -> i | F21: A | G21: Informer tout de suite mon chef et attendre ses consignes
A22: R554-28I | F22: B | G22: Reboucher aussitôt le trou
A23: TC OPERATEUR | F23: C | G23: Continuer car le réseau ne doit plus être en service
F24: D | G24: Je ne sais pas
A26: I | B26: 3-1_007e | D26: E | F26: Dans une tranchée, un câble électrique mal placé gêne le chantier :
D27: =IF(D26="E",IF(A27="P",IF(A26="I","p i","p"),IF(A26="I","i"," ")),"") -> i | E27: =IF(E26="O",IF(A27="P",IF(A26="I","p i","p"),IF(A26="I","i"," ")),"") | F27: A | G27: Je suspends les travaux aux abords du câble
A28: R554-28I | F28: B | G28: J'impose le port de gants isolants aux personnels
F29: C | G29: Je fais déplacer le câble hors de la tranchée
F30: D | G30: Je ne sais pas
A32: I | B32: 3-1_007o | E32: O | F32: Dans une tranchée, un câble électrique mal placé gêne le chantier :
D33: =IF(D32="E",IF(A33="P",IF(A32="I","p i","p"),IF(A32="I","i"," ")),"") | E33: =IF(E32="O",IF(A33="P",IF(A32="I","p i","p"),IF(A32="I","i"," ")),"") -> i | F33: A | G33: J'appelle mon chef pour savoir ce qu'il faut faire
A34: R554-28I | F34: B | G34: Je mets des gants isolants et je le déplace à la main
F35: C | G35: Je le déplace légèrement avec l'engin
F36: D | G36: Je ne sais pas
B38: 3-1_010 | C38: C | D38: E | F38: Lors de travaux, l'executant de travaux découvre un réseau qui présente un écart notable de localisation mettant en cause la poursuite du chantier. Que doit faire l'encadrant du chantier ?
C39: =IF(C38="C",IF(A39="P",IF(A38="I","p i","p"),IF(A38="I","i","")),"") | D39: =IF(D38="E",IF(A39="P",IF(A38="I","p i","p"),IF(A38="I","i"," ")),"") | E39: =IF(E38="O",IF(A39="P",IF(A38="I","p i","p"),IF(A38="I","i"," ")),"") | F39: A | G39: Poursuivre le chantier en prenant toutes les mesures de sécurité nécessaires puis informer le maître d'ouvrage et l'exploitant du réseau en cause pour se dégager de toute responsabilité
A40: R554-28I | F40: B | G40: Arrêter les travaux, alerter le responsable de projet (maître d'ouvrage) et attendre sa décision écrite sur les mesures à prendre
F41: C | G41: Contacter directement l'exploitant du réseau en cause qui doit immédiatement procéder à la mise en sécurité du réseau
F42: D | G42: Je ne sais pas
A44: I | B44: 3-1_011 | E44: O | F44: Dans une fouille, je découvre un câble électrique non cartographié. Comment dois-je le considérer ?
A45: P | D45: =IF(D44="E",IF(A45="P",IF(A44="I","p i","p"),IF(A44="I","i"," ")),"") | E45: =IF(E44="O",IF(A45="P",IF(A44="I","p i","p"),IF(A44="I","i"," ")),"") -> p i | F45: A | G45: Comme étant hors tension
F46: B | G46: Comme étant sous tension
F47: C | G47: Comme étant hors service
F48: D | G48: Je ne sais pas
A51: I | B51: 3-1_011e | D51: E | F51: Dans une fouille, je découvre un câble électrique non cartographié. Comment dois-je le considérer ?
D52: =IF(D51="E",IF(A52="P",IF(A51="I","p i","p"),IF(A51="I","i"," ")),"") -> i | E52: =IF(E51="O",IF(A52="P",IF(A51="I","p i","p"),IF(A51="I","i"," ")),"") | F52: A | G52: Comme étant hors tension
F53: B | G53: Comme étant sous tension
F54: C | G54: Comme étant hors service
F55: D | G55: Je ne sais pas
A57: I | B57: 3-1_012 | E57: O | F57: Si le réseau flexible à soutenir est endommagé :
D58: =IF(D57="E",IF(A58="P",IF(A57="I","p i","p"),IF(A57="I","i"," ")),"") | E58: =IF(E57="O",IF(A58="P",IF(A57="I","p i","p"),IF(A57="I","i"," ")),"") -> i | F58: A | G58: Je double le nombre de sangles
A59: NF C 18-510 | F59: B | G59: Je préviens mon responsable pour qu'il alerte l'exploitant
F60: C | G60: Je le répare avec du ruban adhésif avant de faire le soutènement
F61: D | G61: Je ne sais pas
A63: I | B63: 3-1_013 | D63: E | F63: Un opérateur devant soutenir un câble électrique m'informe que celui-ci est endommagé. Que dois-je faire ?
D64: =IF(D63="E",IF(A64="P",IF(A63="I","p i","p"),IF(A63="I","i"," ")),"") -> i | E64: =IF(E63="O",IF(A64="P",IF(A63="I","p i","p"),IF(A63="I","i"," ")),"") | F64: A | G64: Je fais doubler le nombre de sangles
A65: NF C 18-510 | F65: B | G65: Je fais arrêter l'opération et j'alerte l'exploitant
F66: C | G66: Je le fais réparer avec du ruban adhésif avant de faire le soutènement
F67: D | G67: Je ne sais pas
A69: I | B69: 3-1_014o | E69: O | F69: Pour dégager une canalisation électrique noyée dans du béton :
D70: =IF(D69="E",IF(A70="P",IF(A69="I","p i","p"),IF(A69="I","i"," ")),"") | E70: =IF(E69="O",IF(A70="P",IF(A69="I","p i","p"),IF(A69="I","i"," ")),"") -> i | F70: A | G70: J'utilise un marteau piqueur
A71: NF C 18-510 | F71: B | G71: J'utilise une barre à mines sans taper fort
F72: C | G72: Je demande la mise hors tension à mon responsable
F73: D | G73: Je ne sais pas
A75: I | B75: 3-1_014e | D75: E | F75: Un opérateur m'informe qu'une canalisation d'un réseau sensible à dégager est emprisonnée dans du béton. Que dois-je faire ?
D76: =IF(D75="E",IF(A76="P",IF(A75="I","p i","p"),IF(A75="I","i"," ")),"") -> i | E76: =IF(E75="O",IF(A76="P",IF(A75="I","p i","p"),IF(A75="I","i"," ")),"") | F76: A | G76: Je lui demande de la dégager à l'aide d'un petit marteur piqueur
A77: NF C 18-510 | F77: B | G77: Je lui demande de la dégager avec une barre à mine isolante
F78: C | G78: Je demande la mise hors tension à l'exploitant
F79: D | G79: Je ne sais pas
A82: I | B82: 3-1_015 | E82: O | F82: Cet engin est en contact avec une ligne haute tension :
D83: =IF(D82="E",IF(A83="P",IF(A82="I","p i","p"),IF(A82="I","i"," ")),"") | E83: =IF(E82="O",IF(A83="P",IF(A82="I","p i","p"),IF(A82="I","i"," ")),"") -> i | F83: A | G83: Seul l'ouvrier qui touche l'engin (à gauche de l'image) peut être électrisé
A84: NF C 18-510 | F84: B | G84: L'ouvrier qui touche l'engin et celui qui se trouve à distance (en bas de l'image) peuvent être électrisés
F85: C | G85: Aucun des deux ouvriers ne peut être électrisés
F86: D | G86: Je ne sais pas
A88: I | B88: 3-1_016 | E88: O | F88: A l'arrivée sur le chantier, je constate que la tête du poteau a été endommagée :
D89: =IF(D88="E",IF(A89="P",IF(A88="I","p i","p"),IF(A88="I","i"," ")),"") | E89: =IF(E88="O",IF(A89="P",IF(A88="I","p i","p"),IF(A88="I","i"," ")),"") -> i | F89: A | G89: Cela ne pose pas de problème car le câble est isolé
A90: NF C 18-510 | F90: B | G90: Cela nécessite une intervention en urgence, et j'informe mon chef
F91: C | G91: C’est le problème du propriétaire du terrain
F92: D | G92: Je ne sais pas
A94: I | B94: 3-1_017 | E94: O | F94: Cette canalisation isolée a reçu un coup lors de la réalisation d’une tranchée :
D95: =IF(D94="E",IF(A95="P",IF(A94="I","p i","p"),IF(A94="I","i"," ")),"") | E95: =IF(E94="O",IF(A95="P",IF(A94="I","p i","p"),IF(A94="I","i"," ")),"") -> i | F95: A | G95: Il n’y a pas de problème : les conducteurs électriques ne sont visiblement pas touchés
A96: NF C 18-510 | F96: B | G96: En tout premier lieu, il faut prévenir l’exploitant
F97: C | G97: Il faut s’éloigner immédiatement et prévenir le responsable du chantier
F98: D | G98: Je ne sais pas
A101: I | B101: 3-1_018 | E101: O | F101: Lors des travaux, ces câbles électriques ont été sectionnés :
D102: =IF(D101="E",IF(A102="P",IF(A101="I","p i","p"),IF(A101="I","i"," ")),"") | E102: =IF(E101="O",IF(A102="P",IF(A101="I","p i","p"),IF(A101="I","i"," ")),"") -> i | F102: A | G102: Je peux les raccorder avec une bonne épissure et les enfermer dans une boite, avant de reboucher
A103: NF C 18-510 | F103: B | G103: Je dois prévenir mon chef et attendre les consignes
F104: C | G104: Je demande à un électricien habilité de raccorder les conducteurs
F105: D | G105: Je ne sais pas
A107: I | B107: 3-1_019 | E107: O | F107: Ce coffret électrique est endommagé :
D108: =IF(D107="E",IF(A108="P",IF(A107="I","p i","p"),IF(A107="I","i"," ")),"") | E108: =IF(E107="O",IF(A108="P",IF(A107="I","p i","p"),IF(A107="I","i"," ")),"") -> i | F108: A | G108: Il a été sécurisé provisoirement par l’exploitant : je ne dois pas y toucher
A109: NF C 18-510 | F109: B | G109: Je peux l'ouvrir pour constater les dégâts
F110: C | G110: Je le répare
F111: D | G111: Je ne sais pas
C112: =IF(C111="C",IF(A112="P",IF(A111="I","p i","p"),IF(A111="I","i","")),"") | D112: =IF(D111="E",IF(A112="P",IF(A111="I","p i","p"),IF(A111="I","i"," ")),"") | E112: =IF(E111="O",IF(A112="P",IF(A111="I","p i","p"),IF(A111="I","i"," ")),"")
A114: I | B114: 3-1_020 | E114: O | F114: Du béton est remonté dans ce coffret :
D115: =IF(D114="E",IF(A115="P",IF(A114="I","p i","p"),IF(A114="I","i"," ")),"") | E115: =IF(E114="O",IF(A115="P",IF(A114="I","p i","p"),IF(A114="I","i"," ")),"") -> i | F115: A | G115: Je peux l'enlever au burineur
A116: NF C 18-510 | F116: B | G116: Je peux intervenir car il n'y a plus de courant
F117: C | G117: Je ne peux pas intervenir
F118: D | G118: Je ne sais pas
C119: =IF(C118="C",IF(A119="P",IF(A118="I","p i","p"),IF(A118="I","i","")),"") | D119: =IF(D118="E",IF(A119="P",IF(A118="I","p i","p"),IF(A118="I","i"," ")),"") | E119: =IF(E118="O",IF(A119="P",IF(A118="I","p i","p"),IF(A118="I","i"," ")),"")
C126: =IF(C125="C",IF(A126="P",IF(A125="I","p i","p"),IF(A125="I","i","")),"") | D126: =IF(D125="E",IF(A126="P",IF(A125="I","p i","p"),IF(A125="I","i"," ")),"") | E126: =IF(E125="O",IF(A126="P",IF(A125="I","p i","p"),IF(A125="I","i"," ")),"")
C133: =IF(C132="C",IF(A133="P",IF(A132="I","p i","p"),IF(A132="I","i","")),"") | D133: =IF(D132="E",IF(A133="P",IF(A132="I","p i","p"),IF(A132="I","i"," ")),"") | E133: =IF(E132="O",IF(A133="P",IF(A132="I","p i","p"),IF(A132="I","i"," ")),"")
C140: =IF(C139="C",IF(A140="P",IF(A139="I","p i","p"),IF(A139="I","i","")),"") | D140: =IF(D139="E",IF(A140="P",IF(A139="I","p i","p"),IF(A139="I","i"," ")),"") | E140: =IF(E139="O",IF(A140="P",IF(A139="I","p i","p"),IF(A139="I","i"," ")),"")
...

Sheet 3.2
A1: =Bilan!B22 -> 3.2 Constat de dommage
C3: C | D3: E | E3: O | F3: Total
B4: Nb quest. | C4: =COUNTIF(C8:C663,C3) -> 7 | D4: =COUNTIF(D8:D663,D3) -> 14 | E4: =COUNTIF(E8:E663,E3) -> 15 | F4: =COUNTA(B8:B694) -> 24
B5: Illust. | C5: =COUNTIF(C8:C663,"i")+COUNTIF(C8:C663,"p i") -> 4 | D5: =COUNTIF(D8:D663,"i")+COUNTIF(D8:D663,"p i") -> 9 | E5: =COUNTIF(E8:E663,"i")+COUNTIF(E8:E663,"p i") -> 15 | F5: =COUNTIF(A8:A694,"I") -> 19
B6: Prio | C6: =COUNTIF(C8:C663,"p")+COUNTIF(C8:C663,"p i") -> 2 | D6: =COUNTIF(D8:D663,"p")+COUNTIF(D8:D663,"p i") -> 3 | E6: =COUNTIF(E8:E663,"p")+COUNTIF(E8:E663,"p i") -> 2 | F6: =COUNTIF(A8:A694,"P") -> 4
B8: 3-2_003 | C8: C | D8: E | F8: Le remplissage d’un constat contradictoire en cas de dommage est fait conjointement par :
C9: =IF(C8="C",IF(A9="P",IF(A8="I","p i","p"),IF(A8="I","i","")),"") | D9: =IF(D8="E",IF(A9="P",IF(A8="I","p i","p"),IF(A8="I","i"," ")),"") | E9: =IF(E8="O",IF(A9="P",IF(A8="I","p i","p"),IF(A8="I","i"," ")),"") | F9: A | G9: L’entreprise exécutant les travaux et l’exploitant du réseau concerné
A10: NFS70-003-1/AnE | F10: B | G10: L’entreprise exécutant les travaux et le responsable de projet (ou maître d’ouvrage)
F11: C | G11: Le responsable de projet (ou maître d’ouvrage) et l’exploitant de réseau concerné
F12: D | G12: Je ne sais pas
B14: 3-2_004ce | C14: C | D14: E | F14: En cas d’endommagement d'un réseau de gaz, indiquez la consigne parmi les suivantes qui ne fait pas partie intégrante de la règle des 4A :
C15: =IF(C14="C",IF(A15="P",IF(A14="I","p i","p"),IF(A14="I","i","")),"") | D15: =IF(D14="E",IF(A15="P",IF(A14="I","p i","p"),IF(A14="I","i"," ")),"") | E15: =IF(E14="O",IF(A15="P",IF(A14="I","p i","p"),IF(A14="I","i"," ")),"") | F15: A | G15: Accueillir les secours
A16: A15-2-12/An5-3 | F16: B | G16: Alerter les pompiers
F17: C | G17: Arrêter la fuite
F18: D | G18: Je ne sais pas
A20: I | B20: 3-2_004o | E20: O | F20: J'ai heurté une canalisation et du gaz s'échappe. Quelle consigne n'est pas prévue dans la règle des 4A ?
C21: =IF(C20="C",IF(A21="P",IF(A20="I","p i","p"),IF(A20="I","i","")),"") | D21: =IF(D20="C",IF(B21="P",IF(B20="I","p i","p"),IF(B20="I","i","")),"") | E21: =IF(E20="O",IF(A21="P",IF(A20="I","p i","p"),IF(A20="I","i"," ")),"") -> i | F21: A | G21: Arrêter les engins et les matériels électriques
A22: A15-2-12/An5-3 | F22: B | G22: Appeler les pompiers
F23: C | G23: Arrêter la fuite
F24: D | G24: Je ne sais pas
B26: 3-2_005 | C26: C | D26: E | F26: Un opérateur d’engin a touché une canalisation de gaz avec le godet provoquant une légère éraflure. Que faire ?
A27: P | C27: =IF(C26="C",IF(A27="P",IF(A26="I","p i","p"),IF(A26="I","i","")),"") -> p | D27: =IF(D26="E",IF(A27="P",IF(A26="I","p i","p"),IF(A26="I","i"," ")),"") -> p | E27: =IF(E26="O",IF(A27="P",IF(A26="I","p i","p"),IF(A26="I","i"," ")),"") | F27: A | G27: Entourer la conduite d’un adhésif résistant
A28: R554-31II | F28: B | G28: Arrêter les travaux dans la zone et contacter l’exploitant ainsi que le responsable de projet afin de leur signaler l’incident
F29: C | G29: Continuer le travail car la canalisation est protégée par la protection cathodique
F30: D | G30: Je ne sais pas
A32: I | B32: 3-2_008 | E32: O | F32: J’ai heurté une canalisation de gaz avec une mini-pelle sans provoquer de fuite :
A33: P | C33: =IF(C32="C",IF(A33="P",IF(A32="I","p i","p"),IF(A32="I","i","")),"") | D33: =IF(D32="E",IF(A33="P",IF(A32="I","p i","p"),IF(A32="I","i"," ")),"") | E33: =IF(E32="O",IF(A33="P",IF(A32="I","p i","p"),IF(A32="I","i"," ")),"") -> p i | F33: A | G33: Je continue le chantier, car les canalisations sont prévues pour résister aux chocs légers
A34: R554-31II | F34: B | G34: Je rebouche la tranchée sans rien dire
F35: C | G35: J'arrête tout de suite les travaux
F36: D | G36: Je ne sais pas
B38: 3-2_009 | D38: E | F38: En cas d’endommagement d’une canalisation de gaz avec fuite, en tant qu'encadrant de chantier, j’alerte dans l’ordre :
C39: =IF(C38="C",IF(A39="P",IF(A38="I","p i","p"),IF(A38="I","i","")),"") | D39: =IF(D38="E",IF(A39="P",IF(A38="I","p i","p"),IF(A38="I","i"," ")),"") | E39: =IF(E38="O",IF(A39="P",IF(A38="I","p i","p"),IF(A38="I","i"," ")),"") | F39: A | G39: Les pompiers, l’exploitant, le responsable de projet (ou maître d'ouvrage)
A40: R554-31II | F40: B | G40: L’exploitant, la police, les pompiers
F41: C | G41: Le responsable de projet (ou maître d'ouvrage), le 112, l’exploitant
F42: D | G42: Je ne sais pas
A44: I | B44: 3-2_014e | D44: E | F44: Un opérateur vient de prendre une décharge électrique, mais ça a l'air d'aller. Que dois-je faire ?
C45: =IF(C44="C",IF(A45="P",IF(A44="I","p i","p"),IF(A44="I","i","")),"") | D45: =IF(D44="E",IF(A45="P",IF(A44="I","p i","p"),IF(A44="I","i"," ")),"") -> i | E45: =IF(E44="O",IF(A45="P",IF(A44="I","p i","p"),IF(A44="I","i"," ")),"") | F45: A | G45: Rien de particulier, il continue son travail
A46: A15-2-12/An5-3 | F46: B | G46: J'en parle à un collègue pour qu’il le surveille
F47: C | G47: Je le fais accompagner à un service médical pour un électrocardiogramme
F48: D | G48: Je ne sais pas
A50: I | B50: 3-2_010o | E50: O | F50: J'ai heurté une canalisation et du gaz s'échappe, je dois d'abord alerter :
C51: =IF(C50="E",IF(#REF!="P",IF(#REF!="I","p i","p"),IF(#REF!="I","i"," ")),"") | D51: =IF(D50="E",IF(A51="P",IF(A50="I","p i","p"),IF(A50="I","i"," ")),"") | E51: =IF(E50="O",IF(A51="P",IF(A50="I","p i","p"),IF(A50="I","i"," ")),"") -> i | F51: A | G51: La police
A52: R554-31II | F52: B | G52: Les pompiers
F53: C | G53: L'exploitant
F54: D | G54: Je ne sais pas
A56: I | B56: 3-2_011 | C56: C | D56: E | E56: O | F56: Suite à un accident, j'appelle les pompiers. Je peux raccrocher dès que :
C57: =IF(C56="C",IF(A57="P",IF(A56="I","p i","p"),IF(A56="I","i","")),"") -> i | D57: =IF(D56="E",IF(A57="P",IF(A56="I","p i","p"),IF(A56="I","i"," ")),"") -> i | E57: =IF(E56="O",IF(A57="P",IF(A56="I","p i","p"),IF(A56="I","i"," ")),"") -> i | F57: A | G57: J'ai indiqué la nature et le lieu de l'accident
A58: A15-2-12/An5-3 | F58: B | G58: J'ai fourni le nombre de victimes et leur nom
F59: C | G59: Le pompier me le demande
F60: D | G60: Je ne sais pas
A62: I | B62: 3-2_013 | C62: C | D62: E | E62: O | F62: Une personne prend une décharge électrique et reste en contact avec le câble électrique. Je m'écarte et j'appelle en tout premier ? | H62: x
C63: =IF(C62="C",IF(A63="P",IF(A62="I","p i","p"),IF(A62="I","i","")),"") -> i | D63: =IF(D62="E",IF(A63="P",IF(A62="I","p i","p"),IF(A62="I","i"," ")),"") -> i | E63: =IF(E62="O",IF(A63="P",IF(A62="I","p i","p"),IF(A62="I","i"," ")),"") -> i | F63: A | G63: Les pompiers
A64: A15-2-12/An5-3 | F64: B | G64: L'exploitant
F65: C | G65: le responsable de projet (ou maître d'ouvrage)
F66: D | G66: Je ne sais pas
A68: I | B68: 3-2_014 | E68: O | F68: Je viens de prendre une décharge électrique, mais ça a l'air d'aller. Que dois-je faire ?
C69: =IF(C68="C",IF(A69="P",IF(A68="I","p i","p"),IF(A68="I","i","")),"") | D69: =IF(D68="E",IF(A69="P",IF(A68="I","p i","p"),IF(A68="I","i"," ")),"") | E69: =IF(E68="O",IF(A69="P",IF(A68="I","p i","p"),IF(A68="I","i"," ")),"") -> i | F69: A | G69: Rien de particulier, je continue mon travail
A70: A15-2-12/An5-3 | F70: B | G70: J'en parle à un collègue pour qu’il me surveille
F71: C | G71: Je préviens tout de suite mon chef qui doit m'orienter vers un service médical
F72: D | G72: Je ne sais pas
A74: I | B74: 3-2_015ce | C74: C | D74: E | F74: En cas d’endommagement d’une canalisation de gaz avec fuite, la règle des 4A signifie :
A75: P | C75: =IF(C74="C",IF(A75="P",IF(A74="I","p i","p"),IF(A74="I","i","")),"") -> p i | D75: =IF(D74="E",IF(A75="P",IF(A74="I","p i","p"),IF(A74="I","i"," ")),"") -> p i | E75: =IF(E74="O",IF(A75="P",IF(A74="I","p i","p"),IF(A74="I","i"," ")),"") | F75: A | G75: Alerter, Agir, Aménager, Accompagner
A76: A15-2-12/An5-3 | F76: B | G76: Avertir, Arranger, Arrêter, Accueillir
F77: C | G77: Arrêter, Alerter, Aménager, Accueillir
F78: E | G78: Je ne sais pas
A80: I | B80: 3-2_015o | E80: O | F80: J'ai heurté une canalisation et du gaz s'échappe, que faire en tout premier ?
C81: =IF(C80="C",IF(A83="P",IF(A80="I","p i","p"),IF(A80="I","i","")),"") | D81: =IF(D80="E",IF(A83="P",IF(A80="I","p i","p"),IF(A80="I","i"," ")),"") | E81: =IF(E80="O",IF(A83="P",IF(A80="I","p i","p"),IF(A80="I","i"," ")),"") -> i | F81: A | G81: J'arrête les engins et les matériels électriques
A82: A15-2-12/An5-3 | F82: B | G82: J'appelle les pompiers
A83: TC OPERATEUR | F83: C | G83: J'aménage un périmètre de sécurité
F84: D | G84: Je ne sais pas
A86: I | B86: 3-2_016 | C86: C | D86: E | E86: O | F86: En cas d'accident sur une conduite de gaz, que faut-il faire après avoir prévenu les secours ?
C87: =IF(C86="C",IF(A87="P",IF(A86="I","p i","p"),IF(A86="I","i","")),"") -> i | D87: =IF(D86="E",IF(A87="P",IF(A86="I","p i","p"),IF(A86="I","i"," ")),"") -> i | E87: =IF(E86="O",IF(A87="P",IF(A86="I","p i","p"),IF(A86="I","i"," ")),"") -> i | F87: A | G87: Aménager un périmètre de sécurité et éloigner les passants
A88: A15-2-12/An5-3 | F88: B | G88: Partir au plus vite
F89: C | G89: Colmater la fuite avec le godet de la pelle mécanique
F90: D | G90: Je ne sais pas
A92: I | B92: 3-2_017e | D92: E | F92: La nacelle que l'opérateur manœuvre entre en contact avec une ligne aérienne et il n'arrive pas à se dégager :
C93: =IF(C92="C",IF(A93="P",IF(A92="I","p i","p"),IF(A92="I","i","")),"") | D93: =IF(D92="E",IF(A93="P",IF(A92="I","p i","p"),IF(A92="I","i"," ")),"") -> i | E93: =IF(E92="O",IF(A93="P",IF(A92="I","p i","p"),IF(A92="I","i"," ")),"") | F93: A | G93: Je lui dis de descendre immédiatement de sa nacelle pour se mettre à l’abri
A94: A15-2-12/An5-3 | F94: B | G94: J'arrête le moteur et je lui dis de descendre de sa nacelle
F95: C | G95: Je lui dis d'arrêter le moteur, de rester dans sa nacelle et d'attendre les secours
F96: D | G96: Je ne sais pas
A98: I | B98: 3-2_017o | E98: O | F98: La nacelle que je manœuvre entre en contact avec une ligne aérienne et je n'arrive pas à la dégager :
C99: =IF(C98="C",IF(A99="P",IF(A98="I","p i","p"),IF(A98="I","i","")),"") | D99: =IF(D98="E",IF(A99="P",IF(A98="I","p i","p"),IF(A98="I","i"," ")),"") | E99: =IF(E98="O",IF(A99="P",IF(A98="I","p i","p"),IF(A98="I","i"," ")),"") -> i | F99: A | G99: Je descends immédiatement de ma nacelle pour me mettre à l’abri
A100: A15-2-12/An5-3 | F100: B | G100: J’arrête le moteur et je descends de ma nacelle
F101: C | G101: J’arrête le moteur, je reste dans ma nacelle et j’attends les secours
F102: D | G102: Je ne sais pas
A104: I | B104: 3-2_018e | D104: E | F104: Si une pelle mécanique touche et reste en contact avec une ligne électrique, je dis à l'opérateur :
C105: =IF(C104="C",IF(A105="P",IF(A104="I","p i","p"),IF(A104="I","i","")),"") | D105: =IF(D104="E",IF(A105="P",IF(A104="I","p i","p"),IF(A104="I","i"," ")),"") -> i | E105: =IF(E104="O",IF(A105="P",IF(A104="I","p i","p"),IF(A104="I","i"," ")),"") | F105: A | G105: D'essayer d'écarter sa pelle de la ligne et de rester dans sa cabine
A106: GT - § 3.1.4/3.1.6 | F106: B | G106: D'attendre une minute puis de descendre de l’engin
F107: C | G107: De couper le moteur et de descendre de l'engin
F108: D | G108: Je ne sais pas
A110: I | B110: 3-2_018o | E110: O | F110: Si mon godet touche et reste en contact avec une ligne électrique :
C111: =IF(C110="C",IF(A111="P",IF(A110="I","p i","p"),IF(A110="I","i","")),"") | D111: =IF(D110="E",IF(A111="P",IF(A110="I","p i","p"),IF(A110="I","i"," ")),"") | E111: =IF(E110="O",IF(A111="P",IF(A110="I","p i","p"),IF(A110="I","i"," ")),"") -> i | F111: A | G111: J’essaie d'écarter mon godet de la ligne et je reste dans ma cabine
A112: GT - § 3.1.4/3.1.6 | F112: B | G112: J’attends une minute puis je descends de l’engin
F113: C | G113: Je coupe le moteur et je descends de l'engin
F114: D | G114: Je ne sais pas
B116: 3-2_024 | D116: E | F116: Je constate une légère atteinte du revêtement d'une canalisation de transport de gaz naturel. Que faire ?
A117: R554-31II | F117: A | G117: Je recouvre la canalisation
F118: B | G118: Je procède à la réparation ponctuelle du revêtement et je poursuis les travaux de remblais
F119: C | G119: Je le signale immédiatement à l'exploitant
F120: D | G120: Je ne sais pas
...

Sheet 3.3
A1: =Bilan!B23 -> 3.3 Opérations sur chantier
C3: C | D3: E | E3: O | F3: Total
B4: Nb quest. | C4: =COUNTIF(C8:C654,C3) -> 20 | D4: =COUNTIF(D8:D654,D3) -> 34 | E4: =COUNTIF(E8:E654,E3) -> 36 | F4: =COUNTA(B8:B654) -> 46
B5: Illust. | C5: =COUNTIF(C8:C654,"i")+COUNTIF(C8:C654,"p i") -> 16 | D5: =COUNTIF(D8:D654,"i")+COUNTIF(D8:D654,"p i") -> 28 | E5: =COUNTIF(E8:E654,"i")+COUNTIF(E8:E654,"p i") -> 35 | F5: =COUNTIF(A8:A654,"I") -> 39
B6: Prio | C6: =COUNTIF(C8:C654,"p")+COUNTIF(C8:C654,"p i") -> 1 | D6: =COUNTIF(D8:D654,"p")+COUNTIF(D8:D654,"p i") -> 1 | E6: =COUNTIF(E8:E654,"p")+COUNTIF(E8:E654,"p i") -> 0 | F6: =COUNTIF(A8:A654,"P") -> 1
A9: I | B9: 3-3_001 | C9: C | D9: E | E9: O | F9: Lors d'une fuite d'une canalisation de gaz, les personnes situées à proximité sont exposées à un risque :
C10: =IF(C9="C",IF(A10="P",IF(A9="I","p i","p"),IF(A9="I","i","")),"") -> i | D10: =IF(D9="E",IF(A10="P",IF(A9="I","p i","p"),IF(A9="I","i"," ")),"") -> i | E10: =IF(E9="O",IF(A10="P",IF(A9="I","p i","p"),IF(A9="I","i"," ")),"") -> i | F10: A | G10: De brulure
A11: GT - § 3.3 | F11: B | G11: De fièvre
F12: C | G12: D'eczéma
F13: D | G13: Je ne sais pas
A15: I | B15: 3-3_003 | C15: C | D15: E | E15: O | F15: Suite à un choc sur une canalisation de gaz, je considère :
C16: =IF(C15="C",IF(A16="P",IF(A15="I","p i","p"),IF(A15="I","i","")),"") -> i | D16: =IF(D15="E",IF(A16="P",IF(A15="I","p i","p"),IF(A15="I","i"," ")),"") -> i | E16: =IF(E15="O",IF(A16="P",IF(A15="I","p i","p"),IF(A15="I","i"," ")),"") -> i | F16: A | G16: Qu'il n'y a pas de risque, s'il n'y a pas d'odeur de gaz
A17: GT - § 3.3.3.4 | F17: B | G17: Qu'il n'y a pas de risque, s'il n'y a pas de sifflement
F18: C | G18: Qu'il y a toujours un risque
F19: D | G19: Je ne sais pas
A21: I | B21: 3-3_004 | C21: C | D21: E | E21: O | F21: Dans le cas de contact avec un fil électrique nu, la personne concernée risque la mort par :
C22: =IF(C21="C",IF(A22="P",IF(A21="I","p i","p"),IF(A21="I","i","")),"") -> i | D22: =IF(D21="E",IF(A22="P",IF(A21="I","p i","p"),IF(A21="I","i"," ")),"") -> i | E22: =IF(E21="O",IF(A22="P",IF(A21="I","p i","p"),IF(A21="I","i"," ")),"") -> i | F22: A | G22: Electrocution
A23: GT - § 3.1.4 | F23: B | G23: Intoxication
F24: C | G24: Asphyxie
F25: D | G25: Je ne sais pas
A27: I | B27: 3-3_005 | C27: C | D27: E | E27: O | F27: Lors d'un contact avec un conducteur électrique isolé endommagé, la personne concernée risque :
C28: =IF(C27="C",IF(A28="P",IF(A27="I","p i","p"),IF(A27="I","i","")),"") -> i | D28: =IF(D27="E",IF(A28="P",IF(A27="I","p i","p"),IF(A27="I","i"," ")),"") -> i | E28: =IF(E27="O",IF(A28="P",IF(A27="I","p i","p"),IF(A27="I","i"," ")),"") -> i | F28: A | G28: Seulement l'électrisation
A29: GT - § 3.1.4 | F29: B | G29: Seulement une brulure
F30: C | G30: L'électrisation et une brulure
F31: D | G31: Je ne sais pas
A33: I | B33: 3-3_007 | C33: C | D33: E | E33: O | F33: Je dois dégager une canalisation, mais je ne connais pas sa profondeur. Après avoir cassé la surface dure, je peux utiliser :
C34: =IF(C33="C",IF(A34="P",IF(A33="I","p i","p"),IF(A33="I","i","")),"") -> i | D34: =IF(D33="E",IF(A34="P",IF(A33="I","p i","p"),IF(A33="I","i"," ")),"") -> i | E34: =IF(E33="O",IF(A34="P",IF(A33="I","p i","p"),IF(A33="I","i"," ")),"") -> i | F34: A | G34: Un marteau piqueur
A35: GT - § 5.3.1 et Fiche AT-TED | F35: B | G35: Un camion aspirateur muni d'un embout souple
F36: C | G36: Une mini-pelle
F37: D | G37: Je ne sais pas
A39: I | B39: 3-3_008 | C39: C | D39: E | E39: O | F39: Je dois creuser à proximité d'un ouvrage, mais je ne connais pas sa profondeur. Lequel des outils ou engins suivants est interdit ?
C40: =IF(C39="C",IF(A40="P",IF(A39="I","p i","p"),IF(A39="I","i","")),"") -> i | D40: =IF(D39="E",IF(A40="P",IF(A39="I","p i","p"),IF(A39="I","i"," ")),"") -> i | E40: =IF(E39="O",IF(A40="P",IF(A39="I","p i","p"),IF(A39="I","i"," ")),"") -> i | F40: A | G40: Pioche à air
A41: Fiche AT-RTR du GT | F41: B | G41: Camion aspirateur muni d'un embout souple
F42: C | G42: Trancheuse
F43: E | G43: Je ne sais pas
A45: I | B45: 3-3_009 | C45: C | D45: E | E45: O | F45: Je dois creuser à proximité d'un ouvrage, mais je ne connais pas sa profondeur. Après avoir cassé la surface dure, je ne dois pas utiliser :
C46: =IF(C45="C",IF(A46="P",IF(A45="I","p i","p"),IF(A45="I","i","")),"") -> i | D46: =IF(D45="E",IF(A46="P",IF(A45="I","p i","p"),IF(A45="I","i"," ")),"") -> i | E46: =IF(E45="O",IF(A46="P",IF(A45="I","p i","p"),IF(A45="I","i"," ")),"") -> i | F46: A | G46: Une lance à air
A47: Fiche AT-TED du GT | F47: B | G47: Un camion aspirateur muni d'un embout souple
F48: C | G48: Un marteau piqueur
F49: D | G49: Je ne sais pas
A51: I | B51: 3-3_010 | C51: C | D51: E | F51: Lors de l'utilisation d'un godet de pelle mécanique à proximité d'un réseau enterré, la distance de sécurité à respecter est : | H51: x
A52: GT - § 5.2.5 | C52: =IF(C51="C",IF(A52="P",IF(A51="I","p i","p"),IF(A51="I","i","")),"") -> i | D52: =IF(D51="E",IF(A52="P",IF(A51="I","p i","p"),IF(A51="I","i"," ")),"") -> i | E52: =IF(E51="O",IF(A52="P",IF(A51="I","p i","p"),IF(A51="I","i"," ")),"") | F52: A | G52: L'incertitude de l'ouvrage + l'incertitude de l'outil
F53: B | G53: L'incertitude la plus grande entre l'incertitude de l'ouvrage et l'incertitude de l'outil
F54: C | G54: Le double de l'incertitude de l'outil
F55: D | G55: Je ne sais pas
A57: I | B57: 3-3_011 | E57: O | F57: En creusant, je découvre à l'endroit où je devais poser un réseau d'eau potable, un réseau non signalé par le marquage-piquetage.
E58: =IF(E57="O",IF(A58="P",IF(A57="I","p i","p"),IF(A57="I","i"," ")),"") -> i | F58: A | G58: Je peux continuer à creuser en évitant de toucher le réseau découvert
A59: R554-28I | F59: B | G59: Je pose le nouveau réseau au-dessus du réseau découvert
F60: C | G60: J'arrête de creuser pour faire identifier le réseau découvert
F61: D | G61: Je ne sais pas
A64: I | B64: 3-3_014ce | C64: C | D64: E | F64: Pour être sûr que l'exploitant puisse couper le réseau en cas d’incident lors des travaux, l'exécutant doit :
C65: =IF(C64="C",IF(A65="P",IF(A64="I","p i","p"),IF(A64="I","i","")),"") -> i | D65: =IF(D64="E",IF(A65="P",IF(A64="I","p i","p"),IF(A64="I","i"," ")),"") -> i | E65: =IF(E64="O",IF(A65="P",IF(A64="I","p i","p"),IF(A64="I","i"," ")),"") | F65: A | G65: Veiller à ce que les dispositifs de coupure situés dans l’emprise des travaux restent accessibles pendant tous les travaux
A66: R554-31II | F66: B | G66: S’assurer régulièrement du bon fonctionnement des dispositifs de coupure
F67: C | G67: Demander à l’exploitant de vérifier régulièrement le bon fonctionnement des dispositifs de coupure
F68: D | G68: Je ne sais pas
A70: I | B70: 3-3_014eo | D70: E | E70: O | F70: Sur un chantier, je dois faire en sorte que les vannes d'arrêt restent accessibles.
C71: =IF(C70="C",IF(A71="P",IF(A70="I","p i","p"),IF(A70="I","i","")),"") | D71: =IF(D70="E",IF(A71="P",IF(A70="I","p i","p"),IF(A70="I","i"," ")),"") -> i | E71: =IF(E70="O",IF(A71="P",IF(A70="I","p i","p"),IF(A70="I","i"," ")),"") -> i | F71: A | G71: Non, c'est à l'exploitant du réseau de s'en occuper
A72: R554-31II | F72: B | G72: Seulement si mon chef me le demande
F73: C | G73: Oui, chacun doit y faire attention
F74: D | G74: Je ne sais pas
B76: 3-3_015 | C76: C | D76: E | F76: En tant qu'exécutant des travaux, je dois pendant toute la durée du chantier :
C77: =IF(C76="C",IF(A77="P",IF(A76="I","p i","p"),IF(A76="I","i","")),"") | D77: =IF(D76="E",IF(A77="P",IF(A76="I","p i","p"),IF(A76="I","i"," ")),"") | E77: =IF(E76="O",IF(A77="P",IF(A76="I","p i","p"),IF(A76="I","i"," ")),"") | F77: A | G77: Conserver un exemplaire des récépissés de DT sur le chantier
A78: R554-31II | F78: B | G78: Conserver un exemplaire des récépissés de DICT sur le chantier
F79: C | G79: Conserver un exemplaire du marché de travaux sur le chantier
F80: D | G80: Je ne sais pas
A82: I | B82: 3-3_016 | C82: C | D82: E | E82: O | F82: Je dois intervenir sur un branchement gaz enterré sous un trottoir. Pour dégager la surface dure, je peux utiliser :
C83: =IF(C82="C",IF(A83="P",IF(A82="I","p i","p"),IF(A82="I","i","")),"") -> i | D83: =IF(D82="E",IF(A83="P",IF(A82="I","p i","p"),IF(A82="I","i"," ")),"") -> i | E83: =IF(E82="O",IF(A83="P",IF(A82="I","p i","p"),IF(A82="I","i"," ")),"") -> i | F83: A | G83: Un marteau piqueur
A84: Fiche AT-BRO du GT | F84: B | G84: Une scie circulaire réglée à 30 cm de profondeur maximum
F85: C | G85: Une trancheuse réglée à 30 cm de profondeur maximum
F86: D | G86: Je ne sais pas
A88: I | B88: 3-3_017 | E88: O | F88: Lors d'un terrassement, où risque-t-on de trouver un branchement qui a été posé sans tranchée et donc sans grillage avertisseur ?
E89: =IF(E88="O",IF(A89="P",IF(A88="I","p i","p"),IF(A88="I","i"," ")),"") -> i | F89: A | G89: Uniquement sous les trottoirs
A90: GT - §3 | F90: B | G90: Seulement sous une route
F91: C | G91: C'est toujours possible
F92: D | G92: Je ne sais pas
B95: 3-3_018e | D95: E | F95: On me confie des travaux de terrassement dans une zone sans marquage-piquetage. Que dois-je faire ? | H95: x
F96: A | G96: Je récupère les récépissés de DICT et j'établis moi-même le marquage-piquetage
A97: GT - § 5.2.8 | F97: B | G97: Je vérifie l'absence de réseau sur les récépissés de DICT
F98: C | G98: Je tiens compte des affleurants et j'établis moi-même le marquage-piquetage
F99: D | G99: Je ne sais pas
A101: I | B101: 3-3_018o | E101: O | F101: Je dois creuser dans une zone sans marquage-piquetage.
C102: =IF(C101="C",IF(A102="P",IF(A101="I","p i","p"),IF(A101="I","i","")),"") | D102: =IF(D101="E",IF(A102="P",IF(A101="I","p i","p"),IF(A101="I","i"," ")),"") | E102: =IF(E101="O",IF(A102="P",IF(A101="I","p i","p"),IF(A101="I","i"," ")),"") -> i | F102: A | G102: Je me fais confirmer par mon chef qu'il n'y a pas de réseau
A103: GT - § 1 | F103: B | G103: Je peux creuser, car il n'y a pas de réseau
F104: C | G104: J'appelle les pompiers
F105: D | G105: Je ne sais pas
A107: I | B107: 3-3_019 | C107: C | D107: E | E107: O | F107: Lorsque la zone d'incertitude d'un réseau principal n'est pas indiquée par le marquage, je considère que sa largeur de part et d'autre est de :
C108: =IF(C107="C",IF(A108="P",IF(A107="I","p i","p"),IF(A107="I","i","")),"") -> i | D108: =IF(D107="E",IF(A108="P",IF(A107="I","p i","p"),IF(A107="I","i"," ")),"") -> i | E108: =IF(E107="O",IF(A108="P",IF(A107="I","p i","p"),IF(A107="I","i"," ")),"") -> i | F108: A | G108: 0,5 m
A109: R. 554-23 III | F109: B | G109: 2 m
F110: C | G110: 1,5 m
F111: D | G111: Je ne sais pas
A113: I | B113: 3-3_020 | C113: C | D113: E | E113: O | F113: A proximité d'un regard ou un coffret, le réseau : | H113: x
C114: =IF(C113="C",IF(A114="P",IF(A113="I","p i","p"),IF(A113="I","i","")),"") -> i | D114: =IF(D113="E",IF(A114="P",IF(A113="I","p i","p"),IF(A113="I","i"," ")),"") -> i | E114: =IF(E113="O",IF(A114="P",IF(A113="I","p i","p"),IF(A113="I","i"," ")),"") -> i | F114: A | G114: Peut être à une profondeur de moins de 20 cm
A115: GT - § 4.2.2.1 | F115: B | G115: Est à une profondeur d'au moins 40 cm
F116: C | G116: Est à une profondeur d'au moins 80 cm
F117: D | G117: Je ne sais pas
A119: I | B119: 3-3_021 | D119: E | E119: O | F119: Ce bloc en béton situé en bord de fouille est : | H119: photo
C120: =IF(C119="C",IF(A120="P",IF(A119="I","p i","p"),IF(A119="I","i","")),"") | D120: =IF(D119="E",IF(A120="P",IF(A119="I","p i","p"),IF(A119="I","i"," ")),"") -> i | E120: =IF(E119="O",IF(A120="P",IF(A119="I","p i","p"),IF(A119="I","i"," ")),"") -> i | F120: A | G120: Pratique pour caler des objets lourds
A121: GT - § 7.4 | F121: B | G121: Un danger de chute dans la fouille, à écarter autant que possible
F122: C | G122: Un bon marchepied pour descendre dans la fouille
F123: D | G123: Je ne sais pas
...
